Workbook
Name LR_Lane: 'Timeline Rules'!$A$6:$A$14
Name LR_Code: 'Timeline Rules'!$D$6:$D$14
Name LR_Target: 'Timeline Rules'!$E$6:$E$14
Name DH_Table: 'Timeline Rules'!$A$41:$I$57
Name DH_Head: 'Timeline Rules'!$A$40:$I$40
Name RC_Lane: 'Rate Card'!$A$5:$A$49
Name RC_Band: 'Rate Card'!$C$5:$C$49
Name RC_Transit: 'Rate Card'!$H$5:$H$49
Name SA_Lane: 'Schedule A'!$B$5:$B$145
Name SA_Date: 'Schedule A'!$J$5:$J$145
Name SA_Week: 'Schedule A'!$K$5:$K$145
Name SA_Chg: 'Schedule A'!$H$5:$H$145
Name SA_Kg: 'Schedule A'!$F$5:$F$145
Name SA_Meet: 'Schedule A'!$R$5:$R$145
Name SA_Late: 'Schedule A'!$S$5:$S$145
Name SA_Exp: 'Schedule A'!$Q$5:$Q$145
Name SB_Lane: 'Schedule B'!$B$5:$B$333
Name SB_Date: 'Schedule B'!$J$5:$J$333
Name SB_Week: 'Schedule B'!$K$5:$K$333
Name SB_Chg: 'Schedule B'!$H$5:$H$333
Name SB_Kg: 'Schedule B'!$F$5:$F$333
Name SB_Meet: 'Schedule B'!$R$5:$R$333
Name SB_Late: 'Schedule B'!$S$5:$S$333
Name SB_Exp: 'Schedule B'!$Q$5:$Q$333
Name RS_Lane: 'Optional Regional Stock'!$A$14:$A$22
Name RS_Flag: 'Optional Regional Stock'!$I$14:$I$22
Name RS_Transit: 'Optional Regional Stock'!$K$14:$K$22
Name RS_TotA: 'Optional Regional Stock'!$D$44
Name RS_TotB: 'Optional Regional Stock'!$E$44
Name RS_Loc: 'Optional Regional Stock'!$J$14:$J$22
Name RS_Rate: 'Optional Regional Stock'!$L$14:$L$22
Name RC_CostPS: 'Rate Card'!$P$5:$P$49
Name RC_Disc: 'Rate Card'!$N$5:$N$49
Name SA_From: 'Schedule A'!$U$5:$U$145
Name SA_Cost: 'Schedule A'!$Y$5:$Y$145
Name SA_M3: 'Schedule A'!$G$5:$G$145
Name SB_From: 'Schedule B'!$U$5:$U$333
Name SB_Cost: 'Schedule B'!$Y$5:$Y$333
Name SB_M3: 'Schedule B'!$G$5:$G$333
Name PP_provider_id: 'Provider Profile'!$B$6
Name PP_name: 'Provider Profile'!$B$7
Name PP_website: 'Provider Profile'!$B$8
Name PP_contact_name: 'Provider Profile'!$B$9
Name PP_contact_phone: 'Provider Profile'!$B$10
Name PP_contact_email: 'Provider Profile'!$B$11
Name PP_hq_country: 'Provider Profile'!$B$12
Name PP_quote_reference: 'Provider Profile'!$B$13
Name PP_quote_valid_until: 'Provider Profile'!$B$14
Name PP_response_date: 'Provider Profile'!$B$15
Name PP_currency: 'Provider Profile'!$B$16
Name EXPORT_TABLE: Export!$A$1:$D$737

Sheet Read Me
B1: Transport Volume Scenario: Request for Quotation
B2: FlexiTog EU B.V., Helmond, the Netherlands. Confidential. Shared for quotation purposes only, not for onward distribution.
B4: Contact name and e-mail | C4: [fill in before sending]
B5: Issue date | C5: [fill in before sending]
B6: Response deadline | C6: [fill in before sending]
B7: Rate validity requested | C7: [fill in before sending]
B9: Purpose | C9: FlexiTog EU requests rates and service information for shipments to nine destination countries, from its warehouse in Helmond or from a regional hub you propose. Your answers are compared on cost, reliability and quality.
B10: Origin | C10: Two possible origins. Default: the FlexiTog EU B.V. warehouse in Helmond, the Netherlands, with collection on working days. Alternative: your own hub or warehouse in the region, if you propose one. FlexiTog then stocks products there and directs supplier deliveries to it, and you deliver to the consignees from there (see Regional stock option). Pickup address and cut-off times are confirmed after selection.
B11: Destinations | C11: Nine lanes: Saudi Arabia, United Arab Emirates, Kuwait, Qatar, Türkiye, Morocco, Algeria, Egypt, Tunisia. Deliveries go to business addresses. Main delivery cities per lane are on the Volumes sheet. Deliveries to other cities in the same country follow your standard zone or remote-area pricing.
B12: Goods | C12: Cold-store workwear (jackets, trousers, coveralls, baselayers), gloves, footwear, headwear and small accessories in cartons. Occasional crated stainless steel cabinets of around 70 kg. Non-dangerous goods, no temperature control, stackable.
B13: Incoterm | C13: DAP, named consignee address (Incoterms 2020). FlexiTog EU pays transport to the door and export clearance in the Netherlands. The consignee clears import and pays import duty and VAT. Please state whether you offer import brokerage on the consignee's account and a DDP option per country.
B14: Service requirement | C14: Target door-to-door delivery after collection, in destination working days: GCC (Saudi Arabia, UAE, Kuwait, Qatar) 48 hours, next day preferred. Türkiye and Morocco 3 days. Tunisia and Egypt 4 days. Algeria 5 days. Please state your realistic transit time per lane and weight band. If a target needs local stock, please also complete the Optional Regional Stock sheet.
B15: Volume scenarios | C15: Two annual volume levels, Scenario A and Scenario B. Please quote both. Volumes are estimates for quotation and do not form a volume commitment.
B16: Volume basis | C16: One order equals one shipment. Weights and volumes are estimates. Chargeable kg uses the 1:6000 volumetric divisor. The peak month carries 1.5 times the average month.
... B23: Legend | C23: Yellow cells: your input. White cells: FlexiTog EU data or calculations, please leave unchanged.

Sheet Provider Profile
A1: Provider profile
A2: Please complete every yellow cell. Your company details, provider type, services, coverage per country and certifications.
A4: 1. Company details
A5: Field | B5: Your answer | C5: Note
A6: Provider ID (filled in by FlexiTog) | C6: Do not change
A7: Company name | C7: Required
A8: Website
A9: Contact person | C9: Person responsible for this quote
A10: Contact phone | C10: Include country code
A11: Contact e-mail
A12: Head office country
A13: Your quote reference
A14: Quote valid until | C14: Date
A15: Response date | C15: Date
A16: Quote currency | B16: EUR | C16: EUR, fixed
A19: 2. Provider type (all that apply)
A20: Type | B20: Yes / No | C20: Note
A21: Freight forwarder
A22: 3PL / contract logistics
A23: Carrier (own fleet)
A24: Courier / express
A25: Customs broker
A26: Distributor
A27: 4PL / lead logistics provider
A29: 3. Services offered
A30: Service | B30: Yes / No | C30: Note
A31: Road FTL
A32: Road groupage (LTL)
A33: Sea FCL
A34: Sea LCL
A35: Air freight
A36: Express / courier
A37: Export customs clearance (NL)
A38: Import customs brokerage
A39: DDP service
A40: Warehousing
A41: Cross-docking
A42: Last-mile delivery
... A51: 4. Coverage per destination
A52: Lane | B52: Country | C52: Region | D52: Presence | E52: Agent or partner name | F52: Import brokerage offered | G52: DDP offered
A53: L01 | B53: Saudi Arabia | C53: Gulf/GCC
A54: L02 | B54: United Arab Emirates | C54: Gulf/GCC
A55: L03 | B55: Kuwait | C55: Gulf/GCC
A56: L04 | B56: Qatar | C56: Gulf/GCC
A57: L05 | B57: Türkiye | C57: Türkiye
A58: L06 | B58: Morocco | C58: North Africa
A59: L07 | B59: Algeria | C59: North Africa
A60: L08 | B60: Egypt | C60: North Africa
A61: L09 | B61: Tunisia | C61: North Africa
A63: 5. Certifications
A64: Certification | B64: Yes / No | C64: Note
A65: ISO 9001
A66: ISO 14001
A67: ISO 45001
A68: AEO (authorised economic operator)
A69: TAPA
A70: IATA cargo agent
A71: Other certifications

Sheet Volumes
A1: Annual volumes per lane
A2: Default origin: Helmond, NL. Lanes you choose to serve from your own regional hub use that hub as origin (Optional Regional Stock sheet). Estimates for quotation, not a volume commitment. Shipment-level dates are on the Schedule sheets.
A4: Scenario A
A5: Lane | B5: Destination country | C5: Main delivery cities | D5: Annual shipments | E5: Gross kg | F5: m3 | G5: Chargeable kg | H5: Avg kg per shipment | I5: Peak month shipments
A6: L01 | B6: Saudi Arabia | C6: Jeddah, Riyadh | D6: 50 | E6: 15486 | F6: 100.3 | G6: 16716 | H6: 310 | I6: ='Timeline Summary'!P6
A7: L02 | B7: United Arab Emirates | C7: Dubai | D7: 36 | E7: 1293 | F7: 8.4 | G7: 1395 | H7: 36 | I7: ='Timeline Summary'!P7
A8: L03 | B8: Kuwait | C8: Kuwait City | D8: 12 | E8: 3983 | F8: 25.8 | G8: 4300 | H8: 332 | I8: ='Timeline Summary'!P8
A9: L04 | B9: Qatar | C9: Doha | D9: 10 | E9: 343 | F9: 2.2 | G9: 371 | H9: 34 | I9: ='Timeline Summary'!P9
A10: L05 | B10: Türkiye | C10: Istanbul | D10: 16 | E10: 1819 | F10: 11.8 | G10: 1963 | H10: 114 | I10: ='Timeline Summary'!P10
A11: L06 | B11: Morocco | C11: Casablanca area, Rabat | D11: 6 | E11: 1278 | F11: 8.3 | G11: 1379 | H11: 213 | I11: ='Timeline Summary'!P11
A12: L07 | B12: Algeria | C12: Algiers | D12: 4 | E12: 328 | F12: 2.1 | G12: 354 | H12: 82 | I12: ='Timeline Summary'!P12
A13: L08 | B13: Egypt | C13: Cairo area | D13: 6 | E13: 1278 | F13: 8.3 | G13: 1379 | H13: 213 | I13: ='Timeline Summary'!P13
A14: L09 | B14: Tunisia | C14: Sousse | D14: 1 | E14: 8 | F14: 0.1 | G14: 8 | H14: 8 | I14: ='Timeline Summary'!P14
A15: Total | D15: =SUM(D6:D14) | E15: =SUM(E6:E14) | F15: =SUM(F6:F14) | G15: =SUM(G6:G14) | H15: =IFERROR(E15/D15,0) | I15: ='Timeline Summary'!P15
A18: Scenario B
A19: Lane | B19: Destination country | C19: Main delivery cities | D19: Annual shipments | E19: Gross kg | F19: m3 | G19: Chargeable kg | H19: Avg kg per shipment | I19: Peak month shipments
A20: L01 | B20: Saudi Arabia | C20: Jeddah, Riyadh | D20: 117 | E20: 37169 | F20: 240.7 | G20: 40121 | H20: 318 | I20: ='Timeline Summary'!P20
A21: L02 | B21: United Arab Emirates | C21: Dubai | D21: 84 | E21: 2932 | F21: 19 | G21: 3165 | H21: 35 | I21: ='Timeline Summary'!P21
A22: L03 | B22: Kuwait | C22: Kuwait City | D22: 29 | E22: 9698 | F22: 62.8 | G22: 10468 | H22: 334 | I22: ='Timeline Summary'!P22
A23: L04 | B23: Qatar | C23: Doha | D23: 23 | E23: 798 | F23: 5.2 | G23: 862 | H23: 35 | I23: ='Timeline Summary'!P23
A24: L05 | B24: Türkiye | C24: Istanbul | D24: 37 | E24: 4226 | F24: 27.4 | G24: 4562 | H24: 114 | I24: ='Timeline Summary'!P24
A25: L06 | B25: Morocco | C25: Casablanca area, Rabat | D25: 13 | E25: 1882 | F25: 12.2 | G25: 2032 | H25: 145 | I25: ='Timeline Summary'!P25
A26: L07 | B26: Algeria | C26: Algiers | D26: 9 | E26: 1554 | F26: 10.1 | G26: 1677 | H26: 173 | I26: ='Timeline Summary'!P26
A27: L08 | B27: Egypt | C27: Cairo area | D27: 13 | E27: 1882 | F27: 12.2 | G27: 2032 | H27: 145 | I27: ='Timeline Summary'!P27
A28: L09 | B28: Tunisia | C28: Sousse | D28: 4 | E28: 328 | F28: 2.1 | G28: 354 | H28: 82 | I28: ='Timeline Summary'!P28
A29: Total | D29: =SUM(D20:D28) | E29: =SUM(E20:E28) | F29: =SUM(F20:F28) | G29: =SUM(G20:G28) | H29: =IFERROR(E29/D29,0) | I29: ='Timeline Summary'!P29
A32: Annual shipments per weight band
A33: Lane | B33: Destination country | C33: Scenario A B1 0 to 30 kg | D33: Scenario A B2 30 to 100 kg | E33: Scenario A B3 100 to 500 kg | F33: Scenario A B4 500 to 2,000 kg | G33: Scenario A B5 over 2,000 kg | H33: Scenario B B1 0 to 30 kg | I33: Scenario B B2 30 to 100 kg | J33: Scenario B B3 100 to 500 kg | K33: Scenario B B4 500 to 2,000 kg | L33: Scenario B B5 over 2,000 kg
A34: L01 | B34: Saudi Arabia | C34: 22 | D34: 8 | E34: 10 | F34: 8 | G34: 2 | H34: 51 | I34: 19 | J34: 23 | K34: 19 | L34: 5
A35: L02 | B35: United Arab Emirates | C35: 32 | D35: 0 | E35: 4 | F35: 0 | G35: 0 | H35: 75 | I35: 0 | J35: 9 | K35: 0 | L35: 0
A36: L03 | B36: Kuwait | C36: 2 | D36: 0 | E36: 8 | F36: 2 | G36: 0 | H36: 5 | I36: 0 | J36: 19 | K36: 5 | L36: 0
A37: L04 | B37: Qatar | C37: 4 | D37: 6 | E37: 0 | F37: 0 | G37: 0 | H37: 9 | I37: 14 | J37: 0 | K37: 0 | L37: 0
A38: L05 | B38: Türkiye | C38: 6 | D38: 4 | E38: 6 | F38: 0 | G38: 0 | H38: 14 | I38: 9 | J38: 14 | K38: 0 | L38: 0
A39: L06 | B39: Morocco | C39: 3 | D39: 1 | E39: 1 | F39: 1 | G39: 0 | H39: 7 | I39: 2 | J39: 3 | K39: 1 | L39: 0
A40: L07 | B40: Algeria | C40: 2 | D40: 1 | E40: 1 | F40: 0 | G40: 0 | H40: 5 | I40: 1 | J40: 2 | K40: 1 | L40: 0
A41: L08 | B41: Egypt | C41: 3 | D41: 1 | E41: 1 | F41: 1 | G41: 0 | H41: 7 | I41: 2 | J41: 3 | K41: 1 | L41: 0
A42: L09 | B42: Tunisia | C42: 1 | D42: 0 | E42: 0 | F42: 0 | G42: 0 | H42: 2 | I42: 1 | J42: 1 | K42: 0 | L42: 0
A43: Total | C43: =SUM(C34:C42) | D43: =SUM(D34:D42) | E43: =SUM(E34:E42) | F43: =SUM(F34:F42) | G43: =SUM(G34:G42) | H43: =SUM(H34:H42) | I43: =SUM(I34:I42) | J43: =SUM(J34:J42) | ... L43: =SUM(L34:L42)
A46: Average shipment size per weight band
A47: Weight band | B47: Avg gross kg per shipment | C47: Avg chargeable kg per shipment | D47: Expected mode
A48: B1 0 to 30 kg | B48: 8 | C48: 8 | D48: Express parcel
A49: B2 30 to 100 kg | B49: 52 | C49: 56 | D49: Express heavy or air
A50: B3 100 to 500 kg | B50: 261 | C50: 281 | D50: Air freight
A51: B4 500 to 2,000 kg | B51: 941 | C51: 1016 | D51: Air or groupage road/sea
A52: B5 over 2,000 kg | B52: 2380 | C52: 2569 | D52: FTL road or sea FCL/LCL

Sheet Timeline Rules
A1: Timeline rules behind the shipment schedules
A2: Holiday dates for Islamic holidays are estimates and depend on moon sighting. Please correct any date you know to be different.
A4: Lane rules | K4: Monthly order profile (share of annual shipments)
A5: Lane | B5: Destination | C5: Destination weekend | D5: Weekend code (Excel) | E5: Target delivery (working days after pickup) | F5: Target | K5: Month | L5: Weight (1.0 = average month) | M5: Reason
A6: L01 | B6: Saudi Arabia | C6: Fri-Sat | D6: 7 | E6: 2 | F6: 48 hours, next day preferred | K6: 46388 | L6: 1 | M6: Normal month
A7: L02 | B7: United Arab Emirates | C7: Sat-Sun | D7: 1 | E7: 2 | F7: 48 hours, next day preferred | K7: 46419 | L7: 0.9 | M7: Ramadan starts (est. 8 Feb)
A8: L03 | B8: Kuwait | C8: Fri-Sat | D8: 7 | E8: 2 | F8: 48 hours, next day preferred | K8: 46447 | L8: 0.8 | M8: Ramadan and Eid al-Fitr (est. 9 to 11 Mar)
A9: L04 | B9: Qatar | C9: Fri-Sat | D9: 7 | E9: 2 | F9: 48 hours, next day preferred | K9: 46478 | L9: 1.1 | M9: Post-Ramadan restocking
A10: L05 | B10: Türkiye | C10: Sat-Sun | D10: 1 | E10: 3 | F10: 3 working days | K10: 46508 | L10: 0.9 | M10: Eid al-Adha (est. 15 to 18 May)
A11: L06 | B11: Morocco | C11: Sat-Sun | D11: 1 | E11: 3 | F11: 3 working days | K11: 46539 | L11: 1 | M11: Normal month
A12: L07 | B12: Algeria | C12: Fri-Sat | D12: 7 | E12: 5 | F12: 5 working days | K12: 46569 | L12: 0.8 | M12: Summer slowdown, GCC heat season
A13: L08 | B13: Egypt | C13: Fri-Sat | D13: 7 | E13: 4 | F13: 4 working days | K13: 46600 | L13: 0.8 | M13: Summer slowdown, European holidays
A14: L09 | B14: Tunisia | C14: Sat-Sun | D14: 1 | E14: 4 | F14: 4 working days | K14: 46631 | L14: 1.2 | M14: Season start, restocking
A15: GCC: priority market, next day preferred. Türkiye and Morocco: short routes, road or air. Tunisia and Egypt: longer clearance. Algeria: strictest import controls. | K15: 46661 | L15: 1.5 | M15: Peak month
A16: Order and pickup rules | K16: 46692 | L16: 1.2 | M16: Pre year-end orders
A17: Order release | B17: Orders are released on Helmond working days (Monday to Friday, excluding the Dutch holidays below). | K17: 46722 | L17: 0.8 | M17: Year-end holidays
A18: Planned pickup | B18: Same day as order release. Assumes release before your pickup cut-off. Please state your cut-off in question R3. | K18: Average | L18: =AVERAGE(L6:L17)
A19: Target delivery date | B19: Pickup date plus the target working days, counted in destination working days (skipping the destination weekend and holidays).
A20: Expected delivery date | B20: Pickup date plus your quoted transit days from the Rate Card, counted the same way. Overwrite per shipment in the yellow column where you know better.
A21: Weights | B21: Gross kg per shipment is an estimate. m3 = gross kg x 0.00648. Chargeable kg = gross kg x 1.0794 (1:6000 rule).
A22: Cartons | B22: Estimated with a 60 x 40 x 40 cm carton (0.096 m3).
A25: Helmond non-working days
A26: Date | B26: Holiday
A27: 46388 | B27: New Year's Day
A28: 46475 | B28: Easter Monday
A29: 46504 | B29: King's Day
A30: 46513 | B30: Ascension Day
A31: 46524 | B31: Whit Monday
A39: Destination non-delivery days (indicative, one column per lane)
A40: L01 Saudi Arabia | B40: L02 United Arab Emirates | C40: L03 Kuwait | D40: L04 Qatar | E40: L05 Türkiye | F40: L06 Morocco | G40: L07 Algeria | H40: L08 Egypt | I40: L09 Tunisia
A41: 46440 | B41: 46388 | C41: 46388 | D41: 46427 | E41: 46388 | F41: 46388 | G41: 46388 | H41: 46394 | I41: 46388
A42: 46455 | B42: 46455 | C42: 46443 | D42: 46455 | E42: 46455 | F42: 46398 | G42: 46399 | H42: 46412 | I42: 46401
A43: 46456 | B43: 46456 | C43: 46444 | D43: 46456 | E43: 46456 | F43: 46401 | G43: 46455 | H43: 46455 | I43: 46455
A44: 46457 | B44: 46457 | C44: 46455 | D44: 46457 | E44: 46457 | F44: 46455 | G44: 46456 | H44: 46456 | I44: 46456
A45: 46458 | B45: 46522 | C45: 46456 | D45: 46522 | E45: 46500 | F45: 46456 | G45: 46508 | H45: 46457 | I45: 46466
A46: 46522 | B46: 46523 | C46: 46457 | D46: 46523 | E46: 46508 | F46: 46508 | G46: 46523 | H46: 46502 | I46: 46486
A47: 46523 | B47: 46524 | C47: 46522 | D47: 46524 | E47: 46523 | F47: 46523 | G47: 46524 | H47: 46508 | I47: 46508
A48: 46524 | B48: 46525 | C48: 46523 | D48: 46525 | E48: 46524 | F48: 46524 | G48: 46544 | H48: 46510 | I48: 46523
A49: 46525 | B49: 46544 | C49: 46524 | D49: 46739 | E49: 46525 | F49: 46544 | G49: 46573 | H49: 46522 | I49: 46524
A50: 46653 | B50: 46613 | C50: 46525 | E50: 46526 | F50: 46598 | G50: 46613 | H50: 46523 | I50: 46544
B51: 46723 | C51: 46544 | E51: 46583 | F51: 46613 | G51: 46692 | H51: 46524 | I51: 46593
B52: 46724 | C52: 46613 | E52: 46629 | F52: 46619 | H52: 46525 | I52: 46612
E53: 46689 | F53: 46620 | H53: 46544 | I53: 46613
F54: 46697 | H54: 46568 | I54: 46675
F55: 46709 | H55: 46591 | I55: 46738
H56: 46613
H57: 46666
A58: Covers Eid al-Fitr (est. 9 to 11 Mar), Arafah and Eid al-Adha (est. 15 to 18 May), Islamic New Year, the Prophet's Birthday where observed, and fixed national days.

Sheet Schedule A
A1: Scenario A: shipment schedule
A2: One row per shipment. Default origin is Helmond. Where another origin is possible or better (your hub W1 to W3, a supplier, another hub), set it per shipment in the yellow origin columns. Expected delivery and shipment cost then follow that origin.
A4: Shipment ID | B4: Lane | C4: Destination | D4: Delivery city | E4: Weight band | F4: Gross kg | G4: m3 (est.) | H4: Chargeable kg | I4: Cartons (est.) | J4: Order release date | K4: Week starting | L4: Planned pickup | M4: Target (working days) | N4: Target delivery date | O4: Quoted transit days | P4: Your expected delivery date (optional) | Q4: Expected delivery date | R4: Meets target | S4: Days late | T4: Comment | U4: Ships from | V4: Proposed origin (optional) | W4: Transit days from proposed origin (optional) | X4: Cost per shipment from proposed origin (EUR, optional) | Y4: Shipment cost (EUR)
A5: A-001 | B5: L04 | C5: Qatar | D5: Doha | E5: B1 0 to 30 kg | F5: 2.6 | G5: =F5*0.006477 | H5: =F5*1.079436 | I5: =MAX(1,ROUNDUP(G5/0.096,0)) | J5: 46391 | K5: =J5-WEEKDAY(J5,2)+1 | L5: =J5 | M5: =INDEX(LR_Target,MATCH(B5,LR_Lane,0)) | N5: =WORKDAY.INTL(L5,M5,INDEX(LR_Code,MATCH(B5,LR_Lane,0)),INDEX(DH_Table,0,MATCH(B5&"*",DH_Head,0))) | O5: =IF(W5<>"",W5,IF(U5="Helmond",IF(COUNTIFS(RC_Lane,B5,RC_Band,E5,RC_Transit,"<>")=0,"",SUMIFS(RC_Transit,RC_Lane,B5,RC_Band,E5)),IF(U5="Other","",IF(INDEX(RS_Transit,MATCH(B5,RS_Lane,0))="","",INDEX(RS_Transit,MATCH(B5,RS_Lane,0)))))) | Q5: =IF(P5<>"",P5,IF(O5="","",WORKDAY.INTL(L5,ROUNDUP(O5,0),INDEX(LR_Code,MATCH(B5,LR_Lane,0)),INDEX(DH_Table,0,MATCH(B5&"*",DH_Head,0))))) | R5: =IF(Q5="","",IF(Q5<=N5,"Yes","No")) | S5: =IF(Q5="","",IF(Q5<=N5,0,NETWORKDAYS.INTL(N5,Q5,INDEX(LR_Code,MATCH(B5,LR_Lane,0)),INDEX(DH_Table,0,MATCH(B5&"*",DH_Head,0)))-1)) | U5: =IF(V5<>"",V5,IF(IFERROR(INDEX(RS_Flag,MATCH(B5,RS_Lane,0)),"")="Yes",IF(IFERROR(INDEX(RS_Loc,MATCH(B5,RS_Lane,0)),"")="","Regional stock",IFERROR(INDEX(RS_Loc,MATCH(B5,RS_Lane,0)),"")),"Helmond")) | Y5: =IF(X5<>"",X5,IF(U5="Helmond",IF(COUNTIFS(RC_Lane,B5,RC_Band,E5,RC_CostPS,">0")=0,"",SUMIFS(RC_CostPS,RC_Lane,B5,RC_Band,E5)),IF(U5="Other","",IF(INDEX(RS_Rate,MATCH(B5,RS_Lane,0))="","",INDEX(RS_Rate,MATCH(B5,RS_Lane,0))))))
A6: A-002 | B6: L01 | C6: Saudi Arabia | D6: Riyadh | E6: B3 100 to 500 kg | F6: 279.6 | G6: =F6*0.006477 | H6: =F6*1.079436 | I6: =MAX(1,ROUNDUP(G6/0.096,0)) | J6: 46392 | K6: =J6-WEEKDAY(J6,2)+1 | L6: =J6 | M6: =INDEX(LR_Target,MATCH(B6,LR_Lane,0)) | N6: =WORKDAY.INTL(L6,M6,INDEX(LR_Code,MATCH(B6,LR_Lane,0)),INDEX(DH_Table,0,MATCH(B6&"*",DH_Head,0))) | O6: =IF(W6<>"",W6,IF(U6="Helmond",IF(COUNTIFS(RC_Lane,B6,RC_Band,E6,RC_Transit,"<>")=0,"",SUMIFS(RC_Transit,RC_Lane,B6,RC_Band,E6)),IF(U6="Other","",IF(INDEX(RS_Transit,MATCH(B6,RS_Lane,0))="","",INDEX(RS_Transit,MATCH(B6,RS_Lane,0)))))) | Q6: =IF(P6<>"",P6,IF(O6="","",WORKDAY.INTL(L6,ROUNDUP(O6,0),INDEX(LR_Code,MATCH(B6,LR_Lane,0)),INDEX(DH_Table,0,MATCH(B6&"*",DH_Head,0))))) | R6: =IF(Q6="","",IF(Q6<=N6,"Yes","No")) | S6: =IF(Q6="","",IF(Q6<=N6,0,NETWORKDAYS.INTL(N6,Q6,INDEX(LR_Code,MATCH(B6,LR_Lane,0)),INDEX(DH_Table,0,MATCH(B6&"*",DH_Head,0)))-1)) | U6: =IF(V6<>"",V6,IF(IFERROR(INDEX(RS_Flag,MATCH(B6,RS_Lane,0)),"")="Yes",IF(IFERROR(INDEX(RS_Loc,MATCH(B6,RS_Lane,0)),"")="","Regional stock",IFERROR(INDEX(RS_Loc,MATCH(B6,RS_Lane,0)),"")),"Helmond")) | Y6: =IF(X6<>"",X6,IF(U6="Helmond",IF(COUNTIFS(RC_Lane,B6,RC_Band,E6,RC_CostPS,">0")=0,"",SUMIFS(RC_CostPS,RC_Lane,B6,RC_Band,E6)),IF(U6="Other","",IF(INDEX(RS_Rate,MATCH(B6,RS_Lane,0))="","",INDEX(RS_Rate,MATCH(B6,RS_Lane,0))))))
A7: A-003 | B7: L01 | C7: Saudi Arabia | D7: Jeddah | E7: B1 0 to 30 kg | F7: 11.1 | G7: =F7*0.006477 | H7: =F7*1.079436 | I7: =MAX(1,ROUNDUP(G7/0.096,0)) | J7: 46395 | K7: =J7-WEEKDAY(J7,2)+1 | L7: =J7 | M7: =INDEX(LR_Target,MATCH(B7,LR_Lane,0)) | N7: =WORKDAY.INTL(L7,M7,INDEX(LR_Code,MATCH(B7,LR_Lane,0)),INDEX(DH_Table,0,MATCH(B7&"*",DH_Head,0))) | O7: =IF(W7<>"",W7,IF(U7="Helmond",IF(COUNTIFS(RC_Lane,B7,RC_Band,E7,RC_Transit,"<>")=0,"",SUMIFS(RC_Transit,RC_Lane,B7,RC_Band,E7)),IF(U7="Other","",IF(INDEX(RS_Transit,MATCH(B7,RS_Lane,0))="","",INDEX(RS_Transit,MATCH(B7,RS_Lane,0)))))) | Q7: =IF(P7<>"",P7,IF(O7="","",WORKDAY.INTL(L7,ROUNDUP(O7,0),INDEX(LR_Code,MATCH(B7,LR_Lane,0)),INDEX(DH_Table,0,MATCH(B7&"*",DH_Head,0))))) | R7: =IF(Q7="","",IF(Q7<=N7,"Yes","No")) | S7: =IF(Q7="","",IF(Q7<=N7,0,NETWORKDAYS.INTL(N7,Q7,INDEX(LR_Code,MATCH(B7,LR_Lane,0)),INDEX(DH_Table,0,MATCH(B7&"*",DH_Head,0)))-1)) | U7: =IF(V7<>"",V7,IF(IFERROR(INDEX(RS_Flag,MATCH(B7,RS_Lane,0)),"")="Yes",IF(IFERROR(INDEX(RS_Loc,MATCH(B7,RS_Lane,0)),"")="","Regional stock",IFERROR(INDEX(RS_Loc,MATCH(B7,RS_Lane,0)),"")),"Helmond")) | Y7: =IF(X7<>"",X7,IF(U7="Helmond",IF(COUNTIFS(RC_Lane,B7,RC_Band,E7,RC_CostPS,">0")=0,"",SUMIFS(RC_CostPS,RC_Lane,B7,RC_Band,E7)),IF(U7="Other","",IF(INDEX(RS_Rate,MATCH(B7,RS_Lane,0))="","",INDEX(RS_Rate,MATCH(B7,RS_Lane,0))))))
A8: A-004 | B8: L01 | C8: Saudi Arabia | D8: Riyadh | E8: B3 100 to 500 kg | F8: 270.6 | G8: =F8*0.006477 | H8: =F8*1.079436 | I8: =MAX(1,ROUNDUP(G8/0.096,0)) | J8: 46395 | K8: =J8-WEEKDAY(J8,2)+1 | L8: =J8 | M8: =INDEX(LR_Target,MATCH(B8,LR_Lane,0)) | N8: =WORKDAY.INTL(L8,M8,INDEX(LR_Code,MATCH(B8,LR_Lane,0)),INDEX(DH_Table,0,MATCH(B8&"*",DH_Head,0))) | O8: =IF(W8<>"",W8,IF(U8="Helmond",IF(COUNTIFS(RC_Lane,B8,RC_Band,E8,RC_Transit,"<>")=0,"",SUMIFS(RC_Transit,RC_Lane,B8,RC_Band,E8)),IF(U8="Other","",IF(INDEX(RS_Transit,MATCH(B8,RS_Lane,0))="","",INDEX(RS_Transit,MATCH(B8,RS_Lane,0)))))) | Q8: =IF(P8<>"",P8,IF(O8="","",WORKDAY.INTL(L8,ROUNDUP(O8,0),INDEX(LR_Code,MATCH(B8,LR_Lane,0)),INDEX(DH_Table,0,MATCH(B8&"*",DH_Head,0))))) | R8: =IF(Q8="","",IF(Q8<=N8,"Yes","No")) | S8: =IF(Q8="","",IF(Q8<=N8,0,NETWORKDAYS.INTL(N8,Q8,INDEX(LR_Code,MATCH(B8,LR_Lane,0)),INDEX(DH_Table,0,MATCH(B8&"*",DH_Head,0)))-1)) | U8: =IF(V8<>"",V8,IF(IFERROR(INDEX(RS_Flag,MATCH(B8,RS_Lane,0)),"")="Yes",IF(IFERROR(INDEX(RS_Loc,MATCH(B8,RS_Lane,0)),"")="","Regional stock",IFERROR(INDEX(RS_Loc,MATCH(B8,RS_Lane,0)),"")),"Helmond")) | Y8: =IF(X8<>"",X8,IF(U8="Helmond",IF(COUNTIFS(RC_Lane,B8,RC_Band,E8,RC_CostPS,">0")=0,"",SUMIFS(RC_CostPS,RC_Lane,B8,RC_Band,E8)),IF(U8="Other","",IF(INDEX(RS_Rate,MATCH(B8,RS_Lane,0))="","",INDEX(RS_Rate,MATCH(B8,RS_Lane,0))))))
A9: A-005 | B9: L02 | C9: United Arab Emirates | D9: Dubai | E9: B1 0 to 30 kg | F9: 10.9 | G9: =F9*0.006477 | H9: =F9*1.079436 | I9: =MAX(1,ROUNDUP(G9/0.096,0)) | J9: 46398 | K9: =J9-WEEKDAY(J9,2)+1 | L9: =J9 | M9: =INDEX(LR_Target,MATCH(B9,LR_Lane,0)) | N9: =WORKDAY.INTL(L9,M9,INDEX(LR_Code,MATCH(B9,LR_Lane,0)),INDEX(DH_Table,0,MATCH(B9&"*",DH_Head,0))) | O9: =IF(W9<>"",W9,IF(U9="Helmond",IF(COUNTIFS(RC_Lane,B9,RC_Band,E9,RC_Transit,"<>")=0,"",SUMIFS(RC_Transit,RC_Lane,B9,RC_Band,E9)),IF(U9="Other","",IF(INDEX(RS_Transit,MATCH(B9,RS_Lane,0))="","",INDEX(RS_Transit,MATCH(B9,RS_Lane,0)))))) | Q9: =IF(P9<>"",P9,IF(O9="","",WORKDAY.INTL(L9,ROUNDUP(O9,0),INDEX(LR_Code,MATCH(B9,LR_Lane,0)),INDEX(DH_Table,0,MATCH(B9&"*",DH_Head,0))))) | R9: =IF(Q9="","",IF(Q9<=N9,"Yes","No")) | S9: =IF(Q9="","",IF(Q9<=N9,0,NETWORKDAYS.INTL(N9,Q9,INDEX(LR_Code,MATCH(B9,LR_Lane,0)),INDEX(DH_Table,0,MATCH(B9&"*",DH_Head,0)))-1)) | U9: =IF(V9<>"",V9,IF(IFERROR(INDEX(RS_Flag,MATCH(B9,RS_Lane,0)),"")="Yes",IF(IFERROR(INDEX(RS_Loc,MATCH(B9,RS_Lane,0)),"")="","Regional stock",IFERROR(INDEX(RS_Loc,MATCH(B9,RS_Lane,0)),"")),"Helmond")) | Y9: =IF(X9<>"",X9,IF(U9="Helmond",IF(COUNTIFS(RC_Lane,B9,RC_Band,E9,RC_CostPS,">0")=0,"",SUMIFS(RC_CostPS,RC_Lane,B9,RC_Band,E9)),IF(U9="Other","",IF(INDEX(RS_Rate,MATCH(B9,RS_Lane,0))="","",INDEX(RS_Rate,MATCH(B9,RS_Lane,0))))))
A10: A-006 | B10: L02 | C10: United Arab Emirates | D10: Dubai | E10: B1 0 to 30 kg | F10: 14.1 | G10: =F10*0.006477 | H10: =F10*1.079436 | I10: =MAX(1,ROUNDUP(G10/0.096,0)) | J10: 46398 | K10: =J10-WEEKDAY(J10,2)+1 | L10: =J10 | M10: =INDEX(LR_Target,MATCH(B10,LR_Lane,0)) | N10: =WORKDAY.INTL(L10,M10,INDEX(LR_Code,MATCH(B10,LR_Lane,0)),INDEX(DH_Table,0,MATCH(B10&"*",DH_Head,0))) | O10: =IF(W10<>"",W10,IF(U10="Helmond",IF(COUNTIFS(RC_Lane,B10,RC_Band,E10,RC_Transit,"<>")=0,"",SUMIFS(RC_Transit,RC_Lane,B10,RC_Band,E10)),IF(U10="Other","",IF(INDEX(RS_Transit,MATCH(B10,RS_Lane,0))="","",INDEX(RS_Transit,MATCH(B10,RS_Lane,0)))))) | Q10: =IF(P10<>"",P10,IF(O10="","",WORKDAY.INTL(L10,ROUNDUP(O10,0),INDEX(LR_Code,MATCH(B10,LR_Lane,0)),INDEX(DH_Table,0,MATCH(B10&"*",DH_Head,0))))) | R10: =IF(Q10="","",IF(Q10<=N10,"Yes","No")) | S10: =IF(Q10="","",IF(Q10<=N10,0,NETWORKDAYS.INTL(N10,Q10,INDEX(LR_Code,MATCH(B10,LR_Lane,0)),INDEX(DH_Table,0,MATCH(B10&"*",DH_Head,0)))-1)) | U10: =IF(V10<>"",V10,IF(IFERROR(INDEX(RS_Flag,MATCH(B10,RS_Lane,0)),"")="Yes",IF(IFERROR(INDEX(RS_Loc,MATCH(B10,RS_Lane,0)),"")="","Regional stock",IFERROR(INDEX(RS_Loc,MATCH(B10,RS_Lane,0)),"")),"Helmond")) | Y10: =IF(X10<>"",X10,IF(U10="Helmond",IF(COUNTIFS(RC_Lane,B10,RC_Band,E10,RC_CostPS,">0")=0,"",SUMIFS(RC_CostPS,RC_Lane,B10,RC_Band,E10)),IF(U10="Other","",IF(INDEX(RS_Rate,MATCH(B10,RS_Lane,0))="","",INDEX(RS_Rate,MATCH(B10,RS_Lane,0))))))
A11: A-007 | B11: L05 | C11: Türkiye | D11: Istanbul | E11: B3 100 to 500 kg | F11: 376.7 | G11: =F11*0.006477 | H11: =F11*1.079436 | I11: =MAX(1,ROUNDUP(G11/0.096,0)) | J11: 46398 | K11: =J11-WEEKDAY(J11,2)+1 | L11: =J11 | M11: =INDEX(LR_Target,MATCH(B11,LR_Lane,0)) | N11: =WORKDAY.INTL(L11,M11,INDEX(LR_Code,MATCH(B11,LR_Lane,0)),INDEX(DH_Table,0,MATCH(B11&"*",DH_Head,0))) | O11: =IF(W11<>"",W11,IF(U11="Helmond",IF(COUNTIFS(RC_Lane,B11,RC_Band,E11,RC_Transit,"<>")=0,"",SUMIFS(RC_Transit,RC_Lane,B11,RC_Band,E11)),IF(U11="Other","",IF(INDEX(RS_Transit,MATCH(B11,RS_Lane,0))="","",INDEX(RS_Transit,MATCH(B11,RS_Lane,0)))))) | Q11: =IF(P11<>"",P11,IF(O11="","",WORKDAY.INTL(L11,ROUNDUP(O11,0),INDEX(LR_Code,MATCH(B11,LR_Lane,0)),INDEX(DH_Table,0,MATCH(B11&"*",DH_Head,0))))) | R11: =IF(Q11="","",IF(Q11<=N11,"Yes","No")) | S11: =IF(Q11="","",IF(Q11<=N11,0,NETWORKDAYS.INTL(N11,Q11,INDEX(LR_Code,MATCH(B11,LR_Lane,0)),INDEX(DH_Table,0,MATCH(B11&"*",DH_Head,0)))-1)) | U11: =IF(V11<>"",V11,IF(IFERROR(INDEX(RS_Flag,MATCH(B11,RS_Lane,0)),"")="Yes",IF(IFERROR(INDEX(RS_Loc,MATCH(B11,RS_Lane,0)),"")="","Regional stock",IFERROR(INDEX(RS_Loc,MATCH(B11,RS_Lane,0)),"")),"Helmond")) | Y11: =IF(X11<>"",X11,IF(U11="Helmond",IF(COUNTIFS(RC_Lane,B11,RC_Band,E11,RC_CostPS,">0")=0,"",SUMIFS(RC_CostPS,RC_Lane,B11,RC_Band,E11)),IF(U11="Other","",IF(INDEX(RS_Rate,MATCH(B11,RS_Lane,0))="","",INDEX(RS_Rate,MATCH(B11,RS_Lane,0))))))
A12: A-008 | B12: L06 | C12: Morocco | D12: Casablanca area | E12: B4 500 to 2,000 kg | F12: 941.5 | G12: =F12*0.006477 | H12: =F12*1.079436 | I12: =MAX(1,ROUNDUP(G12/0.096,0)) | J12: 46398 | K12: =J12-WEEKDAY(J12,2)+1 | L12: =J12 | M12: =INDEX(LR_Target,MATCH(B12,LR_Lane,0)) | N12: =WORKDAY.INTL(L12,M12,INDEX(LR_Code,MATCH(B12,LR_Lane,0)),INDEX(DH_Table,0,MATCH(B12&"*",DH_Head,0))) | O12: =IF(W12<>"",W12,IF(U12="Helmond",IF(COUNTIFS(RC_Lane,B12,RC_Band,E12,RC_Transit,"<>")=0,"",SUMIFS(RC_Transit,RC_Lane,B12,RC_Band,E12)),IF(U12="Other","",IF(INDEX(RS_Transit,MATCH(B12,RS_Lane,0))="","",INDEX(RS_Transit,MATCH(B12,RS_Lane,0)))))) | Q12: =IF(P12<>"",P12,IF(O12="","",WORKDAY.INTL(L12,ROUNDUP(O12,0),INDEX(LR_Code,MATCH(B12,LR_Lane,0)),INDEX(DH_Table,0,MATCH(B12&"*",DH_Head,0))))) | R12: =IF(Q12="","",IF(Q12<=N12,"Yes","No")) | S12: =IF(Q12="","",IF(Q12<=N12,0,NETWORKDAYS.INTL(N12,Q12,INDEX(LR_Code,MATCH(B12,LR_Lane,0)),INDEX(DH_Table,0,MATCH(B12&"*",DH_Head,0)))-1)) | U12: =IF(V12<>"",V12,IF(IFERROR(INDEX(RS_Flag,MATCH(B12,RS_Lane,0)),"")="Yes",IF(IFERROR(INDEX(RS_Loc,MATCH(B12,RS_Lane,0)),"")="","Regional stock",IFERROR(INDEX(RS_Loc,MATCH(B12,RS_Lane,0)),"")),"Helmond")) | Y12: =IF(X12<>"",X12,IF(U12="Helmond",IF(COUNTIFS(RC_Lane,B12,RC_Band,E12,RC_CostPS,">0")=0,"",SUMIFS(RC_CostPS,RC_Lane,B12,RC_Band,E12)),IF(U12="Other","",IF(INDEX(RS_Rate,MATCH(B12,RS_Lane,0))="","",INDEX(RS_Rate,MATCH(B12,RS_Lane,0))))))
A13: A-009 | B13: L01 | C13: Saudi Arabia | D13: Jeddah | E13: B1 0 to 30 kg | F13: 5.9 | G13: =F13*0.006477 | H13: =F13*1.079436 | I13: =MAX(1,ROUNDUP(G13/0.096,0)) | J13: 46400 | K13: =J13-WEEKDAY(J13,2)+1 | L13: =J13 | M13: =INDEX(LR_Target,MATCH(B13,LR_Lane,0)) | N13: =WORKDAY.INTL(L13,M13,INDEX(LR_Code,MATCH(B13,LR_Lane,0)),INDEX(DH_Table,0,MATCH(B13&"*",DH_Head,0))) | O13: =IF(W13<>"",W13,IF(U13="Helmond",IF(COUNTIFS(RC_Lane,B13,RC_Band,E13,RC_Transit,"<>")=0,"",SUMIFS(RC_Transit,RC_Lane,B13,RC_Band,E13)),IF(U13="Other","",IF(INDEX(RS_Transit,MATCH(B13,RS_Lane,0))="","",INDEX(RS_Transit,MATCH(B13,RS_Lane,0)))))) | Q13: =IF(P13<>"",P13,IF(O13="","",WORKDAY.INTL(L13,ROUNDUP(O13,0),INDEX(LR_Code,MATCH(B13,LR_Lane,0)),INDEX(DH_Table,0,MATCH(B13&"*",DH_Head,0))))) | R13: =IF(Q13="","",IF(Q13<=N13,"Yes","No")) | S13: =IF(Q13="","",IF(Q13<=N13,0,NETWORKDAYS.INTL(N13,Q13,INDEX(LR_Code,MATCH(B13,LR_Lane,0)),INDEX(DH_Table,0,MATCH(B13&"*",DH_Head,0)))-1)) | U13: =IF(V13<>"",V13,IF(IFERROR(INDEX(RS_Flag,MATCH(B13,RS_Lane,0)),"")="Yes",IF(IFERROR(INDEX(RS_Loc,MATCH(B13,RS_Lane,0)),"")="","Regional stock",IFERROR(INDEX(RS_Loc,MATCH(B13,RS_Lane,0)),"")),"Helmond")) | Y13: =IF(X13<>"",X13,IF(U13="Helmond",IF(COUNTIFS(RC_Lane,B13,RC_Band,E13,RC_CostPS,">0")=0,"",SUMIFS(RC_CostPS,RC_Lane,B13,RC_Band,E13)),IF(U13="Other","",IF(INDEX(RS_Rate,MATCH(B13,RS_Lane,0))="","",INDEX(RS_Rate,MATCH(B13,RS_Lane,0))))))
A14: A-010 | B14: L03 | C14: Kuwait | D14: Kuwait City | E14: B4 500 to 2,000 kg | F14: 1093 | G14: =F14*0.006477 | H14: =F14*1.079436 | I14: =MAX(1,ROUNDUP(G14/0.096,0)) | J14: 46407 | K14: =J14-WEEKDAY(J14,2)+1 | L14: =J14 | M14: =INDEX(LR_Target,MATCH(B14,LR_Lane,0)) | N14: =WORKDAY.INTL(L14,M14,INDEX(LR_Code,MATCH(B14,LR_Lane,0)),INDEX(DH_Table,0,MATCH(B14&"*",DH_Head,0))) | O14: =IF(W14<>"",W14,IF(U14="Helmond",IF(COUNTIFS(RC_Lane,B14,RC_Band,E14,RC_Transit,"<>")=0,"",SUMIFS(RC_Transit,RC_Lane,B14,RC_Band,E14)),IF(U14="Other","",IF(INDEX(RS_Transit,MATCH(B14,RS_Lane,0))="","",INDEX(RS_Transit,MATCH(B14,RS_Lane,0)))))) | Q14: =IF(P14<>"",P14,IF(O14="","",WORKDAY.INTL(L14,ROUNDUP(O14,0),INDEX(LR_Code,MATCH(B14,LR_Lane,0)),INDEX(DH_Table,0,MATCH(B14&"*",DH_Head,0))))) | R14: =IF(Q14="","",IF(Q14<=N14,"Yes","No")) | S14: =IF(Q14="","",IF(Q14<=N14,0,NETWORKDAYS.INTL(N14,Q14,INDEX(LR_Code,MATCH(B14,LR_Lane,0)),INDEX(DH_Table,0,MATCH(B14&"*",DH_Head,0)))-1)) | U14: =IF(V14<>"",V14,IF(IFERROR(INDEX(RS_Flag,MATCH(B14,RS_Lane,0)),"")="Yes",IF(IFERROR(INDEX(RS_Loc,MATCH(B14,RS_Lane,0)),"")="","Regional stock",IFERROR(INDEX(RS_Loc,MATCH(B14,RS_Lane,0)),"")),"Helmond")) | Y14: =IF(X14<>"",X14,IF(U14="Helmond",IF(COUNTIFS(RC_Lane,B14,RC_Band,E14,RC_CostPS,">0")=0,"",SUMIFS(RC_CostPS,RC_Lane,B14,RC_Band,E14)),IF(U14="Other","",IF(INDEX(RS_Rate,MATCH(B14,RS_Lane,0))="","",INDEX(RS_Rate,MATCH(B14,RS_Lane,0))))))
A15: A-011 | B15: L01 | C15: Saudi Arabia | D15: Jeddah | E15: B3 100 to 500 kg | F15: 232.3 | G15: =F15*0.006477 | H15: =F15*1.079436 | I15: =MAX(1,ROUNDUP(G15/0.096,0)) | J15: 46413 | K15: =J15-WEEKDAY(J15,2)+1 | L15: =J15 | M15: =INDEX(LR_Target,MATCH(B15,LR_Lane,0)) | N15: =WORKDAY.INTL(L15,M15,INDEX(LR_Code,MATCH(B15,LR_Lane,0)),INDEX(DH_Table,0,MATCH(B15&"*",DH_Head,0))) | O15: =IF(W15<>"",W15,IF(U15="Helmond",IF(COUNTIFS(RC_Lane,B15,RC_Band,E15,RC_Transit,"<>")=0,"",SUMIFS(RC_Transit,RC_Lane,B15,RC_Band,E15)),IF(U15="Other","",IF(INDEX(RS_Transit,MATCH(B15,RS_Lane,0))="","",INDEX(RS_Transit,MATCH(B15,RS_Lane,0)))))) | Q15: =IF(P15<>"",P15,IF(O15="","",WORKDAY.INTL(L15,ROUNDUP(O15,0),INDEX(LR_Code,MATCH(B15,LR_Lane,0)),INDEX(DH_Table,0,MATCH(B15&"*",DH_Head,0))))) | R15: =IF(Q15="","",IF(Q15<=N15,"Yes","No")) | S15: =IF(Q15="","",IF(Q15<=N15,0,NETWORKDAYS.INTL(N15,Q15,INDEX(LR_Code,MATCH(B15,LR_Lane,0)),INDEX(DH_Table,0,MATCH(B15&"*",DH_Head,0)))-1)) | U15: =IF(V15<>"",V15,IF(IFERROR(INDEX(RS_Flag,MATCH(B15,RS_Lane,0)),"")="Yes",IF(IFERROR(INDEX(RS_Loc,MATCH(B15,RS_Lane,0)),"")="","Regional stock",IFERROR(INDEX(RS_Loc,MATCH(B15,RS_Lane,0)),"")),"Helmond")) | Y15: =IF(X15<>"",X15,IF(U15="Helmond",IF(COUNTIFS(RC_Lane,B15,RC_Band,E15,RC_CostPS,">0")=0,"",SUMIFS(RC_CostPS,RC_Lane,B15,RC_Band,E15)),IF(U15="Other","",IF(INDEX(RS_Rate,MATCH(B15,RS_Lane,0))="","",INDEX(RS_Rate,MATCH(B15,RS_Lane,0))))))
A16: A-012 | B16: L02 | C16: United Arab Emirates | D16: Dubai | E16: B3 100 to 500 kg | F16: 202.1 | G16: =F16*0.006477 | H16: =F16*1.079436 | I16: =MAX(1,ROUNDUP(G16/0.096,0)) | J16: 46413 | K16: =J16-WEEKDAY(J16,2)+1 | L16: =J16 | M16: =INDEX(LR_Target,MATCH(B16,LR_Lane,0)) | N16: =WORKDAY.INTL(L16,M16,INDEX(LR_Code,MATCH(B16,LR_Lane,0)),INDEX(DH_Table,0,MATCH(B16&"*",DH_Head,0))) | O16: =IF(W16<>"",W16,IF(U16="Helmond",IF(COUNTIFS(RC_Lane,B16,RC_Band,E16,RC_Transit,"<>")=0,"",SUMIFS(RC_Transit,RC_Lane,B16,RC_Band,E16)),IF(U16="Other","",IF(INDEX(RS_Transit,MATCH(B16,RS_Lane,0))="","",INDEX(RS_Transit,MATCH(B16,RS_Lane,0)))))) | Q16: =IF(P16<>"",P16,IF(O16="","",WORKDAY.INTL(L16,ROUNDUP(O16,0),INDEX(LR_Code,MATCH(B16,LR_Lane,0)),INDEX(DH_Table,0,MATCH(B16&"*",DH_Head,0))))) | R16: =IF(Q16="","",IF(Q16<=N16,"Yes","No")) | S16: =IF(Q16="","",IF(Q16<=N16,0,NETWORKDAYS.INTL(N16,Q16,INDEX(LR_Code,MATCH(B16,LR_Lane,0)),INDEX(DH_Table,0,MATCH(B16&"*",DH_Head,0)))-1)) | U16: =IF(V16<>"",V16,IF(IFERROR(INDEX(RS_Flag,MATCH(B16,RS_Lane,0)),"")="Yes",IF(IFERROR(INDEX(RS_Loc,MATCH(B16,RS_Lane,0)),"")="","Regional stock",IFERROR(INDEX(RS_Loc,MATCH(B16,RS_Lane,0)),"")),"Helmond")) | Y16: =IF(X16<>"",X16,IF(U16="Helmond",IF(COUNTIFS(RC_Lane,B16,RC_Band,E16,RC_CostPS,">0")=0,"",SUMIFS(RC_CostPS,RC_Lane,B16,RC_Band,E16)),IF(U16="Other","",IF(INDEX(RS_Rate,MATCH(B16,RS_Lane,0))="","",INDEX(RS_Rate,MATCH(B16,RS_Lane,0))))))
... A145: A-141 | B145: L01 | C145: Saudi Arabia | D145: Riyadh | E145: B1 0 to 30 kg | F145: 9.5 | G145: =F145*0.006477 | H145: =F145*1.079436 | I145: =MAX(1,ROUNDUP(G145/0.096,0)) | J145: 46750 | K145: =J145-WEEKDAY(J145,2)+1 | L145: =J145 | M145: =INDEX(LR_Target,MATCH(B145,LR_Lane,0)) | N145: =WORKDAY.INTL(L145,M145,INDEX(LR_Code,MATCH(B145,LR_Lane,0)),INDEX(DH_Table,0,MATCH(B145&"*",DH_Head,0))) | O145: =IF(W145<>"",W145,IF(U145="Helmond",IF(COUNTIFS(RC_Lane,B145,RC_Band,E145,RC_Transit,"<>")=0,"",SUMIFS(RC_Transit,RC_Lane,B145,RC_Band,E145)),IF(U145="Other","",IF(INDEX(RS_Transit,MATCH(B145,RS_Lane,0))="","",INDEX(RS_Transit,MATCH(B145,RS_Lane,0)))))) | Q145: =IF(P145<>"",P145,IF(O145="","",WORKDAY.INTL(L145,ROUNDUP(O145,0),INDEX(LR_Code,MATCH(B145,LR_Lane,0)),INDEX(DH_Table,0,MATCH(B145&"*",DH_Head,0))))) | R145: =IF(Q145="","",IF(Q145<=N145,"Yes","No")) | S145: =IF(Q145="","",IF(Q145<=N145,0,NETWORKDAYS.INTL(N145,Q145,INDEX(LR_Code,MATCH(B145,LR_Lane,0)),INDEX(DH_Table,0,MATCH(B145&"*",DH_Head,0)))-1)) | U145: =IF(V145<>"",V145,IF(IFERROR(INDEX(RS_Flag,MATCH(B145,RS_Lane,0)),"")="Yes",IF(IFERROR(INDEX(RS_Loc,MATCH(B145,RS_Lane,0)),"")="","Regional stock",IFERROR(INDEX(RS_Loc,MATCH(B145,RS_Lane,0)),"")),"Helmond")) | Y145: =IF(X145<>"",X145,IF(U145="Helmond",IF(COUNTIFS(RC_Lane,B145,RC_Band,E145,RC_CostPS,">0")=0,"",SUMIFS(RC_CostPS,RC_Lane,B145,RC_Band,E145)),IF(U145="Other","",IF(INDEX(RS_Rate,MATCH(B145,RS_Lane,0))="","",INDEX(RS_Rate,MATCH(B145,RS_Lane,0))))))
A146: =COUNTA(A5:A145)&" shipments" | F146: =SUM(F5:F145) | G146: =SUM(G5:G145) | H146: =SUM(H5:H145) | I146: =SUM(I5:I145) | U146: =COUNTIF(U5:U145,"<>Helmond")&" not from Helmond" | Y146: =SUM(Y5:Y145)

Sheet Schedule B
A1: Scenario B: shipment schedule
A2: One row per shipment. Default origin is Helmond. Where another origin is possible or better (your hub W1 to W3, a supplier, another hub), set it per shipment in the yellow origin columns. Expected delivery and shipment cost then follow that origin.
A4: Shipment ID | B4: Lane | C4: Destination | D4: Delivery city | E4: Weight band | F4: Gross kg | G4: m3 (est.) | H4: Chargeable kg | I4: Cartons (est.) | J4: Order release date | K4: Week starting | L4: Planned pickup | M4: Target (working days) | N4: Target delivery date | O4: Quoted transit days | P4: Your expected delivery date (optional) | Q4: Expected delivery date | R4: Meets target | S4: Days late | T4: Comment | U4: Ships from | V4: Proposed origin (optional) | W4: Transit days from proposed origin (optional) | X4: Cost per shipment from proposed origin (EUR, optional) | Y4: Shipment cost (EUR)
A5: B-001 | B5: L02 | C5: United Arab Emirates | D5: Dubai | E5: B1 0 to 30 kg | F5: 7.7 | G5: =F5*0.006477 | H5: =F5*1.079436 | I5: =MAX(1,ROUNDUP(G5/0.096,0)) | J5: 46391 | K5: =J5-WEEKDAY(J5,2)+1 | L5: =J5 | M5: =INDEX(LR_Target,MATCH(B5,LR_Lane,0)) | N5: =WORKDAY.INTL(L5,M5,INDEX(LR_Code,MATCH(B5,LR_Lane,0)),INDEX(DH_Table,0,MATCH(B5&"*",DH_Head,0))) | O5: =IF(W5<>"",W5,IF(U5="Helmond",IF(COUNTIFS(RC_Lane,B5,RC_Band,E5,RC_Transit,"<>")=0,"",SUMIFS(RC_Transit,RC_Lane,B5,RC_Band,E5)),IF(U5="Other","",IF(INDEX(RS_Transit,MATCH(B5,RS_Lane,0))="","",INDEX(RS_Transit,MATCH(B5,RS_Lane,0)))))) | Q5: =IF(P5<>"",P5,IF(O5="","",WORKDAY.INTL(L5,ROUNDUP(O5,0),INDEX(LR_Code,MATCH(B5,LR_Lane,0)),INDEX(DH_Table,0,MATCH(B5&"*",DH_Head,0))))) | R5: =IF(Q5="","",IF(Q5<=N5,"Yes","No")) | S5: =IF(Q5="","",IF(Q5<=N5,0,NETWORKDAYS.INTL(N5,Q5,INDEX(LR_Code,MATCH(B5,LR_Lane,0)),INDEX(DH_Table,0,MATCH(B5&"*",DH_Head,0)))-1)) | U5: =IF(V5<>"",V5,IF(IFERROR(INDEX(RS_Flag,MATCH(B5,RS_Lane,0)),"")="Yes",IF(IFERROR(INDEX(RS_Loc,MATCH(B5,RS_Lane,0)),"")="","Regional stock",IFERROR(INDEX(RS_Loc,MATCH(B5,RS_Lane,0)),"")),"Helmond")) | Y5: =IF(X5<>"",X5,IF(U5="Helmond",IF(COUNTIFS(RC_Lane,B5,RC_Band,E5,RC_CostPS,">0")=0,"",SUMIFS(RC_CostPS,RC_Lane,B5,RC_Band,E5)*(1-SUMIFS(RC_Disc,RC_Lane,B5,RC_Band,E5))),IF(U5="Other","",IF(INDEX(RS_Rate,MATCH(B5,RS_Lane,0))="","",INDEX(RS_Rate,MATCH(B5,RS_Lane,0))))))
A6: B-002 | B6: L05 | C6: Türkiye | D6: Istanbul | E6: B1 0 to 30 kg | F6: 3.5 | G6: =F6*0.006477 | H6: =F6*1.079436 | I6: =MAX(1,ROUNDUP(G6/0.096,0)) | J6: 46391 | K6: =J6-WEEKDAY(J6,2)+1 | L6: =J6 | M6: =INDEX(LR_Target,MATCH(B6,LR_Lane,0)) | N6: =WORKDAY.INTL(L6,M6,INDEX(LR_Code,MATCH(B6,LR_Lane,0)),INDEX(DH_Table,0,MATCH(B6&"*",DH_Head,0))) | O6: =IF(W6<>"",W6,IF(U6="Helmond",IF(COUNTIFS(RC_Lane,B6,RC_Band,E6,RC_Transit,"<>")=0,"",SUMIFS(RC_Transit,RC_Lane,B6,RC_Band,E6)),IF(U6="Other","",IF(INDEX(RS_Transit,MATCH(B6,RS_Lane,0))="","",INDEX(RS_Transit,MATCH(B6,RS_Lane,0)))))) | Q6: =IF(P6<>"",P6,IF(O6="","",WORKDAY.INTL(L6,ROUNDUP(O6,0),INDEX(LR_Code,MATCH(B6,LR_Lane,0)),INDEX(DH_Table,0,MATCH(B6&"*",DH_Head,0))))) | R6: =IF(Q6="","",IF(Q6<=N6,"Yes","No")) | S6: =IF(Q6="","",IF(Q6<=N6,0,NETWORKDAYS.INTL(N6,Q6,INDEX(LR_Code,MATCH(B6,LR_Lane,0)),INDEX(DH_Table,0,MATCH(B6&"*",DH_Head,0)))-1)) | U6: =IF(V6<>"",V6,IF(IFERROR(INDEX(RS_Flag,MATCH(B6,RS_Lane,0)),"")="Yes",IF(IFERROR(INDEX(RS_Loc,MATCH(B6,RS_Lane,0)),"")="","Regional stock",IFERROR(INDEX(RS_Loc,MATCH(B6,RS_Lane,0)),"")),"Helmond")) | Y6: =IF(X6<>"",X6,IF(U6="Helmond",IF(COUNTIFS(RC_Lane,B6,RC_Band,E6,RC_CostPS,">0")=0,"",SUMIFS(RC_CostPS,RC_Lane,B6,RC_Band,E6)*(1-SUMIFS(RC_Disc,RC_Lane,B6,RC_Band,E6))),IF(U6="Other","",IF(INDEX(RS_Rate,MATCH(B6,RS_Lane,0))="","",INDEX(RS_Rate,MATCH(B6,RS_Lane,0))))))
A7: B-003 | B7: L01 | C7: Saudi Arabia | D7: Riyadh | E7: B3 100 to 500 kg | F7: 153.3 | G7: =F7*0.006477 | H7: =F7*1.079436 | I7: =MAX(1,ROUNDUP(G7/0.096,0)) | J7: 46393 | K7: =J7-WEEKDAY(J7,2)+1 | L7: =J7 | M7: =INDEX(LR_Target,MATCH(B7,LR_Lane,0)) | N7: =WORKDAY.INTL(L7,M7,INDEX(LR_Code,MATCH(B7,LR_Lane,0)),INDEX(DH_Table,0,MATCH(B7&"*",DH_Head,0))) | O7: =IF(W7<>"",W7,IF(U7="Helmond",IF(COUNTIFS(RC_Lane,B7,RC_Band,E7,RC_Transit,"<>")=0,"",SUMIFS(RC_Transit,RC_Lane,B7,RC_Band,E7)),IF(U7="Other","",IF(INDEX(RS_Transit,MATCH(B7,RS_Lane,0))="","",INDEX(RS_Transit,MATCH(B7,RS_Lane,0)))))) | Q7: =IF(P7<>"",P7,IF(O7="","",WORKDAY.INTL(L7,ROUNDUP(O7,0),INDEX(LR_Code,MATCH(B7,LR_Lane,0)),INDEX(DH_Table,0,MATCH(B7&"*",DH_Head,0))))) | R7: =IF(Q7="","",IF(Q7<=N7,"Yes","No")) | S7: =IF(Q7="","",IF(Q7<=N7,0,NETWORKDAYS.INTL(N7,Q7,INDEX(LR_Code,MATCH(B7,LR_Lane,0)),INDEX(DH_Table,0,MATCH(B7&"*",DH_Head,0)))-1)) | U7: =IF(V7<>"",V7,IF(IFERROR(INDEX(RS_Flag,MATCH(B7,RS_Lane,0)),"")="Yes",IF(IFERROR(INDEX(RS_Loc,MATCH(B7,RS_Lane,0)),"")="","Regional stock",IFERROR(INDEX(RS_Loc,MATCH(B7,RS_Lane,0)),"")),"Helmond")) | Y7: =IF(X7<>"",X7,IF(U7="Helmond",IF(COUNTIFS(RC_Lane,B7,RC_Band,E7,RC_CostPS,">0")=0,"",SUMIFS(RC_CostPS,RC_Lane,B7,RC_Band,E7)*(1-SUMIFS(RC_Disc,RC_Lane,B7,RC_Band,E7))),IF(U7="Other","",IF(INDEX(RS_Rate,MATCH(B7,RS_Lane,0))="","",INDEX(RS_Rate,MATCH(B7,RS_Lane,0))))))
A8: B-004 | B8: L05 | C8: Türkiye | D8: Istanbul | E8: B1 0 to 30 kg | F8: 2.2 | G8: =F8*0.006477 | H8: =F8*1.079436 | I8: =MAX(1,ROUNDUP(G8/0.096,0)) | J8: 46393 | K8: =J8-WEEKDAY(J8,2)+1 | L8: =J8 | M8: =INDEX(LR_Target,MATCH(B8,LR_Lane,0)) | N8: =WORKDAY.INTL(L8,M8,INDEX(LR_Code,MATCH(B8,LR_Lane,0)),INDEX(DH_Table,0,MATCH(B8&"*",DH_Head,0))) | O8: =IF(W8<>"",W8,IF(U8="Helmond",IF(COUNTIFS(RC_Lane,B8,RC_Band,E8,RC_Transit,"<>")=0,"",SUMIFS(RC_Transit,RC_Lane,B8,RC_Band,E8)),IF(U8="Other","",IF(INDEX(RS_Transit,MATCH(B8,RS_Lane,0))="","",INDEX(RS_Transit,MATCH(B8,RS_Lane,0)))))) | Q8: =IF(P8<>"",P8,IF(O8="","",WORKDAY.INTL(L8,ROUNDUP(O8,0),INDEX(LR_Code,MATCH(B8,LR_Lane,0)),INDEX(DH_Table,0,MATCH(B8&"*",DH_Head,0))))) | R8: =IF(Q8="","",IF(Q8<=N8,"Yes","No")) | S8: =IF(Q8="","",IF(Q8<=N8,0,NETWORKDAYS.INTL(N8,Q8,INDEX(LR_Code,MATCH(B8,LR_Lane,0)),INDEX(DH_Table,0,MATCH(B8&"*",DH_Head,0)))-1)) | U8: =IF(V8<>"",V8,IF(IFERROR(INDEX(RS_Flag,MATCH(B8,RS_Lane,0)),"")="Yes",IF(IFERROR(INDEX(RS_Loc,MATCH(B8,RS_Lane,0)),"")="","Regional stock",IFERROR(INDEX(RS_Loc,MATCH(B8,RS_Lane,0)),"")),"Helmond")) | Y8: =IF(X8<>"",X8,IF(U8="Helmond",IF(COUNTIFS(RC_Lane,B8,RC_Band,E8,RC_CostPS,">0")=0,"",SUMIFS(RC_CostPS,RC_Lane,B8,RC_Band,E8)*(1-SUMIFS(RC_Disc,RC_Lane,B8,RC_Band,E8))),IF(U8="Other","",IF(INDEX(RS_Rate,MATCH(B8,RS_Lane,0))="","",INDEX(RS_Rate,MATCH(B8,RS_Lane,0))))))
A9: B-005 | B9: L01 | C9: Saudi Arabia | D9: Jeddah | E9: B1 0 to 30 kg | F9: 10.9 | G9: =F9*0.006477 | H9: =F9*1.079436 | I9: =MAX(1,ROUNDUP(G9/0.096,0)) | J9: 46395 | K9: =J9-WEEKDAY(J9,2)+1 | L9: =J9 | M9: =INDEX(LR_Target,MATCH(B9,LR_Lane,0)) | N9: =WORKDAY.INTL(L9,M9,INDEX(LR_Code,MATCH(B9,LR_Lane,0)),INDEX(DH_Table,0,MATCH(B9&"*",DH_Head,0))) | O9: =IF(W9<>"",W9,IF(U9="Helmond",IF(COUNTIFS(RC_Lane,B9,RC_Band,E9,RC_Transit,"<>")=0,"",SUMIFS(RC_Transit,RC_Lane,B9,RC_Band,E9)),IF(U9="Other","",IF(INDEX(RS_Transit,MATCH(B9,RS_Lane,0))="","",INDEX(RS_Transit,MATCH(B9,RS_Lane,0)))))) | Q9: =IF(P9<>"",P9,IF(O9="","",WORKDAY.INTL(L9,ROUNDUP(O9,0),INDEX(LR_Code,MATCH(B9,LR_Lane,0)),INDEX(DH_Table,0,MATCH(B9&"*",DH_Head,0))))) | R9: =IF(Q9="","",IF(Q9<=N9,"Yes","No")) | S9: =IF(Q9="","",IF(Q9<=N9,0,NETWORKDAYS.INTL(N9,Q9,INDEX(LR_Code,MATCH(B9,LR_Lane,0)),INDEX(DH_Table,0,MATCH(B9&"*",DH_Head,0)))-1)) | U9: =IF(V9<>"",V9,IF(IFERROR(INDEX(RS_Flag,MATCH(B9,RS_Lane,0)),"")="Yes",IF(IFERROR(INDEX(RS_Loc,MATCH(B9,RS_Lane,0)),"")="","Regional stock",IFERROR(INDEX(RS_Loc,MATCH(B9,RS_Lane,0)),"")),"Helmond")) | Y9: =IF(X9<>"",X9,IF(U9="Helmond",IF(COUNTIFS(RC_Lane,B9,RC_Band,E9,RC_CostPS,">0")=0,"",SUMIFS(RC_CostPS,RC_Lane,B9,RC_Band,E9)*(1-SUMIFS(RC_Disc,RC_Lane,B9,RC_Band,E9))),IF(U9="Other","",IF(INDEX(RS_Rate,MATCH(B9,RS_Lane,0))="","",INDEX(RS_Rate,MATCH(B9,RS_Lane,0))))))
A10: B-006 | B10: L02 | C10: United Arab Emirates | D10: Dubai | E10: B1 0 to 30 kg | F10: 7.4 | G10: =F10*0.006477 | H10: =F10*1.079436 | I10: =MAX(1,ROUNDUP(G10/0.096,0)) | J10: 46399 | K10: =J10-WEEKDAY(J10,2)+1 | L10: =J10 | M10: =INDEX(LR_Target,MATCH(B10,LR_Lane,0)) | N10: =WORKDAY.INTL(L10,M10,INDEX(LR_Code,MATCH(B10,LR_Lane,0)),INDEX(DH_Table,0,MATCH(B10&"*",DH_Head,0))) | O10: =IF(W10<>"",W10,IF(U10="Helmond",IF(COUNTIFS(RC_Lane,B10,RC_Band,E10,RC_Transit,"<>")=0,"",SUMIFS(RC_Transit,RC_Lane,B10,RC_Band,E10)),IF(U10="Other","",IF(INDEX(RS_Transit,MATCH(B10,RS_Lane,0))="","",INDEX(RS_Transit,MATCH(B10,RS_Lane,0)))))) | Q10: =IF(P10<>"",P10,IF(O10="","",WORKDAY.INTL(L10,ROUNDUP(O10,0),INDEX(LR_Code,MATCH(B10,LR_Lane,0)),INDEX(DH_Table,0,MATCH(B10&"*",DH_Head,0))))) | R10: =IF(Q10="","",IF(Q10<=N10,"Yes","No")) | S10: =IF(Q10="","",IF(Q10<=N10,0,NETWORKDAYS.INTL(N10,Q10,INDEX(LR_Code,MATCH(B10,LR_Lane,0)),INDEX(DH_Table,0,MATCH(B10&"*",DH_Head,0)))-1)) | U10: =IF(V10<>"",V10,IF(IFERROR(INDEX(RS_Flag,MATCH(B10,RS_Lane,0)),"")="Yes",IF(IFERROR(INDEX(RS_Loc,MATCH(B10,RS_Lane,0)),"")="","Regional stock",IFERROR(INDEX(RS_Loc,MATCH(B10,RS_Lane,0)),"")),"Helmond")) | Y10: =IF(X10<>"",X10,IF(U10="Helmond",IF(COUNTIFS(RC_Lane,B10,RC_Band,E10,RC_CostPS,">0")=0,"",SUMIFS(RC_CostPS,RC_Lane,B10,RC_Band,E10)*(1-SUMIFS(RC_Disc,RC_Lane,B10,RC_Band,E10))),IF(U10="Other","",IF(INDEX(RS_Rate,MATCH(B10,RS_Lane,0))="","",INDEX(RS_Rate,MATCH(B10,RS_Lane,0))))))
A11: B-007 | B11: L02 | C11: United Arab Emirates | D11: Dubai | E11: B1 0 to 30 kg | F11: 11 | G11: =F11*0.006477 | H11: =F11*1.079436 | I11: =MAX(1,ROUNDUP(G11/0.096,0)) | J11: 46399 | K11: =J11-WEEKDAY(J11,2)+1 | L11: =J11 | M11: =INDEX(LR_Target,MATCH(B11,LR_Lane,0)) | N11: =WORKDAY.INTL(L11,M11,INDEX(LR_Code,MATCH(B11,LR_Lane,0)),INDEX(DH_Table,0,MATCH(B11&"*",DH_Head,0))) | O11: =IF(W11<>"",W11,IF(U11="Helmond",IF(COUNTIFS(RC_Lane,B11,RC_Band,E11,RC_Transit,"<>")=0,"",SUMIFS(RC_Transit,RC_Lane,B11,RC_Band,E11)),IF(U11="Other","",IF(INDEX(RS_Transit,MATCH(B11,RS_Lane,0))="","",INDEX(RS_Transit,MATCH(B11,RS_Lane,0)))))) | Q11: =IF(P11<>"",P11,IF(O11="","",WORKDAY.INTL(L11,ROUNDUP(O11,0),INDEX(LR_Code,MATCH(B11,LR_Lane,0)),INDEX(DH_Table,0,MATCH(B11&"*",DH_Head,0))))) | R11: =IF(Q11="","",IF(Q11<=N11,"Yes","No")) | S11: =IF(Q11="","",IF(Q11<=N11,0,NETWORKDAYS.INTL(N11,Q11,INDEX(LR_Code,MATCH(B11,LR_Lane,0)),INDEX(DH_Table,0,MATCH(B11&"*",DH_Head,0)))-1)) | U11: =IF(V11<>"",V11,IF(IFERROR(INDEX(RS_Flag,MATCH(B11,RS_Lane,0)),"")="Yes",IF(IFERROR(INDEX(RS_Loc,MATCH(B11,RS_Lane,0)),"")="","Regional stock",IFERROR(INDEX(RS_Loc,MATCH(B11,RS_Lane,0)),"")),"Helmond")) | Y11: =IF(X11<>"",X11,IF(U11="Helmond",IF(COUNTIFS(RC_Lane,B11,RC_Band,E11,RC_CostPS,">0")=0,"",SUMIFS(RC_CostPS,RC_Lane,B11,RC_Band,E11)*(1-SUMIFS(RC_Disc,RC_Lane,B11,RC_Band,E11))),IF(U11="Other","",IF(INDEX(RS_Rate,MATCH(B11,RS_Lane,0))="","",INDEX(RS_Rate,MATCH(B11,RS_Lane,0))))))
A12: B-008 | B12: L03 | C12: Kuwait | D12: Kuwait City | E12: B1 0 to 30 kg | F12: 4.8 | G12: =F12*0.006477 | H12: =F12*1.079436 | I12: =MAX(1,ROUNDUP(G12/0.096,0)) | J12: 46399 | K12: =J12-WEEKDAY(J12,2)+1 | L12: =J12 | M12: =INDEX(LR_Target,MATCH(B12,LR_Lane,0)) | N12: =WORKDAY.INTL(L12,M12,INDEX(LR_Code,MATCH(B12,LR_Lane,0)),INDEX(DH_Table,0,MATCH(B12&"*",DH_Head,0))) | O12: =IF(W12<>"",W12,IF(U12="Helmond",IF(COUNTIFS(RC_Lane,B12,RC_Band,E12,RC_Transit,"<>")=0,"",SUMIFS(RC_Transit,RC_Lane,B12,RC_Band,E12)),IF(U12="Other","",IF(INDEX(RS_Transit,MATCH(B12,RS_Lane,0))="","",INDEX(RS_Transit,MATCH(B12,RS_Lane,0)))))) | Q12: =IF(P12<>"",P12,IF(O12="","",WORKDAY.INTL(L12,ROUNDUP(O12,0),INDEX(LR_Code,MATCH(B12,LR_Lane,0)),INDEX(DH_Table,0,MATCH(B12&"*",DH_Head,0))))) | R12: =IF(Q12="","",IF(Q12<=N12,"Yes","No")) | S12: =IF(Q12="","",IF(Q12<=N12,0,NETWORKDAYS.INTL(N12,Q12,INDEX(LR_Code,MATCH(B12,LR_Lane,0)),INDEX(DH_Table,0,MATCH(B12&"*",DH_Head,0)))-1)) | U12: =IF(V12<>"",V12,IF(IFERROR(INDEX(RS_Flag,MATCH(B12,RS_Lane,0)),"")="Yes",IF(IFERROR(INDEX(RS_Loc,MATCH(B12,RS_Lane,0)),"")="","Regional stock",IFERROR(INDEX(RS_Loc,MATCH(B12,RS_Lane,0)),"")),"Helmond")) | Y12: =IF(X12<>"",X12,IF(U12="Helmond",IF(COUNTIFS(RC_Lane,B12,RC_Band,E12,RC_CostPS,">0")=0,"",SUMIFS(RC_CostPS,RC_Lane,B12,RC_Band,E12)*(1-SUMIFS(RC_Disc,RC_Lane,B12,RC_Band,E12))),IF(U12="Other","",IF(INDEX(RS_Rate,MATCH(B12,RS_Lane,0))="","",INDEX(RS_Rate,MATCH(B12,RS_Lane,0))))))
A13: B-009 | B13: L01 | C13: Saudi Arabia | D13: Riyadh | E13: B1 0 to 30 kg | F13: 9.4 | G13: =F13*0.006477 | H13: =F13*1.079436 | I13: =MAX(1,ROUNDUP(G13/0.096,0)) | J13: 46400 | K13: =J13-WEEKDAY(J13,2)+1 | L13: =J13 | M13: =INDEX(LR_Target,MATCH(B13,LR_Lane,0)) | N13: =WORKDAY.INTL(L13,M13,INDEX(LR_Code,MATCH(B13,LR_Lane,0)),INDEX(DH_Table,0,MATCH(B13&"*",DH_Head,0))) | O13: =IF(W13<>"",W13,IF(U13="Helmond",IF(COUNTIFS(RC_Lane,B13,RC_Band,E13,RC_Transit,"<>")=0,"",SUMIFS(RC_Transit,RC_Lane,B13,RC_Band,E13)),IF(U13="Other","",IF(INDEX(RS_Transit,MATCH(B13,RS_Lane,0))="","",INDEX(RS_Transit,MATCH(B13,RS_Lane,0)))))) | Q13: =IF(P13<>"",P13,IF(O13="","",WORKDAY.INTL(L13,ROUNDUP(O13,0),INDEX(LR_Code,MATCH(B13,LR_Lane,0)),INDEX(DH_Table,0,MATCH(B13&"*",DH_Head,0))))) | R13: =IF(Q13="","",IF(Q13<=N13,"Yes","No")) | S13: =IF(Q13="","",IF(Q13<=N13,0,NETWORKDAYS.INTL(N13,Q13,INDEX(LR_Code,MATCH(B13,LR_Lane,0)),INDEX(DH_Table,0,MATCH(B13&"*",DH_Head,0)))-1)) | U13: =IF(V13<>"",V13,IF(IFERROR(INDEX(RS_Flag,MATCH(B13,RS_Lane,0)),"")="Yes",IF(IFERROR(INDEX(RS_Loc,MATCH(B13,RS_Lane,0)),"")="","Regional stock",IFERROR(INDEX(RS_Loc,MATCH(B13,RS_Lane,0)),"")),"Helmond")) | Y13: =IF(X13<>"",X13,IF(U13="Helmond",IF(COUNTIFS(RC_Lane,B13,RC_Band,E13,RC_CostPS,">0")=0,"",SUMIFS(RC_CostPS,RC_Lane,B13,RC_Band,E13)*(1-SUMIFS(RC_Disc,RC_Lane,B13,RC_Band,E13))),IF(U13="Other","",IF(INDEX(RS_Rate,MATCH(B13,RS_Lane,0))="","",INDEX(RS_Rate,MATCH(B13,RS_Lane,0))))))
A14: B-010 | B14: L02 | C14: United Arab Emirates | D14: Dubai | E14: B1 0 to 30 kg | F14: 3.2 | G14: =F14*0.006477 | H14: =F14*1.079436 | I14: =MAX(1,ROUNDUP(G14/0.096,0)) | J14: 46400 | K14: =J14-WEEKDAY(J14,2)+1 | L14: =J14 | M14: =INDEX(LR_Target,MATCH(B14,LR_Lane,0)) | N14: =WORKDAY.INTL(L14,M14,INDEX(LR_Code,MATCH(B14,LR_Lane,0)),INDEX(DH_Table,0,MATCH(B14&"*",DH_Head,0))) | O14: =IF(W14<>"",W14,IF(U14="Helmond",IF(COUNTIFS(RC_Lane,B14,RC_Band,E14,RC_Transit,"<>")=0,"",SUMIFS(RC_Transit,RC_Lane,B14,RC_Band,E14)),IF(U14="Other","",IF(INDEX(RS_Transit,MATCH(B14,RS_Lane,0))="","",INDEX(RS_Transit,MATCH(B14,RS_Lane,0)))))) | Q14: =IF(P14<>"",P14,IF(O14="","",WORKDAY.INTL(L14,ROUNDUP(O14,0),INDEX(LR_Code,MATCH(B14,LR_Lane,0)),INDEX(DH_Table,0,MATCH(B14&"*",DH_Head,0))))) | R14: =IF(Q14="","",IF(Q14<=N14,"Yes","No")) | S14: =IF(Q14="","",IF(Q14<=N14,0,NETWORKDAYS.INTL(N14,Q14,INDEX(LR_Code,MATCH(B14,LR_Lane,0)),INDEX(DH_Table,0,MATCH(B14&"*",DH_Head,0)))-1)) | U14: =IF(V14<>"",V14,IF(IFERROR(INDEX(RS_Flag,MATCH(B14,RS_Lane,0)),"")="Yes",IF(IFERROR(INDEX(RS_Loc,MATCH(B14,RS_Lane,0)),"")="","Regional stock",IFERROR(INDEX(RS_Loc,MATCH(B14,RS_Lane,0)),"")),"Helmond")) | Y14: =IF(X14<>"",X14,IF(U14="Helmond",IF(COUNTIFS(RC_Lane,B14,RC_Band,E14,RC_CostPS,">0")=0,"",SUMIFS(RC_CostPS,RC_Lane,B14,RC_Band,E14)*(1-SUMIFS(RC_Disc,RC_Lane,B14,RC_Band,E14))),IF(U14="Other","",IF(INDEX(RS_Rate,MATCH(B14,RS_Lane,0))="","",INDEX(RS_Rate,MATCH(B14,RS_Lane,0))))))
A15: B-011 | B15: L04 | C15: Qatar | D15: Doha | E15: B2 30 to 100 kg | F15: 68.9 | G15: =F15*0.006477 | H15: =F15*1.079436 | I15: =MAX(1,ROUNDUP(G15/0.096,0)) | J15: 46400 | K15: =J15-WEEKDAY(J15,2)+1 | L15: =J15 | M15: =INDEX(LR_Target,MATCH(B15,LR_Lane,0)) | N15: =WORKDAY.INTL(L15,M15,INDEX(LR_Code,MATCH(B15,LR_Lane,0)),INDEX(DH_Table,0,MATCH(B15&"*",DH_Head,0))) | O15: =IF(W15<>"",W15,IF(U15="Helmond",IF(COUNTIFS(RC_Lane,B15,RC_Band,E15,RC_Transit,"<>")=0,"",SUMIFS(RC_Transit,RC_Lane,B15,RC_Band,E15)),IF(U15="Other","",IF(INDEX(RS_Transit,MATCH(B15,RS_Lane,0))="","",INDEX(RS_Transit,MATCH(B15,RS_Lane,0)))))) | Q15: =IF(P15<>"",P15,IF(O15="","",WORKDAY.INTL(L15,ROUNDUP(O15,0),INDEX(LR_Code,MATCH(B15,LR_Lane,0)),INDEX(DH_Table,0,MATCH(B15&"*",DH_Head,0))))) | R15: =IF(Q15="","",IF(Q15<=N15,"Yes","No")) | S15: =IF(Q15="","",IF(Q15<=N15,0,NETWORKDAYS.INTL(N15,Q15,INDEX(LR_Code,MATCH(B15,LR_Lane,0)),INDEX(DH_Table,0,MATCH(B15&"*",DH_Head,0)))-1)) | U15: =IF(V15<>"",V15,IF(IFERROR(INDEX(RS_Flag,MATCH(B15,RS_Lane,0)),"")="Yes",IF(IFERROR(INDEX(RS_Loc,MATCH(B15,RS_Lane,0)),"")="","Regional stock",IFERROR(INDEX(RS_Loc,MATCH(B15,RS_Lane,0)),"")),"Helmond")) | Y15: =IF(X15<>"",X15,IF(U15="Helmond",IF(COUNTIFS(RC_Lane,B15,RC_Band,E15,RC_CostPS,">0")=0,"",SUMIFS(RC_CostPS,RC_Lane,B15,RC_Band,E15)*(1-SUMIFS(RC_Disc,RC_Lane,B15,RC_Band,E15))),IF(U15="Other","",IF(INDEX(RS_Rate,MATCH(B15,RS_Lane,0))="","",INDEX(RS_Rate,MATCH(B15,RS_Lane,0))))))
A16: B-012 | B16: L01 | C16: Saudi Arabia | D16: Riyadh | E16: B1 0 to 30 kg | F16: 13.8 | G16: =F16*0.006477 | H16: =F16*1.079436 | I16: =MAX(1,ROUNDUP(G16/0.096,0)) | J16: 46401 | K16: =J16-WEEKDAY(J16,2)+1 | L16: =J16 | M16: =INDEX(LR_Target,MATCH(B16,LR_Lane,0)) | N16: =WORKDAY.INTL(L16,M16,INDEX(LR_Code,MATCH(B16,LR_Lane,0)),INDEX(DH_Table,0,MATCH(B16&"*",DH_Head,0))) | O16: =IF(W16<>"",W16,IF(U16="Helmond",IF(COUNTIFS(RC_Lane,B16,RC_Band,E16,RC_Transit,"<>")=0,"",SUMIFS(RC_Transit,RC_Lane,B16,RC_Band,E16)),IF(U16="Other","",IF(INDEX(RS_Transit,MATCH(B16,RS_Lane,0))="","",INDEX(RS_Transit,MATCH(B16,RS_Lane,0)))))) | Q16: =IF(P16<>"",P16,IF(O16="","",WORKDAY.INTL(L16,ROUNDUP(O16,0),INDEX(LR_Code,MATCH(B16,LR_Lane,0)),INDEX(DH_Table,0,MATCH(B16&"*",DH_Head,0))))) | R16: =IF(Q16="","",IF(Q16<=N16,"Yes","No")) | S16: =IF(Q16="","",IF(Q16<=N16,0,NETWORKDAYS.INTL(N16,Q16,INDEX(LR_Code,MATCH(B16,LR_Lane,0)),INDEX(DH_Table,0,MATCH(B16&"*",DH_Head,0)))-1)) | U16: =IF(V16<>"",V16,IF(IFERROR(INDEX(RS_Flag,MATCH(B16,RS_Lane,0)),"")="Yes",IF(IFERROR(INDEX(RS_Loc,MATCH(B16,RS_Lane,0)),"")="","Regional stock",IFERROR(INDEX(RS_Loc,MATCH(B16,RS_Lane,0)),"")),"Helmond")) | Y16: =IF(X16<>"",X16,IF(U16="Helmond",IF(COUNTIFS(RC_Lane,B16,RC_Band,E16,RC_CostPS,">0")=0,"",SUMIFS(RC_CostPS,RC_Lane,B16,RC_Band,E16)*(1-SUMIFS(RC_Disc,RC_Lane,B16,RC_Band,E16))),IF(U16="Other","",IF(INDEX(RS_Rate,MATCH(B16,RS_Lane,0))="","",INDEX(RS_Rate,MATCH(B16,RS_Lane,0))))))
... A333: B-329 | B333: L06 | C333: Morocco | D333: Casablanca area | E333: B4 500 to 2,000 kg | F333: 941.5 | G333: =F333*0.006477 | H333: =F333*1.079436 | I333: =MAX(1,ROUNDUP(G333/0.096,0)) | J333: 46752 | K333: =J333-WEEKDAY(J333,2)+1 | L333: =J333 | M333: =INDEX(LR_Target,MATCH(B333,LR_Lane,0)) | N333: =WORKDAY.INTL(L333,M333,INDEX(LR_Code,MATCH(B333,LR_Lane,0)),INDEX(DH_Table,0,MATCH(B333&"*",DH_Head,0))) | O333: =IF(W333<>"",W333,IF(U333="Helmond",IF(COUNTIFS(RC_Lane,B333,RC_Band,E333,RC_Transit,"<>")=0,"",SUMIFS(RC_Transit,RC_Lane,B333,RC_Band,E333)),IF(U333="Other","",IF(INDEX(RS_Transit,MATCH(B333,RS_Lane,0))="","",INDEX(RS_Transit,MATCH(B333,RS_Lane,0)))))) | Q333: =IF(P333<>"",P333,IF(O333="","",WORKDAY.INTL(L333,ROUNDUP(O333,0),INDEX(LR_Code,MATCH(B333,LR_Lane,0)),INDEX(DH_Table,0,MATCH(B333&"*",DH_Head,0))))) | R333: =IF(Q333="","",IF(Q333<=N333,"Yes","No")) | S333: =IF(Q333="","",IF(Q333<=N333,0,NETWORKDAYS.INTL(N333,Q333,INDEX(LR_Code,MATCH(B333,LR_Lane,0)),INDEX(DH_Table,0,MATCH(B333&"*",DH_Head,0)))-1)) | U333: =IF(V333<>"",V333,IF(IFERROR(INDEX(RS_Flag,MATCH(B333,RS_Lane,0)),"")="Yes",IF(IFERROR(INDEX(RS_Loc,MATCH(B333,RS_Lane,0)),"")="","Regional stock",IFERROR(INDEX(RS_Loc,MATCH(B333,RS_Lane,0)),"")),"Helmond")) | Y333: =IF(X333<>"",X333,IF(U333="Helmond",IF(COUNTIFS(RC_Lane,B333,RC_Band,E333,RC_CostPS,">0")=0,"",SUMIFS(RC_CostPS,RC_Lane,B333,RC_Band,E333)*(1-SUMIFS(RC_Disc,RC_Lane,B333,RC_Band,E333))),IF(U333="Other","",IF(INDEX(RS_Rate,MATCH(B333,RS_Lane,0))="","",INDEX(RS_Rate,MATCH(B333,RS_Lane,0))))))
A334: =COUNTA(A5:A333)&" shipments" | F334: =SUM(F5:F333) | G334: =SUM(G5:G333) | H334: =SUM(H5:H333) | I334: =SUM(I5:I333) | U334: =COUNTIF(U5:U333,"<>Helmond")&" not from Helmond" | Y334: =SUM(Y5:Y333)

Sheet Timeline Summary
A1: Timeline summary: shipments per month and week, and on-time check
A2: Counts come from the two schedule sheets. The on-time check fills in once transit days are on the Rate Card.
A4: Scenario A: shipments per month
A5: Lane | B5: Destination | C5: Jan | D5: Feb | E5: Mar | F5: Apr | G5: May | H5: Jun | I5: Jul | J5: Aug | K5: Sep | L5: Oct | M5: Nov | N5: Dec | O5: Year | P5: Peak month
A6: L01 | B6: Saudi Arabia | C6: =COUNTIFS(SA_Lane,$A6,SA_Date,">="&DATE(2027,1,1),SA_Date,"<"&DATE(2027,2,1)) | D6: =COUNTIFS(SA_Lane,$A6,SA_Date,">="&DATE(2027,2,1),SA_Date,"<"&DATE(2027,3,1)) | E6: =COUNTIFS(SA_Lane,$A6,SA_Date,">="&DATE(2027,3,1),SA_Date,"<"&DATE(2027,4,1)) | F6: =COUNTIFS(SA_Lane,$A6,SA_Date,">="&DATE(2027,4,1),SA_Date,"<"&DATE(2027,5,1)) | G6: =COUNTIFS(SA_Lane,$A6,SA_Date,">="&DATE(2027,5,1),SA_Date,"<"&DATE(2027,6,1)) | H6: =COUNTIFS(SA_Lane,$A6,SA_Date,">="&DATE(2027,6,1),SA_Date,"<"&DATE(2027,7,1)) | I6: =COUNTIFS(SA_Lane,$A6,SA_Date,">="&DATE(2027,7,1),SA_Date,"<"&DATE(2027,8,1)) | J6: =COUNTIFS(SA_Lane,$A6,SA_Date,">="&DATE(2027,8,1),SA_Date,"<"&DATE(2027,9,1)) | K6: =COUNTIFS(SA_Lane,$A6,SA_Date,">="&DATE(2027,9,1),SA_Date,"<"&DATE(2027,10,1)) | L6: =COUNTIFS(SA_Lane,$A6,SA_Date,">="&DATE(2027,10,1),SA_Date,"<"&DATE(2027,11,1)) | M6: =COUNTIFS(SA_Lane,$A6,SA_Date,">="&DATE(2027,11,1),SA_Date,"<"&DATE(2027,12,1)) | N6: =COUNTIFS(SA_Lane,$A6,SA_Date,">="&DATE(2027,12,1),SA_Date,"<"&DATE(2028,1,1)) | O6: =SUM(C6:N6) | P6: =MAX(C6:N6)
A7: L02 | B7: United Arab Emirates | C7: =COUNTIFS(SA_Lane,$A7,SA_Date,">="&DATE(2027,1,1),SA_Date,"<"&DATE(2027,2,1)) | D7: =COUNTIFS(SA_Lane,$A7,SA_Date,">="&DATE(2027,2,1),SA_Date,"<"&DATE(2027,3,1)) | E7: =COUNTIFS(SA_Lane,$A7,SA_Date,">="&DATE(2027,3,1),SA_Date,"<"&DATE(2027,4,1)) | F7: =COUNTIFS(SA_Lane,$A7,SA_Date,">="&DATE(2027,4,1),SA_Date,"<"&DATE(2027,5,1)) | G7: =COUNTIFS(SA_Lane,$A7,SA_Date,">="&DATE(2027,5,1),SA_Date,"<"&DATE(2027,6,1)) | H7: =COUNTIFS(SA_Lane,$A7,SA_Date,">="&DATE(2027,6,1),SA_Date,"<"&DATE(2027,7,1)) | I7: =COUNTIFS(SA_Lane,$A7,SA_Date,">="&DATE(2027,7,1),SA_Date,"<"&DATE(2027,8,1)) | J7: =COUNTIFS(SA_Lane,$A7,SA_Date,">="&DATE(2027,8,1),SA_Date,"<"&DATE(2027,9,1)) | K7: =COUNTIFS(SA_Lane,$A7,SA_Date,">="&DATE(2027,9,1),SA_Date,"<"&DATE(2027,10,1)) | L7: =COUNTIFS(SA_Lane,$A7,SA_Date,">="&DATE(2027,10,1),SA_Date,"<"&DATE(2027,11,1)) | M7: =COUNTIFS(SA_Lane,$A7,SA_Date,">="&DATE(2027,11,1),SA_Date,"<"&DATE(2027,12,1)) | N7: =COUNTIFS(SA_Lane,$A7,SA_Date,">="&DATE(2027,12,1),SA_Date,"<"&DATE(2028,1,1)) | O7: =SUM(C7:N7) | P7: =MAX(C7:N7)
A8: L03 | B8: Kuwait | C8: =COUNTIFS(SA_Lane,$A8,SA_Date,">="&DATE(2027,1,1),SA_Date,"<"&DATE(2027,2,1)) | D8: =COUNTIFS(SA_Lane,$A8,SA_Date,">="&DATE(2027,2,1),SA_Date,"<"&DATE(2027,3,1)) | E8: =COUNTIFS(SA_Lane,$A8,SA_Date,">="&DATE(2027,3,1),SA_Date,"<"&DATE(2027,4,1)) | F8: =COUNTIFS(SA_Lane,$A8,SA_Date,">="&DATE(2027,4,1),SA_Date,"<"&DATE(2027,5,1)) | G8: =COUNTIFS(SA_Lane,$A8,SA_Date,">="&DATE(2027,5,1),SA_Date,"<"&DATE(2027,6,1)) | H8: =COUNTIFS(SA_Lane,$A8,SA_Date,">="&DATE(2027,6,1),SA_Date,"<"&DATE(2027,7,1)) | I8: =COUNTIFS(SA_Lane,$A8,SA_Date,">="&DATE(2027,7,1),SA_Date,"<"&DATE(2027,8,1)) | J8: =COUNTIFS(SA_Lane,$A8,SA_Date,">="&DATE(2027,8,1),SA_Date,"<"&DATE(2027,9,1)) | K8: =COUNTIFS(SA_Lane,$A8,SA_Date,">="&DATE(2027,9,1),SA_Date,"<"&DATE(2027,10,1)) | L8: =COUNTIFS(SA_Lane,$A8,SA_Date,">="&DATE(2027,10,1),SA_Date,"<"&DATE(2027,11,1)) | M8: =COUNTIFS(SA_Lane,$A8,SA_Date,">="&DATE(2027,11,1),SA_Date,"<"&DATE(2027,12,1)) | N8: =COUNTIFS(SA_Lane,$A8,SA_Date,">="&DATE(2027,12,1),SA_Date,"<"&DATE(2028,1,1)) | O8: =SUM(C8:N8) | P8: =MAX(C8:N8)
A9: L04 | B9: Qatar | C9: =COUNTIFS(SA_Lane,$A9,SA_Date,">="&DATE(2027,1,1),SA_Date,"<"&DATE(2027,2,1)) | D9: =COUNTIFS(SA_Lane,$A9,SA_Date,">="&DATE(2027,2,1),SA_Date,"<"&DATE(2027,3,1)) | E9: =COUNTIFS(SA_Lane,$A9,SA_Date,">="&DATE(2027,3,1),SA_Date,"<"&DATE(2027,4,1)) | F9: =COUNTIFS(SA_Lane,$A9,SA_Date,">="&DATE(2027,4,1),SA_Date,"<"&DATE(2027,5,1)) | G9: =COUNTIFS(SA_Lane,$A9,SA_Date,">="&DATE(2027,5,1),SA_Date,"<"&DATE(2027,6,1)) | H9: =COUNTIFS(SA_Lane,$A9,SA_Date,">="&DATE(2027,6,1),SA_Date,"<"&DATE(2027,7,1)) | I9: =COUNTIFS(SA_Lane,$A9,SA_Date,">="&DATE(2027,7,1),SA_Date,"<"&DATE(2027,8,1)) | J9: =COUNTIFS(SA_Lane,$A9,SA_Date,">="&DATE(2027,8,1),SA_Date,"<"&DATE(2027,9,1)) | K9: =COUNTIFS(SA_Lane,$A9,SA_Date,">="&DATE(2027,9,1),SA_Date,"<"&DATE(2027,10,1)) | L9: =COUNTIFS(SA_Lane,$A9,SA_Date,">="&DATE(2027,10,1),SA_Date,"<"&DATE(2027,11,1)) | M9: =COUNTIFS(SA_Lane,$A9,SA_Date,">="&DATE(2027,11,1),SA_Date,"<"&DATE(2027,12,1)) | N9: =COUNTIFS(SA_Lane,$A9,SA_Date,">="&DATE(2027,12,1),SA_Date,"<"&DATE(2028,1,1)) | O9: =SUM(C9:N9) | P9: =MAX(C9:N9)
A10: L05 | B10: Türkiye | C10: =COUNTIFS(SA_Lane,$A10,SA_Date,">="&DATE(2027,1,1),SA_Date,"<"&DATE(2027,2,1)) | D10: =COUNTIFS(SA_Lane,$A10,SA_Date,">="&DATE(2027,2,1),SA_Date,"<"&DATE(2027,3,1)) | E10: =COUNTIFS(SA_Lane,$A10,SA_Date,">="&DATE(2027,3,1),SA_Date,"<"&DATE(2027,4,1)) | F10: =COUNTIFS(SA_Lane,$A10,SA_Date,">="&DATE(2027,4,1),SA_Date,"<"&DATE(2027,5,1)) | G10: =COUNTIFS(SA_Lane,$A10,SA_Date,">="&DATE(2027,5,1),SA_Date,"<"&DATE(2027,6,1)) | H10: =COUNTIFS(SA_Lane,$A10,SA_Date,">="&DATE(2027,6,1),SA_Date,"<"&DATE(2027,7,1)) | I10: =COUNTIFS(SA_Lane,$A10,SA_Date,">="&DATE(2027,7,1),SA_Date,"<"&DATE(2027,8,1)) | J10: =COUNTIFS(SA_Lane,$A10,SA_Date,">="&DATE(2027,8,1),SA_Date,"<"&DATE(2027,9,1)) | K10: =COUNTIFS(SA_Lane,$A10,SA_Date,">="&DATE(2027,9,1),SA_Date,"<"&DATE(2027,10,1)) | L10: =COUNTIFS(SA_Lane,$A10,SA_Date,">="&DATE(2027,10,1),SA_Date,"<"&DATE(2027,11,1)) | M10: =COUNTIFS(SA_Lane,$A10,SA_Date,">="&DATE(2027,11,1),SA_Date,"<"&DATE(2027,12,1)) | N10: =COUNTIFS(SA_Lane,$A10,SA_Date,">="&DATE(2027,12,1),SA_Date,"<"&DATE(2028,1,1)) | O10: =SUM(C10:N10) | P10: =MAX(C10:N10)
A11: L06 | B11: Morocco | C11: =COUNTIFS(SA_Lane,$A11,SA_Date,">="&DATE(2027,1,1),SA_Date,"<"&DATE(2027,2,1)) | D11: =COUNTIFS(SA_Lane,$A11,SA_Date,">="&DATE(2027,2,1),SA_Date,"<"&DATE(2027,3,1)) | E11: =COUNTIFS(SA_Lane,$A11,SA_Date,">="&DATE(2027,3,1),SA_Date,"<"&DATE(2027,4,1)) | F11: =COUNTIFS(SA_Lane,$A11,SA_Date,">="&DATE(2027,4,1),SA_Date,"<"&DATE(2027,5,1)) | G11: =COUNTIFS(SA_Lane,$A11,SA_Date,">="&DATE(2027,5,1),SA_Date,"<"&DATE(2027,6,1)) | H11: =COUNTIFS(SA_Lane,$A11,SA_Date,">="&DATE(2027,6,1),SA_Date,"<"&DATE(2027,7,1)) | I11: =COUNTIFS(SA_Lane,$A11,SA_Date,">="&DATE(2027,7,1),SA_Date,"<"&DATE(2027,8,1)) | J11: =COUNTIFS(SA_Lane,$A11,SA_Date,">="&DATE(2027,8,1),SA_Date,"<"&DATE(2027,9,1)) | K11: =COUNTIFS(SA_Lane,$A11,SA_Date,">="&DATE(2027,9,1),SA_Date,"<"&DATE(2027,10,1)) | L11: =COUNTIFS(SA_Lane,$A11,SA_Date,">="&DATE(2027,10,1),SA_Date,"<"&DATE(2027,11,1)) | M11: =COUNTIFS(SA_Lane,$A11,SA_Date,">="&DATE(2027,11,1),SA_Date,"<"&DATE(2027,12,1)) | N11: =COUNTIFS(SA_Lane,$A11,SA_Date,">="&DATE(2027,12,1),SA_Date,"<"&DATE(2028,1,1)) | O11: =SUM(C11:N11) | P11: =MAX(C11:N11)
A12: L07 | B12: Algeria | C12: =COUNTIFS(SA_Lane,$A12,SA_Date,">="&DATE(2027,1,1),SA_Date,"<"&DATE(2027,2,1)) | D12: =COUNTIFS(SA_Lane,$A12,SA_Date,">="&DATE(2027,2,1),SA_Date,"<"&DATE(2027,3,1)) | E12: =COUNTIFS(SA_Lane,$A12,SA_Date,">="&DATE(2027,3,1),SA_Date,"<"&DATE(2027,4,1)) | F12: =COUNTIFS(SA_Lane,$A12,SA_Date,">="&DATE(2027,4,1),SA_Date,"<"&DATE(2027,5,1)) | G12: =COUNTIFS(SA_Lane,$A12,SA_Date,">="&DATE(2027,5,1),SA_Date,"<"&DATE(2027,6,1)) | H12: =COUNTIFS(SA_Lane,$A12,SA_Date,">="&DATE(2027,6,1),SA_Date,"<"&DATE(2027,7,1)) | I12: =COUNTIFS(SA_Lane,$A12,SA_Date,">="&DATE(2027,7,1),SA_Date,"<"&DATE(2027,8,1)) | J12: =COUNTIFS(SA_Lane,$A12,SA_Date,">="&DATE(2027,8,1),SA_Date,"<"&DATE(2027,9,1)) | K12: =COUNTIFS(SA_Lane,$A12,SA_Date,">="&DATE(2027,9,1),SA_Date,"<"&DATE(2027,10,1)) | L12: =COUNTIFS(SA_Lane,$A12,SA_Date,">="&DATE(2027,10,1),SA_Date,"<"&DATE(2027,11,1)) | M12: =COUNTIFS(SA_Lane,$A12,SA_Date,">="&DATE(2027,11,1),SA_Date,"<"&DATE(2027,12,1)) | N12: =COUNTIFS(SA_Lane,$A12,SA_Date,">="&DATE(2027,12,1),SA_Date,"<"&DATE(2028,1,1)) | O12: =SUM(C12:N12) | P12: =MAX(C12:N12)
A13: L08 | B13: Egypt | C13: =COUNTIFS(SA_Lane,$A13,SA_Date,">="&DATE(2027,1,1),SA_Date,"<"&DATE(2027,2,1)) | D13: =COUNTIFS(SA_Lane,$A13,SA_Date,">="&DATE(2027,2,1),SA_Date,"<"&DATE(2027,3,1)) | E13: =COUNTIFS(SA_Lane,$A13,SA_Date,">="&DATE(2027,3,1),SA_Date,"<"&DATE(2027,4,1)) | F13: =COUNTIFS(SA_Lane,$A13,SA_Date,">="&DATE(2027,4,1),SA_Date,"<"&DATE(2027,5,1)) | G13: =COUNTIFS(SA_Lane,$A13,SA_Date,">="&DATE(2027,5,1),SA_Date,"<"&DATE(2027,6,1)) | H13: =COUNTIFS(SA_Lane,$A13,SA_Date,">="&DATE(2027,6,1),SA_Date,"<"&DATE(2027,7,1)) | I13: =COUNTIFS(SA_Lane,$A13,SA_Date,">="&DATE(2027,7,1),SA_Date,"<"&DATE(2027,8,1)) | J13: =COUNTIFS(SA_Lane,$A13,SA_Date,">="&DATE(2027,8,1),SA_Date,"<"&DATE(2027,9,1)) | K13: =COUNTIFS(SA_Lane,$A13,SA_Date,">="&DATE(2027,9,1),SA_Date,"<"&DATE(2027,10,1)) | L13: =COUNTIFS(SA_Lane,$A13,SA_Date,">="&DATE(2027,10,1),SA_Date,"<"&DATE(2027,11,1)) | M13: =COUNTIFS(SA_Lane,$A13,SA_Date,">="&DATE(2027,11,1),SA_Date,"<"&DATE(2027,12,1)) | N13: =COUNTIFS(SA_Lane,$A13,SA_Date,">="&DATE(2027,12,1),SA_Date,"<"&DATE(2028,1,1)) | O13: =SUM(C13:N13) | P13: =MAX(C13:N13)
A14: L09 | B14: Tunisia | C14: =COUNTIFS(SA_Lane,$A14,SA_Date,">="&DATE(2027,1,1),SA_Date,"<"&DATE(2027,2,1)) | D14: =COUNTIFS(SA_Lane,$A14,SA_Date,">="&DATE(2027,2,1),SA_Date,"<"&DATE(2027,3,1)) | E14: =COUNTIFS(SA_Lane,$A14,SA_Date,">="&DATE(2027,3,1),SA_Date,"<"&DATE(2027,4,1)) | F14: =COUNTIFS(SA_Lane,$A14,SA_Date,">="&DATE(2027,4,1),SA_Date,"<"&DATE(2027,5,1)) | G14: =COUNTIFS(SA_Lane,$A14,SA_Date,">="&DATE(2027,5,1),SA_Date,"<"&DATE(2027,6,1)) | H14: =COUNTIFS(SA_Lane,$A14,SA_Date,">="&DATE(2027,6,1),SA_Date,"<"&DATE(2027,7,1)) | I14: =COUNTIFS(SA_Lane,$A14,SA_Date,">="&DATE(2027,7,1),SA_Date,"<"&DATE(2027,8,1)) | J14: =COUNTIFS(SA_Lane,$A14,SA_Date,">="&DATE(2027,8,1),SA_Date,"<"&DATE(2027,9,1)) | K14: =COUNTIFS(SA_Lane,$A14,SA_Date,">="&DATE(2027,9,1),SA_Date,"<"&DATE(2027,10,1)) | L14: =COUNTIFS(SA_Lane,$A14,SA_Date,">="&DATE(2027,10,1),SA_Date,"<"&DATE(2027,11,1)) | M14: =COUNTIFS(SA_Lane,$A14,SA_Date,">="&DATE(2027,11,1),SA_Date,"<"&DATE(2027,12,1)) | N14: =COUNTIFS(SA_Lane,$A14,SA_Date,">="&DATE(2027,12,1),SA_Date,"<"&DATE(2028,1,1)) | O14: =SUM(C14:N14) | P14: =MAX(C14:N14)
A15: Total | C15: =SUM(C6:C14) | D15: =SUM(D6:D14) | E15: =SUM(E6:E14) | F15: =SUM(F6:F14) | G15: =SUM(G6:G14) | H15: =SUM(H6:H14) | I15: =SUM(I6:I14) | J15: =SUM(J6:J14) | ... O15: =SUM(O6:O14) | P15: =MAX(C15:N15)
A16: Chargeable kg | C16: =SUMIFS(SA_Chg,SA_Date,">="&DATE(2027,1,1),SA_Date,"<"&DATE(2027,2,1)) | D16: =SUMIFS(SA_Chg,SA_Date,">="&DATE(2027,2,1),SA_Date,"<"&DATE(2027,3,1)) | E16: =SUMIFS(SA_Chg,SA_Date,">="&DATE(2027,3,1),SA_Date,"<"&DATE(2027,4,1)) | F16: =SUMIFS(SA_Chg,SA_Date,">="&DATE(2027,4,1),SA_Date,"<"&DATE(2027,5,1)) | G16: =SUMIFS(SA_Chg,SA_Date,">="&DATE(2027,5,1),SA_Date,"<"&DATE(2027,6,1)) | H16: =SUMIFS(SA_Chg,SA_Date,">="&DATE(2027,6,1),SA_Date,"<"&DATE(2027,7,1)) | I16: =SUMIFS(SA_Chg,SA_Date,">="&DATE(2027,7,1),SA_Date,"<"&DATE(2027,8,1)) | J16: =SUMIFS(SA_Chg,SA_Date,">="&DATE(2027,8,1),SA_Date,"<"&DATE(2027,9,1)) | K16: =SUMIFS(SA_Chg,SA_Date,">="&DATE(2027,9,1),SA_Date,"<"&DATE(2027,10,1)) | L16: =SUMIFS(SA_Chg,SA_Date,">="&DATE(2027,10,1),SA_Date,"<"&DATE(2027,11,1)) | M16: =SUMIFS(SA_Chg,SA_Date,">="&DATE(2027,11,1),SA_Date,"<"&DATE(2027,12,1)) | N16: =SUMIFS(SA_Chg,SA_Date,">="&DATE(2027,12,1),SA_Date,"<"&DATE(2028,1,1)) | O16: =SUM(C16:N16) | P16: =MAX(C16:N16)
A18: Scenario B: shipments per month
A19: Lane | B19: Destination | C19: Jan | D19: Feb | E19: Mar | F19: Apr | G19: May | H19: Jun | I19: Jul | J19: Aug | K19: Sep | L19: Oct | M19: Nov | N19: Dec | O19: Year | P19: Peak month
A20: L01 | B20: Saudi Arabia | C20: =COUNTIFS(SB_Lane,$A20,SB_Date,">="&DATE(2027,1,1),SB_Date,"<"&DATE(2027,2,1)) | D20: =COUNTIFS(SB_Lane,$A20,SB_Date,">="&DATE(2027,2,1),SB_Date,"<"&DATE(2027,3,1)) | E20: =COUNTIFS(SB_Lane,$A20,SB_Date,">="&DATE(2027,3,1),SB_Date,"<"&DATE(2027,4,1)) | F20: =COUNTIFS(SB_Lane,$A20,SB_Date,">="&DATE(2027,4,1),SB_Date,"<"&DATE(2027,5,1)) | G20: =COUNTIFS(SB_Lane,$A20,SB_Date,">="&DATE(2027,5,1),SB_Date,"<"&DATE(2027,6,1)) | H20: =COUNTIFS(SB_Lane,$A20,SB_Date,">="&DATE(2027,6,1),SB_Date,"<"&DATE(2027,7,1)) | I20: =COUNTIFS(SB_Lane,$A20,SB_Date,">="&DATE(2027,7,1),SB_Date,"<"&DATE(2027,8,1)) | J20: =COUNTIFS(SB_Lane,$A20,SB_Date,">="&DATE(2027,8,1),SB_Date,"<"&DATE(2027,9,1)) | K20: =COUNTIFS(SB_Lane,$A20,SB_Date,">="&DATE(2027,9,1),SB_Date,"<"&DATE(2027,10,1)) | L20: =COUNTIFS(SB_Lane,$A20,SB_Date,">="&DATE(2027,10,1),SB_Date,"<"&DATE(2027,11,1)) | M20: =COUNTIFS(SB_Lane,$A20,SB_Date,">="&DATE(2027,11,1),SB_Date,"<"&DATE(2027,12,1)) | N20: =COUNTIFS(SB_Lane,$A20,SB_Date,">="&DATE(2027,12,1),SB_Date,"<"&DATE(2028,1,1)) | O20: =SUM(C20:N20) | P20: =MAX(C20:N20)
A21: L02 | B21: United Arab Emirates | C21: =COUNTIFS(SB_Lane,$A21,SB_Date,">="&DATE(2027,1,1),SB_Date,"<"&DATE(2027,2,1)) | D21: =COUNTIFS(SB_Lane,$A21,SB_Date,">="&DATE(2027,2,1),SB_Date,"<"&DATE(2027,3,1)) | E21: =COUNTIFS(SB_Lane,$A21,SB_Date,">="&DATE(2027,3,1),SB_Date,"<"&DATE(2027,4,1)) | F21: =COUNTIFS(SB_Lane,$A21,SB_Date,">="&DATE(2027,4,1),SB_Date,"<"&DATE(2027,5,1)) | G21: =COUNTIFS(SB_Lane,$A21,SB_Date,">="&DATE(2027,5,1),SB_Date,"<"&DATE(2027,6,1)) | H21: =COUNTIFS(SB_Lane,$A21,SB_Date,">="&DATE(2027,6,1),SB_Date,"<"&DATE(2027,7,1)) | I21: =COUNTIFS(SB_Lane,$A21,SB_Date,">="&DATE(2027,7,1),SB_Date,"<"&DATE(2027,8,1)) | J21: =COUNTIFS(SB_Lane,$A21,SB_Date,">="&DATE(2027,8,1),SB_Date,"<"&DATE(2027,9,1)) | K21: =COUNTIFS(SB_Lane,$A21,SB_Date,">="&DATE(2027,9,1),SB_Date,"<"&DATE(2027,10,1)) | L21: =COUNTIFS(SB_Lane,$A21,SB_Date,">="&DATE(2027,10,1),SB_Date,"<"&DATE(2027,11,1)) | M21: =COUNTIFS(SB_Lane,$A21,SB_Date,">="&DATE(2027,11,1),SB_Date,"<"&DATE(2027,12,1)) | N21: =COUNTIFS(SB_Lane,$A21,SB_Date,">="&DATE(2027,12,1),SB_Date,"<"&DATE(2028,1,1)) | O21: =SUM(C21:N21) | P21: =MAX(C21:N21)
A22: L03 | B22: Kuwait | C22: =COUNTIFS(SB_Lane,$A22,SB_Date,">="&DATE(2027,1,1),SB_Date,"<"&DATE(2027,2,1)) | D22: =COUNTIFS(SB_Lane,$A22,SB_Date,">="&DATE(2027,2,1),SB_Date,"<"&DATE(2027,3,1)) | E22: =COUNTIFS(SB_Lane,$A22,SB_Date,">="&DATE(2027,3,1),SB_Date,"<"&DATE(2027,4,1)) | F22: =COUNTIFS(SB_Lane,$A22,SB_Date,">="&DATE(2027,4,1),SB_Date,"<"&DATE(2027,5,1)) | G22: =COUNTIFS(SB_Lane,$A22,SB_Date,">="&DATE(2027,5,1),SB_Date,"<"&DATE(2027,6,1)) | H22: =COUNTIFS(SB_Lane,$A22,SB_Date,">="&DATE(2027,6,1),SB_Date,"<"&DATE(2027,7,1)) | I22: =COUNTIFS(SB_Lane,$A22,SB_Date,">="&DATE(2027,7,1),SB_Date,"<"&DATE(2027,8,1)) | J22: =COUNTIFS(SB_Lane,$A22,SB_Date,">="&DATE(2027,8,1),SB_Date,"<"&DATE(2027,9,1)) | K22: =COUNTIFS(SB_Lane,$A22,SB_Date,">="&DATE(2027,9,1),SB_Date,"<"&DATE(2027,10,1)) | L22: =COUNTIFS(SB_Lane,$A22,SB_Date,">="&DATE(2027,10,1),SB_Date,"<"&DATE(2027,11,1)) | M22: =COUNTIFS(SB_Lane,$A22,SB_Date,">="&DATE(2027,11,1),SB_Date,"<"&DATE(2027,12,1)) | N22: =COUNTIFS(SB_Lane,$A22,SB_Date,">="&DATE(2027,12,1),SB_Date,"<"&DATE(2028,1,1)) | O22: =SUM(C22:N22) | P22: =MAX(C22:N22)
A23: L04 | B23: Qatar | C23: =COUNTIFS(SB_Lane,$A23,SB_Date,">="&DATE(2027,1,1),SB_Date,"<"&DATE(2027,2,1)) | D23: =COUNTIFS(SB_Lane,$A23,SB_Date,">="&DATE(2027,2,1),SB_Date,"<"&DATE(2027,3,1)) | E23: =COUNTIFS(SB_Lane,$A23,SB_Date,">="&DATE(2027,3,1),SB_Date,"<"&DATE(2027,4,1)) | F23: =COUNTIFS(SB_Lane,$A23,SB_Date,">="&DATE(2027,4,1),SB_Date,"<"&DATE(2027,5,1)) | G23: =COUNTIFS(SB_Lane,$A23,SB_Date,">="&DATE(2027,5,1),SB_Date,"<"&DATE(2027,6,1)) | H23: =COUNTIFS(SB_Lane,$A23,SB_Date,">="&DATE(2027,6,1),SB_Date,"<"&DATE(2027,7,1)) | I23: =COUNTIFS(SB_Lane,$A23,SB_Date,">="&DATE(2027,7,1),SB_Date,"<"&DATE(2027,8,1)) | J23: =COUNTIFS(SB_Lane,$A23,SB_Date,">="&DATE(2027,8,1),SB_Date,"<"&DATE(2027,9,1)) | K23: =COUNTIFS(SB_Lane,$A23,SB_Date,">="&DATE(2027,9,1),SB_Date,"<"&DATE(2027,10,1)) | L23: =COUNTIFS(SB_Lane,$A23,SB_Date,">="&DATE(2027,10,1),SB_Date,"<"&DATE(2027,11,1)) | M23: =COUNTIFS(SB_Lane,$A23,SB_Date,">="&DATE(2027,11,1),SB_Date,"<"&DATE(2027,12,1)) | N23: =COUNTIFS(SB_Lane,$A23,SB_Date,">="&DATE(2027,12,1),SB_Date,"<"&DATE(2028,1,1)) | O23: =SUM(C23:N23) | P23: =MAX(C23:N23)
A24: L05 | B24: Türkiye | C24: =COUNTIFS(SB_Lane,$A24,SB_Date,">="&DATE(2027,1,1),SB_Date,"<"&DATE(2027,2,1)) | D24: =COUNTIFS(SB_Lane,$A24,SB_Date,">="&DATE(2027,2,1),SB_Date,"<"&DATE(2027,3,1)) | E24: =COUNTIFS(SB_Lane,$A24,SB_Date,">="&DATE(2027,3,1),SB_Date,"<"&DATE(2027,4,1)) | F24: =COUNTIFS(SB_Lane,$A24,SB_Date,">="&DATE(2027,4,1),SB_Date,"<"&DATE(2027,5,1)) | G24: =COUNTIFS(SB_Lane,$A24,SB_Date,">="&DATE(2027,5,1),SB_Date,"<"&DATE(2027,6,1)) | H24: =COUNTIFS(SB_Lane,$A24,SB_Date,">="&DATE(2027,6,1),SB_Date,"<"&DATE(2027,7,1)) | I24: =COUNTIFS(SB_Lane,$A24,SB_Date,">="&DATE(2027,7,1),SB_Date,"<"&DATE(2027,8,1)) | J24: =COUNTIFS(SB_Lane,$A24,SB_Date,">="&DATE(2027,8,1),SB_Date,"<"&DATE(2027,9,1)) | K24: =COUNTIFS(SB_Lane,$A24,SB_Date,">="&DATE(2027,9,1),SB_Date,"<"&DATE(2027,10,1)) | L24: =COUNTIFS(SB_Lane,$A24,SB_Date,">="&DATE(2027,10,1),SB_Date,"<"&DATE(2027,11,1)) | M24: =COUNTIFS(SB_Lane,$A24,SB_Date,">="&DATE(2027,11,1),SB_Date,"<"&DATE(2027,12,1)) | N24: =COUNTIFS(SB_Lane,$A24,SB_Date,">="&DATE(2027,12,1),SB_Date,"<"&DATE(2028,1,1)) | O24: =SUM(C24:N24) | P24: =MAX(C24:N24)
A25: L06 | B25: Morocco | C25: =COUNTIFS(SB_Lane,$A25,SB_Date,">="&DATE(2027,1,1),SB_Date,"<"&DATE(2027,2,1)) | D25: =COUNTIFS(SB_Lane,$A25,SB_Date,">="&DATE(2027,2,1),SB_Date,"<"&DATE(2027,3,1)) | E25: =COUNTIFS(SB_Lane,$A25,SB_Date,">="&DATE(2027,3,1),SB_Date,"<"&DATE(2027,4,1)) | F25: =COUNTIFS(SB_Lane,$A25,SB_Date,">="&DATE(2027,4,1),SB_Date,"<"&DATE(2027,5,1)) | G25: =COUNTIFS(SB_Lane,$A25,SB_Date,">="&DATE(2027,5,1),SB_Date,"<"&DATE(2027,6,1)) | H25: =COUNTIFS(SB_Lane,$A25,SB_Date,">="&DATE(2027,6,1),SB_Date,"<"&DATE(2027,7,1)) | I25: =COUNTIFS(SB_Lane,$A25,SB_Date,">="&DATE(2027,7,1),SB_Date,"<"&DATE(2027,8,1)) | J25: =COUNTIFS(SB_Lane,$A25,SB_Date,">="&DATE(2027,8,1),SB_Date,"<"&DATE(2027,9,1)) | K25: =COUNTIFS(SB_Lane,$A25,SB_Date,">="&DATE(2027,9,1),SB_Date,"<"&DATE(2027,10,1)) | L25: =COUNTIFS(SB_Lane,$A25,SB_Date,">="&DATE(2027,10,1),SB_Date,"<"&DATE(2027,11,1)) | M25: =COUNTIFS(SB_Lane,$A25,SB_Date,">="&DATE(2027,11,1),SB_Date,"<"&DATE(2027,12,1)) | N25: =COUNTIFS(SB_Lane,$A25,SB_Date,">="&DATE(2027,12,1),SB_Date,"<"&DATE(2028,1,1)) | O25: =SUM(C25:N25) | P25: =MAX(C25:N25)
A26: L07 | B26: Algeria | C26: =COUNTIFS(SB_Lane,$A26,SB_Date,">="&DATE(2027,1,1),SB_Date,"<"&DATE(2027,2,1)) | D26: =COUNTIFS(SB_Lane,$A26,SB_Date,">="&DATE(2027,2,1),SB_Date,"<"&DATE(2027,3,1)) | E26: =COUNTIFS(SB_Lane,$A26,SB_Date,">="&DATE(2027,3,1),SB_Date,"<"&DATE(2027,4,1)) | F26: =COUNTIFS(SB_Lane,$A26,SB_Date,">="&DATE(2027,4,1),SB_Date,"<"&DATE(2027,5,1)) | G26: =COUNTIFS(SB_Lane,$A26,SB_Date,">="&DATE(2027,5,1),SB_Date,"<"&DATE(2027,6,1)) | H26: =COUNTIFS(SB_Lane,$A26,SB_Date,">="&DATE(2027,6,1),SB_Date,"<"&DATE(2027,7,1)) | I26: =COUNTIFS(SB_Lane,$A26,SB_Date,">="&DATE(2027,7,1),SB_Date,"<"&DATE(2027,8,1)) | J26: =COUNTIFS(SB_Lane,$A26,SB_Date,">="&DATE(2027,8,1),SB_Date,"<"&DATE(2027,9,1)) | K26: =COUNTIFS(SB_Lane,$A26,SB_Date,">="&DATE(2027,9,1),SB_Date,"<"&DATE(2027,10,1)) | L26: =COUNTIFS(SB_Lane,$A26,SB_Date,">="&DATE(2027,10,1),SB_Date,"<"&DATE(2027,11,1)) | M26: =COUNTIFS(SB_Lane,$A26,SB_Date,">="&DATE(2027,11,1),SB_Date,"<"&DATE(2027,12,1)) | N26: =COUNTIFS(SB_Lane,$A26,SB_Date,">="&DATE(2027,12,1),SB_Date,"<"&DATE(2028,1,1)) | O26: =SUM(C26:N26) | P26: =MAX(C26:N26)
A27: L08 | B27: Egypt | C27: =COUNTIFS(SB_Lane,$A27,SB_Date,">="&DATE(2027,1,1),SB_Date,"<"&DATE(2027,2,1)) | D27: =COUNTIFS(SB_Lane,$A27,SB_Date,">="&DATE(2027,2,1),SB_Date,"<"&DATE(2027,3,1)) | E27: =COUNTIFS(SB_Lane,$A27,SB_Date,">="&DATE(2027,3,1),SB_Date,"<"&DATE(2027,4,1)) | F27: =COUNTIFS(SB_Lane,$A27,SB_Date,">="&DATE(2027,4,1),SB_Date,"<"&DATE(2027,5,1)) | G27: =COUNTIFS(SB_Lane,$A27,SB_Date,">="&DATE(2027,5,1),SB_Date,"<"&DATE(2027,6,1)) | H27: =COUNTIFS(SB_Lane,$A27,SB_Date,">="&DATE(2027,6,1),SB_Date,"<"&DATE(2027,7,1)) | I27: =COUNTIFS(SB_Lane,$A27,SB_Date,">="&DATE(2027,7,1),SB_Date,"<"&DATE(2027,8,1)) | J27: =COUNTIFS(SB_Lane,$A27,SB_Date,">="&DATE(2027,8,1),SB_Date,"<"&DATE(2027,9,1)) | K27: =COUNTIFS(SB_Lane,$A27,SB_Date,">="&DATE(2027,9,1),SB_Date,"<"&DATE(2027,10,1)) | L27: =COUNTIFS(SB_Lane,$A27,SB_Date,">="&DATE(2027,10,1),SB_Date,"<"&DATE(2027,11,1)) | M27: =COUNTIFS(SB_Lane,$A27,SB_Date,">="&DATE(2027,11,1),SB_Date,"<"&DATE(2027,12,1)) | N27: =COUNTIFS(SB_Lane,$A27,SB_Date,">="&DATE(2027,12,1),SB_Date,"<"&DATE(2028,1,1)) | O27: =SUM(C27:N27) | P27: =MAX(C27:N27)
A28: L09 | B28: Tunisia | C28: =COUNTIFS(SB_Lane,$A28,SB_Date,">="&DATE(2027,1,1),SB_Date,"<"&DATE(2027,2,1)) | D28: =COUNTIFS(SB_Lane,$A28,SB_Date,">="&DATE(2027,2,1),SB_Date,"<"&DATE(2027,3,1)) | E28: =COUNTIFS(SB_Lane,$A28,SB_Date,">="&DATE(2027,3,1),SB_Date,"<"&DATE(2027,4,1)) | F28: =COUNTIFS(SB_Lane,$A28,SB_Date,">="&DATE(2027,4,1),SB_Date,"<"&DATE(2027,5,1)) | G28: =COUNTIFS(SB_Lane,$A28,SB_Date,">="&DATE(2027,5,1),SB_Date,"<"&DATE(2027,6,1)) | H28: =COUNTIFS(SB_Lane,$A28,SB_Date,">="&DATE(2027,6,1),SB_Date,"<"&DATE(2027,7,1)) | I28: =COUNTIFS(SB_Lane,$A28,SB_Date,">="&DATE(2027,7,1),SB_Date,"<"&DATE(2027,8,1)) | J28: =COUNTIFS(SB_Lane,$A28,SB_Date,">="&DATE(2027,8,1),SB_Date,"<"&DATE(2027,9,1)) | K28: =COUNTIFS(SB_Lane,$A28,SB_Date,">="&DATE(2027,9,1),SB_Date,"<"&DATE(2027,10,1)) | L28: =COUNTIFS(SB_Lane,$A28,SB_Date,">="&DATE(2027,10,1),SB_Date,"<"&DATE(2027,11,1)) | M28: =COUNTIFS(SB_Lane,$A28,SB_Date,">="&DATE(2027,11,1),SB_Date,"<"&DATE(2027,12,1)) | N28: =COUNTIFS(SB_Lane,$A28,SB_Date,">="&DATE(2027,12,1),SB_Date,"<"&DATE(2028,1,1)) | O28: =SUM(C28:N28) | P28: =MAX(C28:N28)
A29: Total | C29: =SUM(C20:C28) | D29: =SUM(D20:D28) | E29: =SUM(E20:E28) | F29: =SUM(F20:F28) | G29: =SUM(G20:G28) | H29: =SUM(H20:H28) | I29: =SUM(I20:I28) | J29: =SUM(J20:J28) | ... O29: =SUM(O20:O28) | P29: =MAX(C29:N29)
A30: Chargeable kg | C30: =SUMIFS(SB_Chg,SB_Date,">="&DATE(2027,1,1),SB_Date,"<"&DATE(2027,2,1)) | D30: =SUMIFS(SB_Chg,SB_Date,">="&DATE(2027,2,1),SB_Date,"<"&DATE(2027,3,1)) | E30: =SUMIFS(SB_Chg,SB_Date,">="&DATE(2027,3,1),SB_Date,"<"&DATE(2027,4,1)) | F30: =SUMIFS(SB_Chg,SB_Date,">="&DATE(2027,4,1),SB_Date,"<"&DATE(2027,5,1)) | G30: =SUMIFS(SB_Chg,SB_Date,">="&DATE(2027,5,1),SB_Date,"<"&DATE(2027,6,1)) | H30: =SUMIFS(SB_Chg,SB_Date,">="&DATE(2027,6,1),SB_Date,"<"&DATE(2027,7,1)) | I30: =SUMIFS(SB_Chg,SB_Date,">="&DATE(2027,7,1),SB_Date,"<"&DATE(2027,8,1)) | J30: =SUMIFS(SB_Chg,SB_Date,">="&DATE(2027,8,1),SB_Date,"<"&DATE(2027,9,1)) | K30: =SUMIFS(SB_Chg,SB_Date,">="&DATE(2027,9,1),SB_Date,"<"&DATE(2027,10,1)) | L30: =SUMIFS(SB_Chg,SB_Date,">="&DATE(2027,10,1),SB_Date,"<"&DATE(2027,11,1)) | M30: =SUMIFS(SB_Chg,SB_Date,">="&DATE(2027,11,1),SB_Date,"<"&DATE(2027,12,1)) | N30: =SUMIFS(SB_Chg,SB_Date,">="&DATE(2027,12,1),SB_Date,"<"&DATE(2028,1,1)) | O30: =SUM(C30:N30) | P30: =MAX(C30:N30)
A32: On-time check against target (needs transit days on the Rate Card)
A33: Lane | B33: Destination | C33: Target | D33: Shipments A | E33: With expected date A | F33: Meets target A | G33: On target % A | H33: Avg days late A | I33: Shipments B | J33: With expected date B | K33: Meets target B | L33: On target % B | M33: Avg days late B
A34: L01 | B34: Saudi Arabia | C34: ='Timeline Rules'!F6 | D34: =COUNTIF(SA_Lane,$A34) | E34: =COUNTIFS(SA_Lane,$A34,SA_Meet,"?*") | F34: =COUNTIFS(SA_Lane,$A34,SA_Meet,"Yes") | G34: =IFERROR(F34/E34,"") | H34: =IFERROR(SUMIFS(SA_Late,SA_Lane,$A34)/E34,"") | I34: =COUNTIF(SB_Lane,$A34) | J34: =COUNTIFS(SB_Lane,$A34,SB_Meet,"?*") | K34: =COUNTIFS(SB_Lane,$A34,SB_Meet,"Yes") | L34: =IFERROR(K34/J34,"") | M34: =IFERROR(SUMIFS(SB_Late,SB_Lane,$A34)/J34,"")
A35: L02 | B35: United Arab Emirates | C35: ='Timeline Rules'!F7 | D35: =COUNTIF(SA_Lane,$A35) | E35: =COUNTIFS(SA_Lane,$A35,SA_Meet,"?*") | F35: =COUNTIFS(SA_Lane,$A35,SA_Meet,"Yes") | G35: =IFERROR(F35/E35,"") | H35: =IFERROR(SUMIFS(SA_Late,SA_Lane,$A35)/E35,"") | I35: =COUNTIF(SB_Lane,$A35) | J35: =COUNTIFS(SB_Lane,$A35,SB_Meet,"?*") | K35: =COUNTIFS(SB_Lane,$A35,SB_Meet,"Yes") | L35: =IFERROR(K35/J35,"") | M35: =IFERROR(SUMIFS(SB_Late,SB_Lane,$A35)/J35,"")
A36: L03 | B36: Kuwait | C36: ='Timeline Rules'!F8 | D36: =COUNTIF(SA_Lane,$A36) | E36: =COUNTIFS(SA_Lane,$A36,SA_Meet,"?*") | F36: =COUNTIFS(SA_Lane,$A36,SA_Meet,"Yes") | G36: =IFERROR(F36/E36,"") | H36: =IFERROR(SUMIFS(SA_Late,SA_Lane,$A36)/E36,"") | I36: =COUNTIF(SB_Lane,$A36) | J36: =COUNTIFS(SB_Lane,$A36,SB_Meet,"?*") | K36: =COUNTIFS(SB_Lane,$A36,SB_Meet,"Yes") | L36: =IFERROR(K36/J36,"") | M36: =IFERROR(SUMIFS(SB_Late,SB_Lane,$A36)/J36,"")
A37: L04 | B37: Qatar | C37: ='Timeline Rules'!F9 | D37: =COUNTIF(SA_Lane,$A37) | E37: =COUNTIFS(SA_Lane,$A37,SA_Meet,"?*") | F37: =COUNTIFS(SA_Lane,$A37,SA_Meet,"Yes") | G37: =IFERROR(F37/E37,"") | H37: =IFERROR(SUMIFS(SA_Late,SA_Lane,$A37)/E37,"") | I37: =COUNTIF(SB_Lane,$A37) | J37: =COUNTIFS(SB_Lane,$A37,SB_Meet,"?*") | K37: =COUNTIFS(SB_Lane,$A37,SB_Meet,"Yes") | L37: =IFERROR(K37/J37,"") | M37: =IFERROR(SUMIFS(SB_Late,SB_Lane,$A37)/J37,"")
A38: L05 | B38: Türkiye | C38: ='Timeline Rules'!F10 | D38: =COUNTIF(SA_Lane,$A38) | E38: =COUNTIFS(SA_Lane,$A38,SA_Meet,"?*") | F38: =COUNTIFS(SA_Lane,$A38,SA_Meet,"Yes") | G38: =IFERROR(F38/E38,"") | H38: =IFERROR(SUMIFS(SA_Late,SA_Lane,$A38)/E38,"") | I38: =COUNTIF(SB_Lane,$A38) | J38: =COUNTIFS(SB_Lane,$A38,SB_Meet,"?*") | K38: =COUNTIFS(SB_Lane,$A38,SB_Meet,"Yes") | L38: =IFERROR(K38/J38,"") | M38: =IFERROR(SUMIFS(SB_Late,SB_Lane,$A38)/J38,"")
A39: L06 | B39: Morocco | C39: ='Timeline Rules'!F11 | D39: =COUNTIF(SA_Lane,$A39) | E39: =COUNTIFS(SA_Lane,$A39,SA_Meet,"?*") | F39: =COUNTIFS(SA_Lane,$A39,SA_Meet,"Yes") | G39: =IFERROR(F39/E39,"") | H39: =IFERROR(SUMIFS(SA_Late,SA_Lane,$A39)/E39,"") | I39: =COUNTIF(SB_Lane,$A39) | J39: =COUNTIFS(SB_Lane,$A39,SB_Meet,"?*") | K39: =COUNTIFS(SB_Lane,$A39,SB_Meet,"Yes") | L39: =IFERROR(K39/J39,"") | M39: =IFERROR(SUMIFS(SB_Late,SB_Lane,$A39)/J39,"")
A40: L07 | B40: Algeria | C40: ='Timeline Rules'!F12 | D40: =COUNTIF(SA_Lane,$A40) | E40: =COUNTIFS(SA_Lane,$A40,SA_Meet,"?*") | F40: =COUNTIFS(SA_Lane,$A40,SA_Meet,"Yes") | G40: =IFERROR(F40/E40,"") | H40: =IFERROR(SUMIFS(SA_Late,SA_Lane,$A40)/E40,"") | I40: =COUNTIF(SB_Lane,$A40) | J40: =COUNTIFS(SB_Lane,$A40,SB_Meet,"?*") | K40: =COUNTIFS(SB_Lane,$A40,SB_Meet,"Yes") | L40: =IFERROR(K40/J40,"") | M40: =IFERROR(SUMIFS(SB_Late,SB_Lane,$A40)/J40,"")
A41: L08 | B41: Egypt | C41: ='Timeline Rules'!F13 | D41: =COUNTIF(SA_Lane,$A41) | E41: =COUNTIFS(SA_Lane,$A41,SA_Meet,"?*") | F41: =COUNTIFS(SA_Lane,$A41,SA_Meet,"Yes") | G41: =IFERROR(F41/E41,"") | H41: =IFERROR(SUMIFS(SA_Late,SA_Lane,$A41)/E41,"") | I41: =COUNTIF(SB_Lane,$A41) | J41: =COUNTIFS(SB_Lane,$A41,SB_Meet,"?*") | K41: =COUNTIFS(SB_Lane,$A41,SB_Meet,"Yes") | L41: =IFERROR(K41/J41,"") | M41: =IFERROR(SUMIFS(SB_Late,SB_Lane,$A41)/J41,"")
A42: L09 | B42: Tunisia | C42: ='Timeline Rules'!F14 | D42: =COUNTIF(SA_Lane,$A42) | E42: =COUNTIFS(SA_Lane,$A42,SA_Meet,"?*") | F42: =COUNTIFS(SA_Lane,$A42,SA_Meet,"Yes") | G42: =IFERROR(F42/E42,"") | H42: =IFERROR(SUMIFS(SA_Late,SA_Lane,$A42)/E42,"") | I42: =COUNTIF(SB_Lane,$A42) | J42: =COUNTIFS(SB_Lane,$A42,SB_Meet,"?*") | K42: =COUNTIFS(SB_Lane,$A42,SB_Meet,"Yes") | L42: =IFERROR(K42/J42,"") | M42: =IFERROR(SUMIFS(SB_Late,SB_Lane,$A42)/J42,"")
A43: Total | D43: =SUM(D34:D42) | E43: =SUM(E34:E42) | F43: =SUM(F34:F42) | G43: =IFERROR(F43/E43,"") | H43: =IFERROR(SUMPRODUCT(H34:H42,E34:E42)/E43,"") | I43: =SUM(I34:I42) | J43: =SUM(J34:J42) | K43: =SUM(K34:K42) | L43: =IFERROR(K43/J43,"") | M43: =IFERROR(SUMPRODUCT(M34:M42,J34:J42)/J43,"")
A47: Shipments per week (all lanes)
A48: Week starting (Mon) | B48: Shipments A | C48: Chargeable kg A | D48: Shipments B | E48: Chargeable kg B
A49: 46384 | B49: =COUNTIF(SA_Week,A49) | C49: =SUMIFS(SA_Chg,SA_Week,A49) | D49: =COUNTIF(SB_Week,A49) | E49: =SUMIFS(SB_Chg,SB_Week,A49)
A50: 46391 | B50: =COUNTIF(SA_Week,A50) | C50: =SUMIFS(SA_Chg,SA_Week,A50) | D50: =COUNTIF(SB_Week,A50) | E50: =SUMIFS(SB_Chg,SB_Week,A50)
A51: 46398 | B51: =COUNTIF(SA_Week,A51) | C51: =SUMIFS(SA_Chg,SA_Week,A51) | D51: =COUNTIF(SB_Week,A51) | E51: =SUMIFS(SB_Chg,SB_Week,A51)
A52: 46405 | B52: =COUNTIF(SA_Week,A52) | C52: =SUMIFS(SA_Chg,SA_Week,A52) | D52: =COUNTIF(SB_Week,A52) | E52: =SUMIFS(SB_Chg,SB_Week,A52)
A53: 46412 | B53: =COUNTIF(SA_Week,A53) | C53: =SUMIFS(SA_Chg,SA_Week,A53) | D53: =COUNTIF(SB_Week,A53) | E53: =SUMIFS(SB_Chg,SB_Week,A53)
A54: 46419 | B54: =COUNTIF(SA_Week,A54) | C54: =SUMIFS(SA_Chg,SA_Week,A54) | D54: =COUNTIF(SB_Week,A54) | E54: =SUMIFS(SB_Chg,SB_Week,A54)
A55: 46426 | B55: =COUNTIF(SA_Week,A55) | C55: =SUMIFS(SA_Chg,SA_Week,A55) | D55: =COUNTIF(SB_Week,A55) | E55: =SUMIFS(SB_Chg,SB_Week,A55)
A56: 46433 | B56: =COUNTIF(SA_Week,A56) | C56: =SUMIFS(SA_Chg,SA_Week,A56) | D56: =COUNTIF(SB_Week,A56) | E56: =SUMIFS(SB_Chg,SB_Week,A56)
A57: 46440 | B57: =COUNTIF(SA_Week,A57) | C57: =SUMIFS(SA_Chg,SA_Week,A57) | D57: =COUNTIF(SB_Week,A57) | E57: =SUMIFS(SB_Chg,SB_Week,A57)
A58: 46447 | B58: =COUNTIF(SA_Week,A58) | C58: =SUMIFS(SA_Chg,SA_Week,A58) | D58: =COUNTIF(SB_Week,A58) | E58: =SUMIFS(SB_Chg,SB_Week,A58)
A59: 46454 | B59: =COUNTIF(SA_Week,A59) | C59: =SUMIFS(SA_Chg,SA_Week,A59) | D59: =COUNTIF(SB_Week,A59) | E59: =SUMIFS(SB_Chg,SB_Week,A59)
A60: 46461 | B60: =COUNTIF(SA_Week,A60) | C60: =SUMIFS(SA_Chg,SA_Week,A60) | D60: =COUNTIF(SB_Week,A60) | E60: =SUMIFS(SB_Chg,SB_Week,A60)
... A101: 46748 | B101: =COUNTIF(SA_Week,A101) | C101: =SUMIFS(SA_Chg,SA_Week,A101) | D101: =COUNTIF(SB_Week,A101) | E101: =SUMIFS(SB_Chg,SB_Week,A101)
A102: Busiest week | B102: =MAX(B49:B101) | C102: =MAX(C49:C101) | D102: =MAX(D49:D101) | E102: =MAX(E49:E101)

Sheet Rate Card
A1: Rate card: please fill in the yellow cells
A2: Rates from Helmond, NL. EUR excl. VAT. Cost per shipment = MAX(minimum, rate x chargeable kg) x (1 + fuel %) + export docs fee + other fixed fees. Use the Scenario B discount if your rates improve at Scenario B volume. Rates from your own regional hub go on the Optional Regional Stock sheet.
A4: Lane | B4: Destination | C4: Weight band | D4: Shipments A | E4: Shipments B | F4: Avg chargeable kg per shipment | G4: Proposed mode / service | H4: Transit time door-to-door (working days) | I4: Rate per chargeable kg | J4: Minimum charge per shipment | K4: Fuel surcharge % | L4: Export customs & docs per shipment | M4: Other fixed fees per shipment | N4: Scenario B volume discount % | O4: Notes | P4: Cost per shipment | Q4: Annual cost Scenario A | R4: Annual cost Scenario B | S4: Worst-case transit (working days)
A5: L01 | B5: Saudi Arabia | C5: B1 0 to 30 kg | D5: =Volumes!C34 | E5: =Volumes!H34 | F5: =Volumes!C48 | P5: =IF(AND(I5="",J5=""),"",MAX(N(J5),N(I5)*F5)*(1+N(K5))+N(L5)+N(M5)) | Q5: =IF(P5="",0,D5*P5) | R5: =IF(P5="",0,E5*P5*(1-N(N5)))
A6: L01 | B6: Saudi Arabia | C6: B2 30 to 100 kg | D6: =Volumes!D34 | E6: =Volumes!I34 | F6: =Volumes!C49 | P6: =IF(AND(I6="",J6=""),"",MAX(N(J6),N(I6)*F6)*(1+N(K6))+N(L6)+N(M6)) | Q6: =IF(P6="",0,D6*P6) | R6: =IF(P6="",0,E6*P6*(1-N(N6)))
A7: L01 | B7: Saudi Arabia | C7: B3 100 to 500 kg | D7: =Volumes!E34 | E7: =Volumes!J34 | F7: =Volumes!C50 | P7: =IF(AND(I7="",J7=""),"",MAX(N(J7),N(I7)*F7)*(1+N(K7))+N(L7)+N(M7)) | Q7: =IF(P7="",0,D7*P7) | R7: =IF(P7="",0,E7*P7*(1-N(N7)))
A8: L01 | B8: Saudi Arabia | C8: B4 500 to 2,000 kg | D8: =Volumes!F34 | E8: =Volumes!K34 | F8: =Volumes!C51 | P8: =IF(AND(I8="",J8=""),"",MAX(N(J8),N(I8)*F8)*(1+N(K8))+N(L8)+N(M8)) | Q8: =IF(P8="",0,D8*P8) | R8: =IF(P8="",0,E8*P8*(1-N(N8)))
A9: L01 | B9: Saudi Arabia | C9: B5 over 2,000 kg | D9: =Volumes!G34 | E9: =Volumes!L34 | F9: =Volumes!C52 | P9: =IF(AND(I9="",J9=""),"",MAX(N(J9),N(I9)*F9)*(1+N(K9))+N(L9)+N(M9)) | Q9: =IF(P9="",0,D9*P9) | R9: =IF(P9="",0,E9*P9*(1-N(N9)))
A10: L02 | B10: United Arab Emirates | C10: B1 0 to 30 kg | D10: =Volumes!C35 | E10: =Volumes!H35 | F10: =Volumes!C48 | P10: =IF(AND(I10="",J10=""),"",MAX(N(J10),N(I10)*F10)*(1+N(K10))+N(L10)+N(M10)) | Q10: =IF(P10="",0,D10*P10) | R10: =IF(P10="",0,E10*P10*(1-N(N10)))
A11: L02 | B11: United Arab Emirates | C11: B2 30 to 100 kg | D11: =Volumes!D35 | E11: =Volumes!I35 | F11: =Volumes!C49 | P11: =IF(AND(I11="",J11=""),"",MAX(N(J11),N(I11)*F11)*(1+N(K11))+N(L11)+N(M11)) | Q11: =IF(P11="",0,D11*P11) | R11: =IF(P11="",0,E11*P11*(1-N(N11)))
A12: L02 | B12: United Arab Emirates | C12: B3 100 to 500 kg | D12: =Volumes!E35 | E12: =Volumes!J35 | F12: =Volumes!C50 | P12: =IF(AND(I12="",J12=""),"",MAX(N(J12),N(I12)*F12)*(1+N(K12))+N(L12)+N(M12)) | Q12: =IF(P12="",0,D12*P12) | R12: =IF(P12="",0,E12*P12*(1-N(N12)))
A13: L02 | B13: United Arab Emirates | C13: B4 500 to 2,000 kg | D13: =Volumes!F35 | E13: =Volumes!K35 | F13: =Volumes!C51 | P13: =IF(AND(I13="",J13=""),"",MAX(N(J13),N(I13)*F13)*(1+N(K13))+N(L13)+N(M13)) | Q13: =IF(P13="",0,D13*P13) | R13: =IF(P13="",0,E13*P13*(1-N(N13)))
A14: L02 | B14: United Arab Emirates | C14: B5 over 2,000 kg | D14: =Volumes!G35 | E14: =Volumes!L35 | F14: =Volumes!C52 | P14: =IF(AND(I14="",J14=""),"",MAX(N(J14),N(I14)*F14)*(1+N(K14))+N(L14)+N(M14)) | Q14: =IF(P14="",0,D14*P14) | R14: =IF(P14="",0,E14*P14*(1-N(N14)))
A15: L03 | B15: Kuwait | C15: B1 0 to 30 kg | D15: =Volumes!C36 | E15: =Volumes!H36 | F15: =Volumes!C48 | P15: =IF(AND(I15="",J15=""),"",MAX(N(J15),N(I15)*F15)*(1+N(K15))+N(L15)+N(M15)) | Q15: =IF(P15="",0,D15*P15) | R15: =IF(P15="",0,E15*P15*(1-N(N15)))
A16: L03 | B16: Kuwait | C16: B2 30 to 100 kg | D16: =Volumes!D36 | E16: =Volumes!I36 | F16: =Volumes!C49 | P16: =IF(AND(I16="",J16=""),"",MAX(N(J16),N(I16)*F16)*(1+N(K16))+N(L16)+N(M16)) | Q16: =IF(P16="",0,D16*P16) | R16: =IF(P16="",0,E16*P16*(1-N(N16)))
A17: L03 | B17: Kuwait | C17: B3 100 to 500 kg | D17: =Volumes!E36 | E17: =Volumes!J36 | F17: =Volumes!C50 | P17: =IF(AND(I17="",J17=""),"",MAX(N(J17),N(I17)*F17)*(1+N(K17))+N(L17)+N(M17)) | Q17: =IF(P17="",0,D17*P17) | R17: =IF(P17="",0,E17*P17*(1-N(N17)))
A18: L03 | B18: Kuwait | C18: B4 500 to 2,000 kg | D18: =Volumes!F36 | E18: =Volumes!K36 | F18: =Volumes!C51 | P18: =IF(AND(I18="",J18=""),"",MAX(N(J18),N(I18)*F18)*(1+N(K18))+N(L18)+N(M18)) | Q18: =IF(P18="",0,D18*P18) | R18: =IF(P18="",0,E18*P18*(1-N(N18)))
A19: L03 | B19: Kuwait | C19: B5 over 2,000 kg | D19: =Volumes!G36 | E19: =Volumes!L36 | F19: =Volumes!C52 | P19: =IF(AND(I19="",J19=""),"",MAX(N(J19),N(I19)*F19)*(1+N(K19))+N(L19)+N(M19)) | Q19: =IF(P19="",0,D19*P19) | R19: =IF(P19="",0,E19*P19*(1-N(N19)))
A20: L04 | B20: Qatar | C20: B1 0 to 30 kg | D20: =Volumes!C37 | E20: =Volumes!H37 | F20: =Volumes!C48 | P20: =IF(AND(I20="",J20=""),"",MAX(N(J20),N(I20)*F20)*(1+N(K20))+N(L20)+N(M20)) | Q20: =IF(P20="",0,D20*P20) | R20: =IF(P20="",0,E20*P20*(1-N(N20)))
A21: L04 | B21: Qatar | C21: B2 30 to 100 kg | D21: =Volumes!D37 | E21: =Volumes!I37 | F21: =Volumes!C49 | P21: =IF(AND(I21="",J21=""),"",MAX(N(J21),N(I21)*F21)*(1+N(K21))+N(L21)+N(M21)) | Q21: =IF(P21="",0,D21*P21) | R21: =IF(P21="",0,E21*P21*(1-N(N21)))
A22: L04 | B22: Qatar | C22: B3 100 to 500 kg | D22: =Volumes!E37 | E22: =Volumes!J37 | F22: =Volumes!C50 | P22: =IF(AND(I22="",J22=""),"",MAX(N(J22),N(I22)*F22)*(1+N(K22))+N(L22)+N(M22)) | Q22: =IF(P22="",0,D22*P22) | R22: =IF(P22="",0,E22*P22*(1-N(N22)))
A23: L04 | B23: Qatar | C23: B4 500 to 2,000 kg | D23: =Volumes!F37 | E23: =Volumes!K37 | F23: =Volumes!C51 | P23: =IF(AND(I23="",J23=""),"",MAX(N(J23),N(I23)*F23)*(1+N(K23))+N(L23)+N(M23)) | Q23: =IF(P23="",0,D23*P23) | R23: =IF(P23="",0,E23*P23*(1-N(N23)))
A24: L04 | B24: Qatar | C24: B5 over 2,000 kg | D24: =Volumes!G37 | E24: =Volumes!L37 | F24: =Volumes!C52 | P24: =IF(AND(I24="",J24=""),"",MAX(N(J24),N(I24)*F24)*(1+N(K24))+N(L24)+N(M24)) | Q24: =IF(P24="",0,D24*P24) | R24: =IF(P24="",0,E24*P24*(1-N(N24)))
A25: L05 | B25: Türkiye | C25: B1 0 to 30 kg | D25: =Volumes!C38 | E25: =Volumes!H38 | F25: =Volumes!C48 | P25: =IF(AND(I25="",J25=""),"",MAX(N(J25),N(I25)*F25)*(1+N(K25))+N(L25)+N(M25)) | Q25: =IF(P25="",0,D25*P25) | R25: =IF(P25="",0,E25*P25*(1-N(N25)))
A26: L05 | B26: Türkiye | C26: B2 30 to 100 kg | D26: =Volumes!D38 | E26: =Volumes!I38 | F26: =Volumes!C49 | P26: =IF(AND(I26="",J26=""),"",MAX(N(J26),N(I26)*F26)*(1+N(K26))+N(L26)+N(M26)) | Q26: =IF(P26="",0,D26*P26) | R26: =IF(P26="",0,E26*P26*(1-N(N26)))
A27: L05 | B27: Türkiye | C27: B3 100 to 500 kg | D27: =Volumes!E38 | E27: =Volumes!J38 | F27: =Volumes!C50 | P27: =IF(AND(I27="",J27=""),"",MAX(N(J27),N(I27)*F27)*(1+N(K27))+N(L27)+N(M27)) | Q27: =IF(P27="",0,D27*P27) | R27: =IF(P27="",0,E27*P27*(1-N(N27)))
A28: L05 | B28: Türkiye | C28: B4 500 to 2,000 kg | D28: =Volumes!F38 | E28: =Volumes!K38 | F28: =Volumes!C51 | P28: =IF(AND(I28="",J28=""),"",MAX(N(J28),N(I28)*F28)*(1+N(K28))+N(L28)+N(M28)) | Q28: =IF(P28="",0,D28*P28) | R28: =IF(P28="",0,E28*P28*(1-N(N28)))
A29: L05 | B29: Türkiye | C29: B5 over 2,000 kg | D29: =Volumes!G38 | E29: =Volumes!L38 | F29: =Volumes!C52 | P29: =IF(AND(I29="",J29=""),"",MAX(N(J29),N(I29)*F29)*(1+N(K29))+N(L29)+N(M29)) | Q29: =IF(P29="",0,D29*P29) | R29: =IF(P29="",0,E29*P29*(1-N(N29)))
A30: L06 | B30: Morocco | C30: B1 0 to 30 kg | D30: =Volumes!C39 | E30: =Volumes!H39 | F30: =Volumes!C48 | P30: =IF(AND(I30="",J30=""),"",MAX(N(J30),N(I30)*F30)*(1+N(K30))+N(L30)+N(M30)) | Q30: =IF(P30="",0,D30*P30) | R30: =IF(P30="",0,E30*P30*(1-N(N30)))
A31: L06 | B31: Morocco | C31: B2 30 to 100 kg | D31: =Volumes!D39 | E31: =Volumes!I39 | F31: =Volumes!C49 | P31: =IF(AND(I31="",J31=""),"",MAX(N(J31),N(I31)*F31)*(1+N(K31))+N(L31)+N(M31)) | Q31: =IF(P31="",0,D31*P31) | R31: =IF(P31="",0,E31*P31*(1-N(N31)))
A32: L06 | B32: Morocco | C32: B3 100 to 500 kg | D32: =Volumes!E39 | E32: =Volumes!J39 | F32: =Volumes!C50 | P32: =IF(AND(I32="",J32=""),"",MAX(N(J32),N(I32)*F32)*(1+N(K32))+N(L32)+N(M32)) | Q32: =IF(P32="",0,D32*P32) | R32: =IF(P32="",0,E32*P32*(1-N(N32)))
A33: L06 | B33: Morocco | C33: B4 500 to 2,000 kg | D33: =Volumes!F39 | E33: =Volumes!K39 | F33: =Volumes!C51 | P33: =IF(AND(I33="",J33=""),"",MAX(N(J33),N(I33)*F33)*(1+N(K33))+N(L33)+N(M33)) | Q33: =IF(P33="",0,D33*P33) | R33: =IF(P33="",0,E33*P33*(1-N(N33)))
A34: L06 | B34: Morocco | C34: B5 over 2,000 kg | D34: =Volumes!G39 | E34: =Volumes!L39 | F34: =Volumes!C52 | P34: =IF(AND(I34="",J34=""),"",MAX(N(J34),N(I34)*F34)*(1+N(K34))+N(L34)+N(M34)) | Q34: =IF(P34="",0,D34*P34) | R34: =IF(P34="",0,E34*P34*(1-N(N34)))
A35: L07 | B35: Algeria | C35: B1 0 to 30 kg | D35: =Volumes!C40 | E35: =Volumes!H40 | F35: =Volumes!C48 | P35: =IF(AND(I35="",J35=""),"",MAX(N(J35),N(I35)*F35)*(1+N(K35))+N(L35)+N(M35)) | Q35: =IF(P35="",0,D35*P35) | R35: =IF(P35="",0,E35*P35*(1-N(N35)))
A36: L07 | B36: Algeria | C36: B2 30 to 100 kg | D36: =Volumes!D40 | E36: =Volumes!I40 | F36: =Volumes!C49 | P36: =IF(AND(I36="",J36=""),"",MAX(N(J36),N(I36)*F36)*(1+N(K36))+N(L36)+N(M36)) | Q36: =IF(P36="",0,D36*P36) | R36: =IF(P36="",0,E36*P36*(1-N(N36)))
A37: L07 | B37: Algeria | C37: B3 100 to 500 kg | D37: =Volumes!E40 | E37: =Volumes!J40 | F37: =Volumes!C50 | P37: =IF(AND(I37="",J37=""),"",MAX(N(J37),N(I37)*F37)*(1+N(K37))+N(L37)+N(M37)) | Q37: =IF(P37="",0,D37*P37) | R37: =IF(P37="",0,E37*P37*(1-N(N37)))
A38: L07 | B38: Algeria | C38: B4 500 to 2,000 kg | D38: =Volumes!F40 | E38: =Volumes!K40 | F38: =Volumes!C51 | P38: =IF(AND(I38="",J38=""),"",MAX(N(J38),N(I38)*F38)*(1+N(K38))+N(L38)+N(M38)) | Q38: =IF(P38="",0,D38*P38) | R38: =IF(P38="",0,E38*P38*(1-N(N38)))
A39: L07 | B39: Algeria | C39: B5 over 2,000 kg | D39: =Volumes!G40 | E39: =Volumes!L40 | F39: =Volumes!C52 | P39: =IF(AND(I39="",J39=""),"",MAX(N(J39),N(I39)*F39)*(1+N(K39))+N(L39)+N(M39)) | Q39: =IF(P39="",0,D39*P39) | R39: =IF(P39="",0,E39*P39*(1-N(N39)))
A40: L08 | B40: Egypt | C40: B1 0 to 30 kg | D40: =Volumes!C41 | E40: =Volumes!H41 | F40: =Volumes!C48 | P40: =IF(AND(I40="",J40=""),"",MAX(N(J40),N(I40)*F40)*(1+N(K40))+N(L40)+N(M40)) | Q40: =IF(P40="",0,D40*P40) | R40: =IF(P40="",0,E40*P40*(1-N(N40)))
A41: L08 | B41: Egypt | C41: B2 30 to 100 kg | D41: =Volumes!D41 | E41: =Volumes!I41 | F41: =Volumes!C49 | P41: =IF(AND(I41="",J41=""),"",MAX(N(J41),N(I41)*F41)*(1+N(K41))+N(L41)+N(M41)) | Q41: =IF(P41="",0,D41*P41) | R41: =IF(P41="",0,E41*P41*(1-N(N41)))
A42: L08 | B42: Egypt | C42: B3 100 to 500 kg | D42: =Volumes!E41 | E42: =Volumes!J41 | F42: =Volumes!C50 | P42: =IF(AND(I42="",J42=""),"",MAX(N(J42),N(I42)*F42)*(1+N(K42))+N(L42)+N(M42)) | Q42: =IF(P42="",0,D42*P42) | R42: =IF(P42="",0,E42*P42*(1-N(N42)))
A43: L08 | B43: Egypt | C43: B4 500 to 2,000 kg | D43: =Volumes!F41 | E43: =Volumes!K41 | F43: =Volumes!C51 | P43: =IF(AND(I43="",J43=""),"",MAX(N(J43),N(I43)*F43)*(1+N(K43))+N(L43)+N(M43)) | Q43: =IF(P43="",0,D43*P43) | R43: =IF(P43="",0,E43*P43*(1-N(N43)))
A44: L08 | B44: Egypt | C44: B5 over 2,000 kg | D44: =Volumes!G41 | E44: =Volumes!L41 | F44: =Volumes!C52 | P44: =IF(AND(I44="",J44=""),"",MAX(N(J44),N(I44)*F44)*(1+N(K44))+N(L44)+N(M44)) | Q44: =IF(P44="",0,D44*P44) | R44: =IF(P44="",0,E44*P44*(1-N(N44)))
A45: L09 | B45: Tunisia | C45: B1 0 to 30 kg | D45: =Volumes!C42 | E45: =Volumes!H42 | F45: =Volumes!C48 | P45: =IF(AND(I45="",J45=""),"",MAX(N(J45),N(I45)*F45)*(1+N(K45))+N(L45)+N(M45)) | Q45: =IF(P45="",0,D45*P45) | R45: =IF(P45="",0,E45*P45*(1-N(N45)))
A46: L09 | B46: Tunisia | C46: B2 30 to 100 kg | D46: =Volumes!D42 | E46: =Volumes!I42 | F46: =Volumes!C49 | P46: =IF(AND(I46="",J46=""),"",MAX(N(J46),N(I46)*F46)*(1+N(K46))+N(L46)+N(M46)) | Q46: =IF(P46="",0,D46*P46) | R46: =IF(P46="",0,E46*P46*(1-N(N46)))
A47: L09 | B47: Tunisia | C47: B3 100 to 500 kg | D47: =Volumes!E42 | E47: =Volumes!J42 | F47: =Volumes!C50 | P47: =IF(AND(I47="",J47=""),"",MAX(N(J47),N(I47)*F47)*(1+N(K47))+N(L47)+N(M47)) | Q47: =IF(P47="",0,D47*P47) | R47: =IF(P47="",0,E47*P47*(1-N(N47)))
A48: L09 | B48: Tunisia | C48: B4 500 to 2,000 kg | D48: =Volumes!F42 | E48: =Volumes!K42 | F48: =Volumes!C51 | P48: =IF(AND(I48="",J48=""),"",MAX(N(J48),N(I48)*F48)*(1+N(K48))+N(L48)+N(M48)) | Q48: =IF(P48="",0,D48*P48) | R48: =IF(P48="",0,E48*P48*(1-N(N48)))
A49: L09 | B49: Tunisia | C49: B5 over 2,000 kg | D49: =Volumes!G42 | E49: =Volumes!L42 | F49: =Volumes!C52 | P49: =IF(AND(I49="",J49=""),"",MAX(N(J49),N(I49)*F49)*(1+N(K49))+N(L49)+N(M49)) | Q49: =IF(P49="",0,D49*P49) | R49: =IF(P49="",0,E49*P49*(1-N(N49)))
A50: Total | D50: =SUM(D5:D49) | E50: =SUM(E5:E49) | Q50: =SUM(Q5:Q49) | R50: =SUM(R5:R49)
A51: Grey rows have no expected shipments. A rate is still welcome.

Sheet Cost Overview
A1: Cost overview (calculates from the Rate Card)
A2: EUR excl. VAT. Transit time is weighted by Scenario B shipments.
A4: Lane | B4: Destination | C4: Shipments A | D4: Chargeable kg A | E4: Annual cost A | F4: Cost per kg A | G4: Cost per shipment A | H4: Shipments B | I4: Chargeable kg B | J4: Annual cost B | K4: Cost per kg B | L4: Cost per shipment B | M4: Avg transit days | N4: Bands without a rate | O4: Shipments B from other origins | P4: Direct transport A (from Helmond) | Q4: Direct transport B (from Helmond) | S4: Total logistics cost
A5: L01 | B5: Saudi Arabia | C5: =Volumes!D6 | D5: =Volumes!G6 | E5: =SUMIFS('Rate Card'!$Q$5:$Q$49,'Rate Card'!$A$5:$A$49,A5) | F5: =IFERROR(E5/D5,0) | G5: =IFERROR(E5/C5,0) | H5: =Volumes!D20 | I5: =Volumes!G20 | J5: =SUMIFS('Rate Card'!$R$5:$R$49,'Rate Card'!$A$5:$A$49,A5) | K5: =IFERROR(J5/I5,0) | L5: =IFERROR(J5/H5,0) | M5: =IFERROR(SUMPRODUCT(--('Rate Card'!$A$5:$A$49=A5),'Rate Card'!$E$5:$E$49,'Rate Card'!$H$5:$H$49)/SUMPRODUCT(--('Rate Card'!$A$5:$A$49=A5),'Rate Card'!$E$5:$E$49,--ISNUMBER('Rate Card'!$H$5:$H$49)),0) | N5: =COUNTIFS('Rate Card'!$A$5:$A$49,A5,'Rate Card'!$I$5:$I$49,"") | O5: =COUNTIFS(SB_Lane,A5,SB_From,"<>Helmond") | P5: =SUMIFS(SA_Cost,SA_Lane,A5,SA_From,"Helmond") | Q5: =SUMIFS(SB_Cost,SB_Lane,A5,SB_From,"Helmond") | S5: Cost block | T5: Scenario A | U5: Scenario B
A6: L02 | B6: United Arab Emirates | C6: =Volumes!D7 | D6: =Volumes!G7 | E6: =SUMIFS('Rate Card'!$Q$5:$Q$49,'Rate Card'!$A$5:$A$49,A6) | F6: =IFERROR(E6/D6,0) | G6: =IFERROR(E6/C6,0) | H6: =Volumes!D21 | I6: =Volumes!G21 | J6: =SUMIFS('Rate Card'!$R$5:$R$49,'Rate Card'!$A$5:$A$49,A6) | K6: =IFERROR(J6/I6,0) | L6: =IFERROR(J6/H6,0) | M6: =IFERROR(SUMPRODUCT(--('Rate Card'!$A$5:$A$49=A6),'Rate Card'!$E$5:$E$49,'Rate Card'!$H$5:$H$49)/SUMPRODUCT(--('Rate Card'!$A$5:$A$49=A6),'Rate Card'!$E$5:$E$49,--ISNUMBER('Rate Card'!$H$5:$H$49)),0) | N6: =COUNTIFS('Rate Card'!$A$5:$A$49,A6,'Rate Card'!$I$5:$I$49,"") | O6: =COUNTIFS(SB_Lane,A6,SB_From,"<>Helmond") | P6: =SUMIFS(SA_Cost,SA_Lane,A6,SA_From,"Helmond") | Q6: =SUMIFS(SB_Cost,SB_Lane,A6,SB_From,"Helmond") | S6: Direct transport from Helmond | T6: =P14 | U6: =Q14
A7: L03 | B7: Kuwait | C7: =Volumes!D8 | D7: =Volumes!G8 | E7: =SUMIFS('Rate Card'!$Q$5:$Q$49,'Rate Card'!$A$5:$A$49,A7) | F7: =IFERROR(E7/D7,0) | G7: =IFERROR(E7/C7,0) | H7: =Volumes!D22 | I7: =Volumes!G22 | J7: =SUMIFS('Rate Card'!$R$5:$R$49,'Rate Card'!$A$5:$A$49,A7) | K7: =IFERROR(J7/I7,0) | L7: =IFERROR(J7/H7,0) | M7: =IFERROR(SUMPRODUCT(--('Rate Card'!$A$5:$A$49=A7),'Rate Card'!$E$5:$E$49,'Rate Card'!$H$5:$H$49)/SUMPRODUCT(--('Rate Card'!$A$5:$A$49=A7),'Rate Card'!$E$5:$E$49,--ISNUMBER('Rate Card'!$H$5:$H$49)),0) | N7: =COUNTIFS('Rate Card'!$A$5:$A$49,A7,'Rate Card'!$I$5:$I$49,"") | O7: =COUNTIFS(SB_Lane,A7,SB_From,"<>Helmond") | P7: =SUMIFS(SA_Cost,SA_Lane,A7,SA_From,"Helmond") | Q7: =SUMIFS(SB_Cost,SB_Lane,A7,SB_From,"Helmond") | S7: Other origins (regional stock, supplier or other hubs) | T7: =RS_TotA | U7: =RS_TotB
A8: L04 | B8: Qatar | C8: =Volumes!D9 | D8: =Volumes!G9 | E8: =SUMIFS('Rate Card'!$Q$5:$Q$49,'Rate Card'!$A$5:$A$49,A8) | F8: =IFERROR(E8/D8,0) | G8: =IFERROR(E8/C8,0) | H8: =Volumes!D23 | I8: =Volumes!G23 | J8: =SUMIFS('Rate Card'!$R$5:$R$49,'Rate Card'!$A$5:$A$49,A8) | K8: =IFERROR(J8/I8,0) | L8: =IFERROR(J8/H8,0) | M8: =IFERROR(SUMPRODUCT(--('Rate Card'!$A$5:$A$49=A8),'Rate Card'!$E$5:$E$49,'Rate Card'!$H$5:$H$49)/SUMPRODUCT(--('Rate Card'!$A$5:$A$49=A8),'Rate Card'!$E$5:$E$49,--ISNUMBER('Rate Card'!$H$5:$H$49)),0) | N8: =COUNTIFS('Rate Card'!$A$5:$A$49,A8,'Rate Card'!$I$5:$I$49,"") | O8: =COUNTIFS(SB_Lane,A8,SB_From,"<>Helmond") | P8: =SUMIFS(SA_Cost,SA_Lane,A8,SA_From,"Helmond") | Q8: =SUMIFS(SB_Cost,SB_Lane,A8,SB_From,"Helmond") | S8: Total | T8: =T6+T7 | U8: =U6+U7
A9: L05 | B9: Türkiye | C9: =Volumes!D10 | D9: =Volumes!G10 | E9: =SUMIFS('Rate Card'!$Q$5:$Q$49,'Rate Card'!$A$5:$A$49,A9) | F9: =IFERROR(E9/D9,0) | G9: =IFERROR(E9/C9,0) | H9: =Volumes!D24 | I9: =Volumes!G24 | J9: =SUMIFS('Rate Card'!$R$5:$R$49,'Rate Card'!$A$5:$A$49,A9) | K9: =IFERROR(J9/I9,0) | L9: =IFERROR(J9/H9,0) | M9: =IFERROR(SUMPRODUCT(--('Rate Card'!$A$5:$A$49=A9),'Rate Card'!$E$5:$E$49,'Rate Card'!$H$5:$H$49)/SUMPRODUCT(--('Rate Card'!$A$5:$A$49=A9),'Rate Card'!$E$5:$E$49,--ISNUMBER('Rate Card'!$H$5:$H$49)),0) | N9: =COUNTIFS('Rate Card'!$A$5:$A$49,A9,'Rate Card'!$I$5:$I$49,"") | O9: =COUNTIFS(SB_Lane,A9,SB_From,"<>Helmond") | P9: =SUMIFS(SA_Cost,SA_Lane,A9,SA_From,"Helmond") | Q9: =SUMIFS(SB_Cost,SB_Lane,A9,SB_From,"Helmond") | S9: Columns E and J price every shipment from Helmond. Columns P and Q and the total block follow the origin chosen per shipment. Supplier freight into a regional warehouse is excluded.
A10: L06 | B10: Morocco | C10: =Volumes!D11 | D10: =Volumes!G11 | E10: =SUMIFS('Rate Card'!$Q$5:$Q$49,'Rate Card'!$A$5:$A$49,A10) | F10: =IFERROR(E10/D10,0) | G10: =IFERROR(E10/C10,0) | H10: =Volumes!D25 | I10: =Volumes!G25 | J10: =SUMIFS('Rate Card'!$R$5:$R$49,'Rate Card'!$A$5:$A$49,A10) | K10: =IFERROR(J10/I10,0) | L10: =IFERROR(J10/H10,0) | M10: =IFERROR(SUMPRODUCT(--('Rate Card'!$A$5:$A$49=A10),'Rate Card'!$E$5:$E$49,'Rate Card'!$H$5:$H$49)/SUMPRODUCT(--('Rate Card'!$A$5:$A$49=A10),'Rate Card'!$E$5:$E$49,--ISNUMBER('Rate Card'!$H$5:$H$49)),0) | N10: =COUNTIFS('Rate Card'!$A$5:$A$49,A10,'Rate Card'!$I$5:$I$49,"") | O10: =COUNTIFS(SB_Lane,A10,SB_From,"<>Helmond") | P10: =SUMIFS(SA_Cost,SA_Lane,A10,SA_From,"Helmond") | Q10: =SUMIFS(SB_Cost,SB_Lane,A10,SB_From,"Helmond")
A11: L07 | B11: Algeria | C11: =Volumes!D12 | D11: =Volumes!G12 | E11: =SUMIFS('Rate Card'!$Q$5:$Q$49,'Rate Card'!$A$5:$A$49,A11) | F11: =IFERROR(E11/D11,0) | G11: =IFERROR(E11/C11,0) | H11: =Volumes!D26 | I11: =Volumes!G26 | J11: =SUMIFS('Rate Card'!$R$5:$R$49,'Rate Card'!$A$5:$A$49,A11) | K11: =IFERROR(J11/I11,0) | L11: =IFERROR(J11/H11,0) | M11: =IFERROR(SUMPRODUCT(--('Rate Card'!$A$5:$A$49=A11),'Rate Card'!$E$5:$E$49,'Rate Card'!$H$5:$H$49)/SUMPRODUCT(--('Rate Card'!$A$5:$A$49=A11),'Rate Card'!$E$5:$E$49,--ISNUMBER('Rate Card'!$H$5:$H$49)),0) | N11: =COUNTIFS('Rate Card'!$A$5:$A$49,A11,'Rate Card'!$I$5:$I$49,"") | O11: =COUNTIFS(SB_Lane,A11,SB_From,"<>Helmond") | P11: =SUMIFS(SA_Cost,SA_Lane,A11,SA_From,"Helmond") | Q11: =SUMIFS(SB_Cost,SB_Lane,A11,SB_From,"Helmond")
A12: L08 | B12: Egypt | C12: =Volumes!D13 | D12: =Volumes!G13 | E12: =SUMIFS('Rate Card'!$Q$5:$Q$49,'Rate Card'!$A$5:$A$49,A12) | F12: =IFERROR(E12/D12,0) | G12: =IFERROR(E12/C12,0) | H12: =Volumes!D27 | I12: =Volumes!G27 | J12: =SUMIFS('Rate Card'!$R$5:$R$49,'Rate Card'!$A$5:$A$49,A12) | K12: =IFERROR(J12/I12,0) | L12: =IFERROR(J12/H12,0) | M12: =IFERROR(SUMPRODUCT(--('Rate Card'!$A$5:$A$49=A12),'Rate Card'!$E$5:$E$49,'Rate Card'!$H$5:$H$49)/SUMPRODUCT(--('Rate Card'!$A$5:$A$49=A12),'Rate Card'!$E$5:$E$49,--ISNUMBER('Rate Card'!$H$5:$H$49)),0) | N12: =COUNTIFS('Rate Card'!$A$5:$A$49,A12,'Rate Card'!$I$5:$I$49,"") | O12: =COUNTIFS(SB_Lane,A12,SB_From,"<>Helmond") | P12: =SUMIFS(SA_Cost,SA_Lane,A12,SA_From,"Helmond") | Q12: =SUMIFS(SB_Cost,SB_Lane,A12,SB_From,"Helmond")
A13: L09 | B13: Tunisia | C13: =Volumes!D14 | D13: =Volumes!G14 | E13: =SUMIFS('Rate Card'!$Q$5:$Q$49,'Rate Card'!$A$5:$A$49,A13) | F13: =IFERROR(E13/D13,0) | G13: =IFERROR(E13/C13,0) | H13: =Volumes!D28 | I13: =Volumes!G28 | J13: =SUMIFS('Rate Card'!$R$5:$R$49,'Rate Card'!$A$5:$A$49,A13) | K13: =IFERROR(J13/I13,0) | L13: =IFERROR(J13/H13,0) | M13: =IFERROR(SUMPRODUCT(--('Rate Card'!$A$5:$A$49=A13),'Rate Card'!$E$5:$E$49,'Rate Card'!$H$5:$H$49)/SUMPRODUCT(--('Rate Card'!$A$5:$A$49=A13),'Rate Card'!$E$5:$E$49,--ISNUMBER('Rate Card'!$H$5:$H$49)),0) | N13: =COUNTIFS('Rate Card'!$A$5:$A$49,A13,'Rate Card'!$I$5:$I$49,"") | O13: =COUNTIFS(SB_Lane,A13,SB_From,"<>Helmond") | P13: =SUMIFS(SA_Cost,SA_Lane,A13,SA_From,"Helmond") | Q13: =SUMIFS(SB_Cost,SB_Lane,A13,SB_From,"Helmond")
A14: Total | C14: =SUM(C5:C13) | D14: =SUM(D5:D13) | E14: =SUM(E5:E13) | F14: =IFERROR(E14/D14,0) | G14: =IFERROR(E14/C14,0) | H14: =SUM(H5:H13) | I14: =SUM(I5:I13) | J14: =SUM(J5:J13) | K14: =IFERROR(J14/I14,0) | L14: =IFERROR(J14/H14,0) | N14: =SUM(N5:N13) | O14: =SUM(O5:O13) | P14: =SUM(P5:P13) | Q14: =SUM(Q5:Q13)

Sheet Reliability & Quality
A1: Reliability, quality and ease of working
A2: Answer in the fixed format of column E. Add context in Details. Mark whether you can share evidence (KPI report, certificate, reference customer).
A4: # | B4: Area | C4: Question | D4: Answer format | E4: Your answer | F4: Details | G4: Evidence available | H4: Evidence description
A5: R1 | B5: Reliability | C5: On-time delivery rate on these lanes over the last 12 months (on or before the promised date). | D5: Percent
A6: R2 | B6: Reliability | C6: Share of shipments delivered within the transit time quoted on the Rate Card. | D6: Percent
A7: R3 | B7: Reliability | C7: Pickups per week at Helmond. State your daily cut-off time in Details. | D7: Number
A8: R4 | B8: Reliability | C8: Guaranteed capacity in peak months (1.5 times the average month). | D8: Yes/Partial/No
A9: R5 | B9: Reliability | C9: Documented contingency routing for disruptions (Red Sea / Suez, airspace, port congestion). | D9: Yes/Partial/No
A10: R6 | B10: Reliability | C10: Average import clearance time across the nine countries. Per country in Details. | D10: Days
A11: R7 | B11: Reliability | C11: Share of shipments held in customs more than 2 working days over the last 12 months. | D11: Percent
A12: R8 | B12: Reliability | C12: Next-day delivery in the GCC, from Helmond or from regional stock. | D12: Yes/Partial/No
A13: Q1 | B13: Quality | C13: Damage and loss rate over the last 12 months. | D13: Percent
A14: Q2 | B14: Quality | C14: Average claim settlement time. | D14: Days
A15: Q3 | B15: Quality | C15: Liability limit per kg (SDR). Name the convention or terms in Details. | D15: Number
A16: Q4 | B16: Quality | C16: Track and trace with API or EDI integration. | D16: Yes/Partial/No
... A35: H5 | B35: Ease of working | C35: One contact person for all lanes. | D35: Yes/No

Sheet Optional Regional Stock
A1: Optional: regional stock held by you
A2: You may propose to hold FlexiTog stock in the region and deliver from there. FlexiTog then directs supplier deliveries to your warehouse, so replenishment arrives from our suppliers as well as from Helmond.
A4: 1. Proposed stock location(s)
A5: # | B5: Location (city, country) | C5: Type (free zone, bonded, duty-paid) | D5: Receiving hours and booking lead time | E5: Inbound formats accepted (FCL 20/40ft, LCL, pallets, parcels) | F5: Labelling and ASN requirements for supplier deliveries
A6: W1
A7: W2
A8: W3
A11: 2. Lanes served from your stock
A12: Set "Yes" for lanes you would serve from your stock by default. Single shipments can also move to another origin in the yellow columns of the schedules. Volumes, picks and delivery cost below follow the schedules.
A13: Lane | B13: Destination | C13: Orders A | D13: Order lines (picks) A | E13: m3 A | F13: Orders B | G13: Order lines (picks) B | H13: m3 B | I13: Serve from your stock? | J13: Stock location (W1, W2, W3) | K13: Transit days from stock (working days) | L13: Delivery rate per shipment from stock (EUR) | M13: Delivery cost from other origins A | N13: Delivery cost from other origins B | O13: Shipments from your stock A | P13: Shipments from your stock B | Q13: m3 from stock A | R13: m3 from stock B | S13: Picks from stock A | T13: Picks from stock B
A14: L01 | B14: Saudi Arabia | C14: =Volumes!D6 | D14: 308 | E14: =Volumes!F6 | F14: =Volumes!D20 | G14: 721 | H14: =Volumes!F20 | M14: =SUMIFS(SA_Cost,SA_Lane,A14,SA_From,"<>Helmond") | N14: =SUMIFS(SB_Cost,SB_Lane,A14,SB_From,"<>Helmond") | O14: =COUNTIFS(SA_Lane,A14,SA_From,"<>Helmond",SA_From,"<>Other") | P14: =COUNTIFS(SB_Lane,A14,SB_From,"<>Helmond",SB_From,"<>Other") | Q14: =SUMIFS(SA_M3,SA_Lane,A14,SA_From,"<>Helmond",SA_From,"<>Other") | R14: =SUMIFS(SB_M3,SB_Lane,A14,SB_From,"<>Helmond",SB_From,"<>Other") | S14: =IFERROR(ROUND(O14*D14/C14,0),0) | T14: =IFERROR(ROUND(P14*G14/F14,0),0)
A15: L02 | B15: United Arab Emirates | C15: =Volumes!D7 | D15: 160 | E15: =Volumes!F7 | F15: =Volumes!D21 | G15: 373 | H15: =Volumes!F21 | M15: =SUMIFS(SA_Cost,SA_Lane,A15,SA_From,"<>Helmond") | N15: =SUMIFS(SB_Cost,SB_Lane,A15,SB_From,"<>Helmond") | O15: =COUNTIFS(SA_Lane,A15,SA_From,"<>Helmond",SA_From,"<>Other") | P15: =COUNTIFS(SB_Lane,A15,SB_From,"<>Helmond",SB_From,"<>Other") | Q15: =SUMIFS(SA_M3,SA_Lane,A15,SA_From,"<>Helmond",SA_From,"<>Other") | R15: =SUMIFS(SB_M3,SB_Lane,A15,SB_From,"<>Helmond",SB_From,"<>Other") | S15: =IFERROR(ROUND(O15*D15/C15,0),0) | T15: =IFERROR(ROUND(P15*G15/F15,0),0)
A16: L03 | B16: Kuwait | C16: =Volumes!D8 | D16: 64 | E16: =Volumes!F8 | F16: =Volumes!D22 | G16: 155 | H16: =Volumes!F22 | M16: =SUMIFS(SA_Cost,SA_Lane,A16,SA_From,"<>Helmond") | N16: =SUMIFS(SB_Cost,SB_Lane,A16,SB_From,"<>Helmond") | O16: =COUNTIFS(SA_Lane,A16,SA_From,"<>Helmond",SA_From,"<>Other") | P16: =COUNTIFS(SB_Lane,A16,SB_From,"<>Helmond",SB_From,"<>Other") | Q16: =SUMIFS(SA_M3,SA_Lane,A16,SA_From,"<>Helmond",SA_From,"<>Other") | R16: =SUMIFS(SB_M3,SB_Lane,A16,SB_From,"<>Helmond",SB_From,"<>Other") | S16: =IFERROR(ROUND(O16*D16/C16,0),0) | T16: =IFERROR(ROUND(P16*G16/F16,0),0)
A17: L04 | B17: Qatar | C17: =Volumes!D9 | D17: 42 | E17: =Volumes!F9 | F17: =Volumes!D23 | G17: 97 | H17: =Volumes!F23 | M17: =SUMIFS(SA_Cost,SA_Lane,A17,SA_From,"<>Helmond") | N17: =SUMIFS(SB_Cost,SB_Lane,A17,SB_From,"<>Helmond") | O17: =COUNTIFS(SA_Lane,A17,SA_From,"<>Helmond",SA_From,"<>Other") | P17: =COUNTIFS(SB_Lane,A17,SB_From,"<>Helmond",SB_From,"<>Other") | Q17: =SUMIFS(SA_M3,SA_Lane,A17,SA_From,"<>Helmond",SA_From,"<>Other") | R17: =SUMIFS(SB_M3,SB_Lane,A17,SB_From,"<>Helmond",SB_From,"<>Other") | S17: =IFERROR(ROUND(O17*D17/C17,0),0) | T17: =IFERROR(ROUND(P17*G17/F17,0),0)
A18: L05 | B18: Türkiye | C18: =Volumes!D10 | D18: 58 | E18: =Volumes!F10 | F18: =Volumes!D24 | G18: 134 | H18: =Volumes!F24 | M18: =SUMIFS(SA_Cost,SA_Lane,A18,SA_From,"<>Helmond") | N18: =SUMIFS(SB_Cost,SB_Lane,A18,SB_From,"<>Helmond") | O18: =COUNTIFS(SA_Lane,A18,SA_From,"<>Helmond",SA_From,"<>Other") | P18: =COUNTIFS(SB_Lane,A18,SB_From,"<>Helmond",SB_From,"<>Other") | Q18: =SUMIFS(SA_M3,SA_Lane,A18,SA_From,"<>Helmond",SA_From,"<>Other") | R18: =SUMIFS(SB_M3,SB_Lane,A18,SB_From,"<>Helmond",SB_From,"<>Other") | S18: =IFERROR(ROUND(O18*D18/C18,0),0) | T18: =IFERROR(ROUND(P18*G18/F18,0),0)
A19: L06 | B19: Morocco | C19: =Volumes!D11 | D19: 48 | E19: =Volumes!F11 | F19: =Volumes!D25 | G19: 104 | H19: =Volumes!F25 | M19: =SUMIFS(SA_Cost,SA_Lane,A19,SA_From,"<>Helmond") | N19: =SUMIFS(SB_Cost,SB_Lane,A19,SB_From,"<>Helmond") | O19: =COUNTIFS(SA_Lane,A19,SA_From,"<>Helmond",SA_From,"<>Other") | P19: =COUNTIFS(SB_Lane,A19,SB_From,"<>Helmond",SB_From,"<>Other") | Q19: =SUMIFS(SA_M3,SA_Lane,A19,SA_From,"<>Helmond",SA_From,"<>Other") | R19: =SUMIFS(SB_M3,SB_Lane,A19,SB_From,"<>Helmond",SB_From,"<>Other") | S19: =IFERROR(ROUND(O19*D19/C19,0),0) | T19: =IFERROR(ROUND(P19*G19/F19,0),0)
A20: L07 | B20: Algeria | C20: =Volumes!D12 | D20: 128 | E20: =Volumes!F12 | F20: =Volumes!D26 | G20: 288 | H20: =Volumes!F26 | M20: =SUMIFS(SA_Cost,SA_Lane,A20,SA_From,"<>Helmond") | N20: =SUMIFS(SB_Cost,SB_Lane,A20,SB_From,"<>Helmond") | O20: =COUNTIFS(SA_Lane,A20,SA_From,"<>Helmond",SA_From,"<>Other") | P20: =COUNTIFS(SB_Lane,A20,SB_From,"<>Helmond",SB_From,"<>Other") | Q20: =SUMIFS(SA_M3,SA_Lane,A20,SA_From,"<>Helmond",SA_From,"<>Other") | R20: =SUMIFS(SB_M3,SB_Lane,A20,SB_From,"<>Helmond",SB_From,"<>Other") | S20: =IFERROR(ROUND(O20*D20/C20,0),0) | T20: =IFERROR(ROUND(P20*G20/F20,0),0)
A21: L08 | B21: Egypt | C21: =Volumes!D13 | D21: 26 | E21: =Volumes!F13 | F21: =Volumes!D27 | G21: 56 | H21: =Volumes!F27 | M21: =SUMIFS(SA_Cost,SA_Lane,A21,SA_From,"<>Helmond") | N21: =SUMIFS(SB_Cost,SB_Lane,A21,SB_From,"<>Helmond") | O21: =COUNTIFS(SA_Lane,A21,SA_From,"<>Helmond",SA_From,"<>Other") | P21: =COUNTIFS(SB_Lane,A21,SB_From,"<>Helmond",SB_From,"<>Other") | Q21: =SUMIFS(SA_M3,SA_Lane,A21,SA_From,"<>Helmond",SA_From,"<>Other") | R21: =SUMIFS(SB_M3,SB_Lane,A21,SB_From,"<>Helmond",SB_From,"<>Other") | S21: =IFERROR(ROUND(O21*D21/C21,0),0) | T21: =IFERROR(ROUND(P21*G21/F21,0),0)
A22: L09 | B22: Tunisia | C22: =Volumes!D14 | D22: 6 | E22: =Volumes!F14 | F22: =Volumes!D28 | G22: 24 | H22: =Volumes!F28 | M22: =SUMIFS(SA_Cost,SA_Lane,A22,SA_From,"<>Helmond") | N22: =SUMIFS(SB_Cost,SB_Lane,A22,SB_From,"<>Helmond") | O22: =COUNTIFS(SA_Lane,A22,SA_From,"<>Helmond",SA_From,"<>Other") | P22: =COUNTIFS(SB_Lane,A22,SB_From,"<>Helmond",SB_From,"<>Other") | Q22: =SUMIFS(SA_M3,SA_Lane,A22,SA_From,"<>Helmond",SA_From,"<>Other") | R22: =SUMIFS(SB_M3,SB_Lane,A22,SB_From,"<>Helmond",SB_From,"<>Other") | S22: =IFERROR(ROUND(O22*D22/C22,0),0) | T22: =IFERROR(ROUND(P22*G22/F22,0),0)
A23: Total | C23: =SUM(C14:C22) | D23: =SUM(D14:D22) | E23: =SUM(E14:E22) | F23: =SUM(F14:F22) | G23: =SUM(G14:G22) | H23: =SUM(H14:H22) | I23: =COUNTIF(I14:I22,"Yes")&" lanes" | M23: =SUM(M14:M22) | N23: =SUM(N14:N22) | O23: =SUM(O14:O22) | P23: =SUM(P14:P22) | Q23: =SUM(Q14:Q22) | R23: =SUM(R14:R22) | S23: =SUM(S14:S22) | T23: =SUM(T14:T22)
A26: 3. Warehouse volumes for shipments served from your stock
A27: Item | B27: Scenario A | C27: Scenario B | D27: Unit
A28: Average stock pallet positions (indicative) | B28: =ROUNDUP(Q23/52*6/1.5,0) | C28: =ROUNDUP(R23/52*6/1.5,0) | D28: pallets
A29: Inbound pallets per year (supplier and Helmond deliveries) | B29: =ROUND(Q23/1.5,0) | C29: =ROUND(R23/1.5,0) | D29: pallets
A30: Order lines picked per year | B30: =S23 | C30: =T23 | D30: lines
A31: Outbound orders per year | B31: =O23 | C31: =P23 | D31: orders
A33: 4. Your warehouse rates (EUR excl. VAT)
A34: Rate | B34: Your rate | C34: Unit | D34: Annual cost A | E34: Annual cost B
A35: Storage per pallet position per month | C35: per pallet per month | D35: =N(B35)*B28*12 | E35: =N(B35)*C28*12
A36: Inbound receiving per pallet (any origin) | C36: per pallet | D36: =N(B36)*B29 | E36: =N(B36)*C29
A37: Container devanning, 20ft (information only) | C37: per container
A38: Container devanning, 40ft (information only) | C38: per container
A39: Pick per order line | C39: per line | D39: =N(B39)*B30 | E39: =N(B39)*C30
A40: Pack and dispatch per order | C40: per order | D40: =N(B40)*B31 | E40: =N(B40)*C31
A41: Fixed monthly fee (account, WMS, minimum) | C41: per month | D41: =IF(O23=0,0,N(B41)*12) | E41: =IF(P23=0,0,N(B41)*12)
A42: Line haul Helmond to your warehouse per pallet (information only) | C42: per pallet
A43: Deliveries from other origins (from the schedules) | B43: see section 2 | C43: per shipment | D43: =M23 | E43: =N23
A44: Total other-origin cost | D44: =SUM(D35:D43) | E44: =SUM(E35:E43)
A46: 5. Replenishment
A47: • FlexiTog arranges and pays the supplier deliveries into your warehouse. Supplier origins are shared after selection.
A48: • Please describe in section 1 what you need from a supplier delivery: booking lead time, advance shipping notice, pallet type, labels and documents.
A49: • Please state whether your warehouse holds goods duty-unpaid (free zone or bonded) and how you clear each outbound delivery into the destination country.

Sheet Export
A1: key | B1: value | C1: type | D1: description
A2: meta.rfq_version | B2: RFQ-MENA-TR v1.0 | C2: text | D2: Template version
A3: meta.export_rows | B3: 734 | C3: number | D3: Number of key rows below
A4: provider.provider_id | B4: =IF('Provider Profile'!B6="","",'Provider Profile'!B6) | C4: text | D4: Provider ID (filled in by FlexiTog)
A5: provider.name | B5: =IF('Provider Profile'!B7="","",'Provider Profile'!B7) | C5: text | D5: Company name
A6: provider.website | B6: =IF('Provider Profile'!B8="","",'Provider Profile'!B8) | C6: text | D6: Website
A7: provider.contact_name | B7: =IF('Provider Profile'!B9="","",'Provider Profile'!B9) | C7: text | D7: Contact person
A8: provider.contact_phone | B8: =IF('Provider Profile'!B10="","",'Provider Profile'!B10) | C8: text | D8: Contact phone
A9: provider.contact_email | B9: =IF('Provider Profile'!B11="","",'Provider Profile'!B11) | C9: text | D9: Contact e-mail
A10: provider.hq_country | B10: =IF('Provider Profile'!B12="","",'Provider Profile'!B12) | C10: text | D10: Head office country
A11: provider.quote_reference | B11: =IF('Provider Profile'!B13="","",'Provider Profile'!B13) | C11: text | D11: Your quote reference
A12: provider.quote_valid_until | B12: =IF('Provider Profile'!B14="","",'Provider Profile'!B14) | C12: date | D12: Quote valid until
A13: provider.response_date | B13: =IF('Provider Profile'!B15="","",'Provider Profile'!B15) | C13: date | D13: Response date
A14: provider.currency | B14: =IF('Provider Profile'!B16="","",'Provider Profile'!B16) | C14: text | D14: Quote currency
A15: type.freight_forwarder | B15: =IF('Provider Profile'!B21="","",'Provider Profile'!B21) | C15: yesno | D15: Freight forwarder
A16: type.3pl_contract_logistics | B16: =IF('Provider Profile'!B22="","",'Provider Profile'!B22) | C16: yesno | D16: 3PL / contract logistics
A17: type.carrier_own_fleet | B17: =IF('Provider Profile'!B23="","",'Provider Profile'!B23) | C17: yesno | D17: Carrier (own fleet)
A18: type.courier_express | B18: =IF('Provider Profile'!B24="","",'Provider Profile'!B24) | C18: yesno | D18: Courier / express
A19: type.customs_broker | B19: =IF('Provider Profile'!B25="","",'Provider Profile'!B25) | C19: yesno | D19: Customs broker
A20: type.distributor | B20: =IF('Provider Profile'!B26="","",'Provider Profile'!B26) | C20: yesno | D20: Distributor
A21: type.4pl_lead_logistics_provider | B21: =IF('Provider Profile'!B27="","",'Provider Profile'!B27) | C21: yesno | D21: 4PL / lead logistics provider
A22: service.road_ftl | B22: =IF('Provider Profile'!B31="","",'Provider Profile'!B31) | C22: yesno | D22: Road FTL
A23: service.road_groupage_ltl | B23: =IF('Provider Profile'!B32="","",'Provider Profile'!B32) | C23: yesno | D23: Road groupage (LTL)
A24: service.sea_fcl | B24: =IF('Provider Profile'!B33="","",'Provider Profile'!B33) | C24: yesno | D24: Sea FCL
A25: service.sea_lcl | B25: =IF('Provider Profile'!B34="","",'Provider Profile'!B34) | C25: yesno | D25: Sea LCL
A26: service.air_freight | B26: =IF('Provider Profile'!B35="","",'Provider Profile'!B35) | C26: yesno | D26: Air freight
A27: service.express_courier | B27: =IF('Provider Profile'!B36="","",'Provider Profile'!B36) | C27: yesno | D27: Express / courier
A28: service.export_customs_clearance_nl | B28: =IF('Provider Profile'!B37="","",'Provider Profile'!B37) | C28: yesno | D28: Export customs clearance (NL)
A29: service.import_customs_brokerage | B29: =IF('Provider Profile'!B38="","",'Provider Profile'!B38) | C29: yesno | D29: Import customs brokerage
A30: service.ddp_service | B30: =IF('Provider Profile'!B39="","",'Provider Profile'!B39) | C30: yesno | D30: DDP service
A31: service.warehousing | B31: =IF('Provider Profile'!B40="","",'Provider Profile'!B40) | C31: yesno | D31: Warehousing
A32: service.cross_docking | B32: =IF('Provider Profile'!B41="","",'Provider Profile'!B41) | C32: yesno | D32: Cross-docking
A33: service.last_mile_delivery | B33: =IF('Provider Profile'!B42="","",'Provider Profile'!B42) | C33: yesno | D33: Last-mile delivery
... A40: service.co2e_reporting | B40: =IF('Provider Profile'!B49="","",'Provider Profile'!B49) | C40: yesno | D40: CO2e reporting
A41: coverage.L01.presence | B41: =IF('Provider Profile'!D53="","",'Provider Profile'!D53) | C41: text | D41: Saudi Arabia: presence
A42: coverage.L01.partner | B42: =IF('Provider Profile'!E53="","",'Provider Profile'!E53) | C42: text | D42: Saudi Arabia: partner
A43: coverage.L01.import_brokerage | B43: =IF('Provider Profile'!F53="","",'Provider Profile'!F53) | C43: yesno | D43: Saudi Arabia: import brokerage
A44: coverage.L01.ddp | B44: =IF('Provider Profile'!G53="","",'Provider Profile'!G53) | C44: yesno | D44: Saudi Arabia: ddp
A45: coverage.L02.presence | B45: =IF('Provider Profile'!D54="","",'Provider Profile'!D54) | C45: text | D45: United Arab Emirates: presence
A46: coverage.L02.partner | B46: =IF('Provider Profile'!E54="","",'Provider Profile'!E54) | C46: text | D46: United Arab Emirates: partner
A47: coverage.L02.import_brokerage | B47: =IF('Provider Profile'!F54="","",'Provider Profile'!F54) | C47: yesno | D47: United Arab Emirates: import brokerage
A48: coverage.L02.ddp | B48: =IF('Provider Profile'!G54="","",'Provider Profile'!G54) | C48: yesno | D48: United Arab Emirates: ddp
A49: coverage.L03.presence | B49: =IF('Provider Profile'!D55="","",'Provider Profile'!D55) | C49: text | D49: Kuwait: presence
A50: coverage.L03.partner | B50: =IF('Provider Profile'!E55="","",'Provider Profile'!E55) | C50: text | D50: Kuwait: partner
A51: coverage.L03.import_brokerage | B51: =IF('Provider Profile'!F55="","",'Provider Profile'!F55) | C51: yesno | D51: Kuwait: import brokerage
A52: coverage.L03.ddp | B52: =IF('Provider Profile'!G55="","",'Provider Profile'!G55) | C52: yesno | D52: Kuwait: ddp
A53: coverage.L04.presence | B53: =IF('Provider Profile'!D56="","",'Provider Profile'!D56) | C53: text | D53: Qatar: presence
A54: coverage.L04.partner | B54: =IF('Provider Profile'!E56="","",'Provider Profile'!E56) | C54: text | D54: Qatar: partner
A55: coverage.L04.import_brokerage | B55: =IF('Provider Profile'!F56="","",'Provider Profile'!F56) | C55: yesno | D55: Qatar: import brokerage
A56: coverage.L04.ddp | B56: =IF('Provider Profile'!G56="","",'Provider Profile'!G56) | C56: yesno | D56: Qatar: ddp
A57: coverage.L05.presence | B57: =IF('Provider Profile'!D57="","",'Provider Profile'!D57) | C57: text | D57: Türkiye: presence
A58: coverage.L05.partner | B58: =IF('Provider Profile'!E57="","",'Provider Profile'!E57) | C58: text | D58: Türkiye: partner
A59: coverage.L05.import_brokerage | B59: =IF('Provider Profile'!F57="","",'Provider Profile'!F57) | C59: yesno | D59: Türkiye: import brokerage
A60: coverage.L05.ddp | B60: =IF('Provider Profile'!G57="","",'Provider Profile'!G57) | C60: yesno | D60: Türkiye: ddp
A61: coverage.L06.presence | B61: =IF('Provider Profile'!D58="","",'Provider Profile'!D58) | C61: text | D61: Morocco: presence
A62: coverage.L06.partner | B62: =IF('Provider Profile'!E58="","",'Provider Profile'!E58) | C62: text | D62: Morocco: partner
A63: coverage.L06.import_brokerage | B63: =IF('Provider Profile'!F58="","",'Provider Profile'!F58) | C63: yesno | D63: Morocco: import brokerage
A64: coverage.L06.ddp | B64: =IF('Provider Profile'!G58="","",'Provider Profile'!G58) | C64: yesno | D64: Morocco: ddp
A65: coverage.L07.presence | B65: =IF('Provider Profile'!D59="","",'Provider Profile'!D59) | C65: text | D65: Algeria: presence
A66: coverage.L07.partner | B66: =IF('Provider Profile'!E59="","",'Provider Profile'!E59) | C66: text | D66: Algeria: partner
A67: coverage.L07.import_brokerage | B67: =IF('Provider Profile'!F59="","",'Provider Profile'!F59) | C67: yesno | D67: Algeria: import brokerage
A68: coverage.L07.ddp | B68: =IF('Provider Profile'!G59="","",'Provider Profile'!G59) | C68: yesno | D68: Algeria: ddp
A69: coverage.L08.presence | B69: =IF('Provider Profile'!D60="","",'Provider Profile'!D60) | C69: text | D69: Egypt: presence
A70: coverage.L08.partner | B70: =IF('Provider Profile'!E60="","",'Provider Profile'!E60) | C70: text | D70: Egypt: partner
A71: coverage.L08.import_brokerage | B71: =IF('Provider Profile'!F60="","",'Provider Profile'!F60) | C71: yesno | D71: Egypt: import brokerage
A72: coverage.L08.ddp | B72: =IF('Provider Profile'!G60="","",'Provider Profile'!G60) | C72: yesno | D72: Egypt: ddp
A73: coverage.L09.presence | B73: =IF('Provider Profile'!D61="","",'Provider Profile'!D61) | C73: text | D73: Tunisia: presence
A74: coverage.L09.partner | B74: =IF('Provider Profile'!E61="","",'Provider Profile'!E61) | C74: text | D74: Tunisia: partner
A75: coverage.L09.import_brokerage | B75: =IF('Provider Profile'!F61="","",'Provider Profile'!F61) | C75: yesno | D75: Tunisia: import brokerage
A76: coverage.L09.ddp | B76: =IF('Provider Profile'!G61="","",'Provider Profile'!G61) | C76: yesno | D76: Tunisia: ddp
A77: region.turkiye | B77: =IF(AND('Provider Profile'!D57<>"",'Provider Profile'!D57<>"Not served")*1>0,"Yes","No") | C77: yesno | D77: Region covered: turkiye
A78: region.north_africa | B78: =IF(AND('Provider Profile'!D58<>"",'Provider Profile'!D58<>"Not served")*1+AND('Provider Profile'!D59<>"",'Provider Profile'!D59<>"Not served")*1+AND('Provider Profile'!D60<>"",'Provider Profile'!D60<>"Not served")*1+AND('Provider Profile'!D61<>"",'Provider Profile'!D61<>"Not served")*1>0,"Yes","No") | C78: yesno | D78: Region covered: north_africa
A79: region.gulf_gcc | B79: =IF(AND('Provider Profile'!D53<>"",'Provider Profile'!D53<>"Not served")*1+AND('Provider Profile'!D54<>"",'Provider Profile'!D54<>"Not served")*1+AND('Provider Profile'!D55<>"",'Provider Profile'!D55<>"Not served")*1+AND('Provider Profile'!D56<>"",'Provider Profile'!D56<>"Not served")*1>0,"Yes","No") | C79: yesno | D79: Region covered: gulf_gcc
A80: cert.iso_9001 | B80: =IF('Provider Profile'!B65="","",'Provider Profile'!B65) | C80: yesno | D80: ISO 9001
A81: cert.iso_14001 | B81: =IF('Provider Profile'!B66="","",'Provider Profile'!B66) | C81: yesno | D81: ISO 14001
A82: cert.iso_45001 | B82: =IF('Provider Profile'!B67="","",'Provider Profile'!B67) | C82: yesno | D82: ISO 45001
A83: cert.aeo_authorised_economic_operator | B83: =IF('Provider Profile'!B68="","",'Provider Profile'!B68) | C83: yesno | D83: AEO (authorised economic operator)
A84: cert.tapa | B84: =IF('Provider Profile'!B69="","",'Provider Profile'!B69) | C84: yesno | D84: TAPA
A85: cert.iata_cargo_agent | B85: =IF('Provider Profile'!B70="","",'Provider Profile'!B70) | C85: yesno | D85: IATA cargo agent
A86: cert.other | B86: =IF('Provider Profile'!B71="","",'Provider Profile'!B71) | C86: text | D86: Other certifications
A87: kpi.R1 | B87: =IF('Reliability & Quality'!E5="","",'Reliability & Quality'!E5) | C87: percent | D87: On-time delivery rate on these lanes over the last 12 months (on or before the promised date).
A88: kpi.R1.evidence | B88: =IF('Reliability & Quality'!G5="","",'Reliability & Quality'!G5) | C88: yesno | D88: R1 evidence available
A89: kpi.R1.details | B89: =IF('Reliability & Quality'!F5="","",'Reliability & Quality'!F5) | C89: text | D89: R1 details
A90: kpi.R2 | B90: =IF('Reliability & Quality'!E6="","",'Reliability & Quality'!E6) | C90: percent | D90: Share of shipments delivered within the transit time quoted on the Rate Card.
A91: kpi.R2.evidence | B91: =IF('Reliability & Quality'!G6="","",'Reliability & Quality'!G6) | C91: yesno | D91: R2 evidence available
A92: kpi.R2.details | B92: =IF('Reliability & Quality'!F6="","",'Reliability & Quality'!F6) | C92: text | D92: R2 details
A93: kpi.R3 | B93: =IF('Reliability & Quality'!E7="","",'Reliability & Quality'!E7) | C93: number | D93: Pickups per week at Helmond. State your daily cut-off time in Details.
A94: kpi.R3.evidence | B94: =IF('Reliability & Quality'!G7="","",'Reliability & Quality'!G7) | C94: yesno | D94: R3 evidence available
A95: kpi.R3.details | B95: =IF('Reliability & Quality'!F7="","",'Reliability & Quality'!F7) | C95: text | D95: R3 details
A96: kpi.R4 | B96: =IF('Reliability & Quality'!E8="","",'Reliability & Quality'!E8) | C96: ypn | D96: Guaranteed capacity in peak months (1.5 times the average month).
A97: kpi.R4.evidence | B97: =IF('Reliability & Quality'!G8="","",'Reliability & Quality'!G8) | C97: yesno | D97: R4 evidence available
A98: kpi.R4.details | B98: =IF('Reliability & Quality'!F8="","",'Reliability & Quality'!F8) | C98: text | D98: R4 details
A99: kpi.R5 | B99: =IF('Reliability & Quality'!E9="","",'Reliability & Quality'!E9) | C99: ypn | D99: Documented contingency routing for disruptions (Red Sea / Suez, airspace, port congestion).
A100: kpi.R5.evidence | B100: =IF('Reliability & Quality'!G9="","",'Reliability & Quality'!G9) | C100: yesno | D100: R5 evidence available
A101: kpi.R5.details | B101: =IF('Reliability & Quality'!F9="","",'Reliability & Quality'!F9) | C101: text | D101: R5 details
A102: kpi.R6 | B102: =IF('Reliability & Quality'!E10="","",'Reliability & Quality'!E10) | C102: number | D102: Average import clearance time across the nine countries. Per country in Details.
A103: kpi.R6.evidence | B103: =IF('Reliability & Quality'!G10="","",'Reliability & Quality'!G10) | C103: yesno | D103: R6 evidence available
A104: kpi.R6.details | B104: =IF('Reliability & Quality'!F10="","",'Reliability & Quality'!F10) | C104: text | D104: R6 details
A105: kpi.R7 | B105: =IF('Reliability & Quality'!E11="","",'Reliability & Quality'!E11) | C105: percent | D105: Share of shipments held in customs more than 2 working days over the last 12 months.
A106: kpi.R7.evidence | B106: =IF('Reliability & Quality'!G11="","",'Reliability & Quality'!G11) | C106: yesno | D106: R7 evidence available
...
